Workbook

Sheet NHẬP ĐƠN
A1: Tên khách | B1: Tên Sp | C1: Mã SP | D1: SIZE | E1: COLOR | F1: Số lượng | G1: Giá sp | H1: NGÀY OD | I1: TRẠNG THÁI | J1: Link fb
A2: Ngọc Thuý Trần | B2: Phông trơn ngắn tay | C2: 8886 | D2: S | E2: TRẮNG | F2: 1 | G2: 1090 | H2: 46085 | I2: Đã gửi | J2: https://www.facebook.com/share/1QYxbzMHD7/?mibextid=wwXIfr
A3: Ngọc Thuý Trần | B3: Phông trơn ngắn tay | C3: 8886 | D3: S | E3: HỒNG | F3: 1 | G3: 1090 | H3: 46085 | I3: Đã gửi
A4: Uyên Lê | B4: Phông trơn ngắn tay | C4: 8886 | D4: S | E4: ĐEN | F4: 1 | G4: 1090 | H4: 46085 | I4: Đã gửi
A5: Hà Giang | B5: Phông trơn ngắn tay | C5: 8886 | D5: S | E5: ĐEN | F5: 1 | G5: 1090 | H5: 46085 | I5: Đã gửi
A6: Hà Giang | B6: Phông trơn ngắn tay | C6: 8886 | D6: S | E6: TRẮNG | F6: 1 | G6: 1090 | H6: 46085 | I6: Đã gửi
A7: Hà Giang | B7: Phông trơn ngắn tay | C7: 8886 | D7: S | E7: XÁM ĐẬM | F7: 1 | G7: 1090 | H7: 46085 | I7: Đã gửi
A8: Bùi Thị Ngọc Hân | B8: Phông trơn ngắn tay | C8: 8886 | D8: M | E8: XÁM | F8: 1 | G8: 1090 | H8: 46085 | I8: Đã xoá
A9: Trang Mẩu | B9: Phông trơn ngắn tay | C9: 8886 | D9: M | E9: NÂU | F9: 1 | G9: 1090 | H9: 46085 | I9: Đã gửi
A10: Trang Mẩu | B10: Phông trơn ngắn tay | C10: 8886 | D10: M | E10: TRẮNG | F10: 1 | G10: 1090 | H10: 46085 | I10: Đã gửi
A11: Trang Mẩu | B11: Phông trơn ngắn tay | C11: 8886 | D11: M | E11: ĐEN | F11: 1 | G11: 1090 | H11: 46085 | I11: Đã gửi
A12: Trang Mẩu | B12: Phông trơn ngắn tay | C12: 8886 | D12: M | E12: ĐỎ | F12: 1 | G12: 1090 | H12: 46085 | I12: Đã gửi
A13: Nguyễn Phương Vy | B13: Phông trơn ngắn tay | C13: 8886 | D13: M | E13: ĐEN | F13: 1 | G13: 1090 | H13: 46085 | I13: Đã gửi
A14: Nguyễn Phương Vy | B14: Phông trơn ngắn tay | C14: 8886 | D14: M | E14: TRẮNG | F14: 1 | G14: 1090 | H14: 46085 | I14: Đã gửi
... A41: Ng Hà Phương | B41: Phông trơn ngắn tay | C41: 8886 | D41: S | E41: XÁM | F41: 1 | G41: 1090 | H41: 46085 | I41: Đã gửi
A42: Nguyễn Hương | B42: Phông trơn ngắn tay | C42: 8886 | D42: S | E42: TRẮNG | F42: 1 | G42: 1090 | H42: 46085 | I42: Đã gửi | J42: https://www.facebook.com/share/17v6iyn5xx/?mibextid=wwXIfr
A43: Hương Cherry | B43: Polo lông thỏ | C43: 7859 | D43: FZ | E43: BE | F43: 1 | G43: 2100 | H43: 46085 | I43: Đã gửi
A44: Hoàng Yếnn | B44: Polo lông thỏ | C44: 7859 | D44: FZ | E44: HỒNG | F44: 1 | G44: 2100 | H44: 46085 | I44: Đã gửi
A45: Lộc Tâm | B45: Polo lông thỏ | C45: 7859 | D45: FZ | E45: HỒNG | F45: 1 | G45: 2100 | H45: 46085 | I45: Đã gửi
A46: Ngọc Hà | B46: Polo lông thỏ | C46: 7859 | D46: FZ | E46: HỒNG | F46: 1 | G46: 2100 | H46: 46085 | I46: Đã gửi
A47: Phương Nga | B47: Polo lông thỏ | C47: 7859 | D47: FZ | E47: BE | F47: 1 | G47: 2100 | H47: 46085 | I47: Đã gửi
A48: Lụa Mỹ | B48: Polo lông thỏ | C48: 7859 | D48: FZ | E48: HỒNG | F48: 1 | G48: 2100 | H48: 46085 | I48: Đã gửi
A49: Trần Thị Thu | B49: Polo lông thỏ | C49: 7859 | D49: FZ | E49: BE | F49: 1 | G49: 2100 | H49: 46085 | I49: Đã gửi
A50: Phạm Hoàn | B50: Polo lông thỏ | C50: 7859 | D50: FZ | E50: BE | F50: 1 | G50: 2100 | H50: 46085 | I50: Đã gửi
A51: Hà Oanh | B51: Polo lông thỏ | C51: 7859 | D51: FZ | E51: HỒNG | F51: 1 | G51: 2100 | H51: 46085 | I51: Đã gửi
A52: Lê Thuỳ Dương | B52: Polo lông thỏ | C52: 7859 | D52: FZ | E52: BE | F52: 1 | G52: 2100 | H52: 46085 | I52: Đã gửi
A53: Lê Thuỳ Dương | B53: Polo lông thỏ | C53: 7859 | D53: FZ | E53: HỒNG | F53: 1 | G53: 2100 | H53: 46085 | I53: Đã gửi
A54: Thuỳ Trang | B54: Polo lông thỏ | C54: 7859 | D54: FZ | E54: HỒNG | F54: 1 | G54: 2100 | H54: 46085 | I54: Đã gửi
A55: Tâm Tâm | B55: Jean xanh đậm | C55: 8865 | D55: M | E55: XANH THAN | F55: 1 | G55: 2500 | H55: 46085 | I55: Đã gửi | J55: https://www.facebook.com/share/1GzVVq96Za/?mibextid=wwXIfr
A56: Trang Minn | B56: Jean xanh đậm | C56: 8865 | D56: M | E56: XANH THAN | F56: 1 | G56: 2500 | H56: 46085 | I56: Đã gửi
A57: Phan Nhung | B57: Jean xanh đậm | C57: 8865 | D57: M | E57: XANH THAN | F57: 1 | G57: 2500 | H57: 46085 | I57: Đã gửi
A58: GiangHoang Vu | B58: Jean xanh đậm | C58: 8865 | D58: M | E58: XANH THAN | F58: 1 | G58: 2500 | H58: 46085 | I58: Đã gửi
A59: Thuỳ Trang | B59: Jean xanh đậm | C59: 8865 | D59: S | E59: XANH THAN | F59: 1 | G59: 2500 | H59: 46085 | I59: Đã gửi
A60: Trang Đoàn | B60: Jean xanh đậm | C60: 8865 | D60: M | E60: XANH THAN | F60: 1 | G60: 2500 | H60: 46085 | I60: Đã gửi
A61: Hoàng Nhật Mai | B61: Jean xanh đậm | C61: 8865 | D61: S | E61: XANH THAN | F61: 1 | G61: 2500 | H61: 46085 | I61: Đã gửi
A62: Hong Doan | B62: Jean xanh đậm | C62: 8865 | D62: S | E62: XANH THAN | F62: 2 | G62: 2500 | H62: 46085 | I62: Đã gửi
A63: Cao The | B63: Jean xanh đậm | C63: 8865 | D63: S | E63: XANH THAN | F63: 1 | G63: 2500 | H63: 46085 | I63: Đã gửi | J63: https://www.facebook.com/share/18RcCZWJ6a/?mibextid=wwXIfr
A64: Ngọc Hiền | B64: Jean xanh đậm | C64: 8865 | D64: S | E64: XANH THAN | F64: 1 | G64: 2500 | H64: 46085 | I64: Đã gửi
A65: Huyền Trang | B65: Jean xanh đậm | C65: 8865 | D65: M | E65: XANH THAN | F65: 1 | G65: 2500 | H65: 46085 | I65: Đã gửi | J65: https://www.facebook.com/share/1EJQU4nE6g/?mibextid=wwXIfr
A66: Li Ly | B66: Jean xanh đậm | C66: 8865 | D66: M | E66: XANH THAN | F66: 1 | G66: 2500 | H66: 46085 | I66: Đã gửi
A67: Thảo Huyền | B67: Jean xanh đậm | C67: 8865 | D67: S | E67: XANH THAN | F67: 1 | G67: 2500 | H67: 46085 | I67: Đã gửi
A68: Huyền Thỏ | B68: Jean xanh đậm | C68: 8865 | D68: M | E68: XANH THAN | F68: 1 | G68: 2500 | H68: 46085 | I68: Đã gửi
A69: Trà Mei | B69: Jean xanh đậm | C69: 8865 | D69: L | E69: XANH THAN | F69: 1 | G69: 2500 | H69: 46085 | I69: Đã gửi
A70: Vân Trang | B70: Jean xanh đậm | C70: 8865 | D70: S | E70: XANH THAN | F70: 1 | G70: 2500 | H70: 46085 | I70: Đã gửi
A71: Nguyễn Hoàng | B71: Jean xanh đậm | C71: 8865 | D71: S | E71: XANH THAN | F71: 1 | G71: 2500 | H71: 46085 | I71: Đã gửi
A72: Sami Sami | B72: Jean xanh đậm | C72: 8865 | D72: S | E72: XANH THAN | F72: 1 | G72: 2500 | H72: 46085 | I72: Đã gửi
A73: Yến Nhi | B73: Jean xanh đậm | C73: 8865 | D73: S | E73: XANH THAN | F73: 1 | G73: 2500 | H73: 46085 | I73: Đã gửi
A74: Nhung Đỗ | B74: Jean xanh đậm | C74: 8865 | D74: M | E74: XANH THAN | F74: 1 | G74: 2500 | H74: 46085 | I74: Đã gửi | J74: https://www.facebook.com/share/1D4ngbZHBR/?mibextid=wwXIfr
A75: Hà Nhi | B75: Váy jean nâu | C75: 7739 | D75: S | E75: NÂU | F75: 1 | G75: 1800 | H75: 46085 | I75: Đã gửi
A76: Hương Nhật | B76: Váy jean nâu | C76: 7739 | D76: M | E76: NÂU | F76: 1 | G76: 1800 | H76: 46085 | I76: Đã gửi
A77: Anh Kieu Bao | B77: Váy jean nâu | C77: 7739 | D77: M | E77: NÂU | F77: 1 | G77: 1800 | H77: 46085 | I77: Đã gửi
A78: Phạm Hoàn | B78: Váy jean nâu | C78: 7739 | D78: S | E78: NÂU | F78: 1 | G78: 1800 | H78: 46085 | I78: Đã gửi
A79: Trangg Tũnn | B79: Váy jean nâu | C79: 7739 | D79: S | E79: NÂU | F79: 1 | G79: 1800 | H79: 46085 | I79: Đã gửi
A80: Trangg Tũnn | B80: Váy jean nâu | C80: 7739 | D80: S | E80: ĐEN | F80: 1 | G80: 1800 | H80: 46085 | I80: Đã xoá
A81: Ngọc Dung | B81: Váy jean nâu | C81: 7739 | D81: M | E81: NÂU | F81: 1 | G81: 1800 | H81: 46085 | I81: Đã gửi
A82: Nguyen Yen Nhi | B82: Quần jean đùi xanh | C82: 7322 | D82: S | E82: XANH THAN | F82: 1 | G82: 2100 | H82: 46085 | I82: Đã gửi
A83: Lộc Tâm | B83: Quần jean đùi xanh | C83: 7322 | D83: S | E83: XANH THAN | F83: 1 | G83: 2100 | H83: 46085 | I83: Đã gửi
A84: Khánh Hoà | B84: Quần jean đùi xanh | C84: 7322 | D84: S | E84: XANH THAN | F84: 1 | G84: 2100 | H84: 46085 | I84: Đã gửi
A85: Hồng Nhi | B85: Quần jean đùi xanh | C85: 7322 | D85: L | E85: XANH THAN | F85: 1 | G85: 2100 | H85: 46085 | I85: Đã gửi
A86: Ngọc Hà | B86: Quần jean đùi xanh | C86: 7322 | D86: M | E86: XANH THAN | F86: 1 | G86: 2100 | H86: 46085 | I86: Đã gửi
... A91: Ty Ty | B91: Quần jean đùi xanh | C91: 7322 | D91: L | E91: XANH THAN | F91: 1 | G91: 2100 | H91: 46085 | I91: Đã gửi
A92: Phạm Thuý | B92: Jean lửng xanh đậm | C92: 8748 | D92: S | E92: XANH THAN | F92: 1 | G92: 1800 | H92: 46085 | I92: Đã gửi | J92: https://www.facebook.com/share/17GC4jqgbw/?mibextid=wwXIfr
A93: Chanh Lê | B93: Jean lửng xanh đậm | C93: 8748 | D93: S | E93: XANH THAN | F93: 1 | G93: 1800 | H93: 46085 | I93: Đã gửi
A94: Hương Nhật | B94: Jean lửng xanh đậm | C94: 8748 | D94: M | E94: XANH THAN | F94: 1 | G94: 1800 | H94: 46085 | I94: Đã gửi
A95: Hoàng Yếnn | B95: Jean lửng xanh đậm | C95: 8748 | D95: S | E95: XANH THAN | F95: 1 | G95: 1800 | H95: 46085 | I95: Đã gửi
A96: Thanh Tiền | B96: Jean lửng xanh đậm | C96: 8748 | D96: M | E96: XANH THAN | F96: 1 | G96: 1800 | H96: 46085 | I96: Đã gửi
A97: Bùi Thu Hiền | B97: Jean lửng xanh đậm | C97: 8748 | D97: S | E97: XANH THAN | F97: 1 | G97: 1800 | H97: 46085 | I97: Đã gửi
A98: Thuận Lê | B98: Jean lửng xanh đậm | C98: 8748 | D98: M | E98: XANH THAN | F98: 1 | G98: 1800 | H98: 46085 | I98: Đã gửi
A99: Hạ Trang | B99: Jean lửng xanh đậm | C99: 8748 | D99: S | E99: XANH THAN | F99: 1 | G99: 1800 | H99: 46085 | I99: Đã gửi
A100: Huyền Nga | B100: Jean lửng xanh đậm | C100: 8748 | D100: S | E100: XANH THAN | F100: 1 | G100: 1800 | H100: 46085 | I100: Đã gửi
A101: Lộc Tâm | B101: Jean lửng xanh đậm | C101: 8748 | D101: S | E101: XANH THAN | F101: 1 | G101: 1800 | H101: 46085 | I101: Đã gửi
A102: Thư Thư | B102: Jean lửng xanh đậm | C102: 8748 | D102: L | E102: XANH THAN | F102: 1 | G102: 1800 | H102: 46085 | I102: Đã gửi
A103: Vũ Tuyền | B103: Jean lửng xanh đậm | C103: 8748 | D103: M | E103: XANH THAN | F103: 1 | G103: 1800 | H103: 46085 | I103: Đã gửi
A104: Hồ Thị Hải | B104: Jean lửng xanh đậm | C104: 8748 | D104: S | E104: XANH THAN | F104: 1 | G104: 1800 | H104: 46085 | I104: Đã gửi
... A116: Thiên An | B116: Jean lửng xanh đậm | C116: 8748 | D116: S | E116: XANH THAN | F116: 1 | G116: 1800 | H116: 46085 | I116: Đã gửi
A117: Nhung Kul's | B117: Jean lửng xanh đậm | C117: 8748 | D117: M | E117: XANH THAN | F117: 1 | G117: 1800 | H117: 46085 | I117: Đã gửi | J117: https://www.facebook.com/share/1GJK8WCYwa/?mibextid=wwXIfr
A118: Thiên Lý | B118: Jean lửng xanh đậm | C118: 8748 | D118: M | E118: XANH THAN | F118: 1 | G118: 1800 | H118: 46085 | I118: Đã gửi
A119: Hoàng Nhật Mai | B119: Jean lửng xanh đậm | C119: 8748 | D119: S | E119: XANH THAN | F119: 1 | G119: 1800 | H119: 46085 | I119: Đã gửi
A120: Trang Trần | B120: Jean lửng xanh đậm | C120: 8748 | D120: M | E120: XANH THAN | F120: 1 | G120: 1800 | H120: 46085 | I120: Đã gửi
A121: Thu Hường Nguyễn | B121: Jean lửng xanh đậm | C121: 8748 | D121: S | E121: XANH THAN | F121: 1 | G121: 1800 | H121: 46085 | I121: Đã gửi
A122: Duong Cam Tu | B122: Jean lửng xanh đậm | C122: 8748 | D122: S | E122: XANH THAN | F122: 1 | G122: 1800 | H122: 46085 | I122: Đã gửi
A123: Đỗ Duyên | B123: Jean lửng xanh đậm | C123: 8748 | D123: M | E123: XANH THAN | F123: 1 | G123: 1800 | H123: 46085 | I123: Đã gửi
A124: Ngọc Hiền | B124: Jean lửng xanh đậm | C124: 8748 | D124: S | E124: XANH THAN | F124: 1 | G124: 1800 | H124: 46085 | I124: Đã gửi
A125: Loan Trần | B125: Jean lửng xanh đậm | C125: 8748 | D125: M | E125: XANH THAN | F125: 1 | G125: 1800 | H125: 46085 | I125: Đã gửi
A126: Phương Nga | B126: Jean lửng xanh đậm | C126: 8748 | D126: M | E126: XANH THAN | F126: 1 | G126: 1800 | H126: 46085 | I126: Đã gửi
A127: Ngọc Hà | B127: Jean lửng xanh đậm | C127: 8748 | D127: M | E127: XANH THAN | F127: 1 | G127: 1800 | H127: 46085 | I127: Đã gửi
A128: Lê Hải Yến | B128: Jean lửng xanh đậm | C128: 8748 | D128: M | E128: XANH THAN | F128: 1 | G128: 1800 | H128: 46085 | I128: Đã gửi
A129: Linh Nguyen | B129: Jean lửng xanh đậm | C129: 8748 | D129: S | E129: XANH THAN | F129: 1 | G129: 1800 | H129: 46085 | I129: Đã gửi
... A133: Thuý Hạnh | B133: Jean lửng xanh đậm | C133: 8748 | D133: S | E133: XANH THAN | F133: 1 | G133: 1800 | H133: 46085 | I133: Đã gửi
A134: Hoàng Huyền | B134: Jean lửng xanh đậm | C134: 8748 | D134: S | E134: XANH THAN | F134: 1 | G134: 1800 | H134: 46085 | I134: Đã gửi | J134: https://www.facebook.com/share/1CaXKMnryV/?mibextid=wwXIfr
A135: chup bi Kiều | B135: Jean lửng xanh đậm | C135: 8748 | D135: L | E135: XANH THAN | F135: 1 | G135: 1800 | H135: 46085 | I135: Đã xoá
A136: Quỳnh Như | B136: Jean lửng xanh đậm | C136: 8748 | D136: S | E136: XANH THAN | F136: 1 | G136: 1800 | H136: 46085 | I136: Đã gửi
A137: Khánh Nhung | B137: Jean lửng xanh đậm | C137: 8748 | D137: M | E137: XANH THAN | F137: 1 | G137: 1800 | H137: 46085 | I137: Đã gửi
A138: Li Ly | B138: Jean lửng xanh đậm | C138: 8748 | D138: M | E138: XANH THAN | F138: 1 | G138: 1800 | H138: 46085 | I138: Đã gửi
A139: Nguyễn Thu Thảo | B139: Jean lửng xanh đậm | C139: 8748 | D139: S | E139: XANH THAN | F139: 1 | G139: 1800 | H139: 46085 | I139: Đã gửi
A140: Hằng Min's | B140: Jean lửng xanh đậm | C140: 8748 | D140: S | E140: XANH THAN | F140: 1 | G140: 1800 | H140: 46085 | I140: Đã gửi
A141: Sáu Nguyễn | B141: Jean lửng xanh đậm | C141: 8748 | D141: S | E141: XANH THAN | F141: 1 | G141: 1800 | H141: 46085 | I141: Đã gửi | J141: Page
A142: Hà Trần | B142: Jean lửng xanh đậm | C142: 8748 | D142: M | E142: XANH THAN | F142: 1 | G142: 1800 | H142: 46085 | I142: Đã gửi
A143: Diễm Pưngg | B143: Jean lửng xanh đậm | C143: 8748 | D143: L | E143: XANH THAN | F143: 1 | G143: 1800 | H143: 46085 | I143: Đã gửi
A144: Lộc Tâm | B144: Polo len tăm | C144: 8646 | D144: FZ | E144: BE | F144: 1 | G144: 1550 | H144: 46085 | I144: Đã gửi
...

Sheet Trang tính8

Sheet HÀNG DƯ
A1: Mã SP | B1: Size | C1: Color | D1: SL dư | E1: Trạng thái | F1: Ngày tạo
A2: 8876 | B2: M | C2: ĐEN | D2: 5 | E2: Về kho | F2: 46144
A3: 8876 | B3: S | C3: ĐEN | D3: 2 | E3: Về kho | F3: 46153
A4: 3225 | B4: M | C4: XANH THAN | D4: 1 | E4: Về kho | F4: 46153
A5: 9094 | B5: S | C5: XANH THAN | D5: 1 | E5: Về kho | F5: 46153
A6: 9094 | B6: S | C6: XÁM | D6: 1 | E6: Về kho | F6: 46153
A7: 7957 | B7: M | C7: XÁM | D7: 1 | E7: Về kho | F7: 46153
A8: M005 | B8: 39 | C8: NÂU | D8: 1 | E8: Về kho | F8: 46153
A9: M001 | B9: 35 | C9: ĐEN | D9: 1 | E9: Về kho | F9: 46153
A10: M001 | B10: 40 | C10: ĐEN | D10: 1 | E10: Về kho | F10: 46153
A11: M001 | B11: 39 | C11: ĐEN | D11: 1 | E11: Về kho | F11: 46153
A12: 6612 | B12: FZ | C12: 5 | D12: 1 | E12: Về kho | F12: 46177
A13: 1639 | B13: S | C13: CAM | D13: 1 | E13: Về kho | F13: 46176
A14: 1639 | B14: M | C14: CAM | D14: 1 | E14: Về kho | F14: 46176
A15: M007 | B15: FZ | C15: NHUNGDO | D15: 1 | E15: Về kho | F15: 46176
A16: 9094 | B16: M | C16: HỒNG | D16: 2 | E16: Về kho | F16: 46176
A17: 5007 | B17: M | C17: ĐEN | D17: 1 | E17: Chờ hàng | F17: 46178
A18: P230MTX362 | B18: 36 | C18: NÂU | D18: 2 | E18: Về kho | F18: 46178
A19: CK98118 | B19: S | C19: ĐEN | D19: 3 | E19: Về kho | F19: 46183
A20: BRA2 | B20: M | C20: TRẮNG | D20: 1 | E20: Về kho | F20: 46182
A21: M009 | B21: XL | C21: ĐEN | D21: 1 | E21: Về kho | F21: 46182
A22: M009 | B22: XL | C22: XÁM | D22: 1 | E22: Về kho | F22: 46182
A23: M014 | B23: FZ | C23: TÍM | D23: 1 | E23: Về kho | F23: 46182
A24: M012 | B24: FZ | C24: TÍM | D24: 2 | E24: Về kho | F24: 46182
A25: M012 | B25: FZ | C25: VÀNG | D25: 2 | E25: Về kho | F25: 46182
A26: 9425 | B26: M | C26: XANH THAN | D26: 2 | E26: Về kho | F26: 46182
A27: 5709 | B27: S | C27: XANH NHẠT | D27: 2 | E27: Về kho | F27: 46183
A28: 9031 | B28: M | C28: TRẮNG | D28: 1 | E28: Chờ hàng | F28: 46184
A29: 5670 | B29: S | C29: TRẮNG | D29: 2 | E29: Về kho | F29: 46184

Sheet LỊCH SỬ
A1: Tên khách | B1: Tên Sp | C1: Mã SP | D1: SIZE | E1: COLOR | F1: Số lượng | G1: Giá sp | H1: NGÀY OD | I1: TRẠNG THÁI | J1: Link fb
A2: Thuỳ Trangg | B2: Giày howell | C2: M001 | D2: 37 | E2: ĐEN | F2: 1 | G2: 1990 | H2: 46100 | I2: Đã gửi
A3: Thảo Thỏ | B3: Giày howell | C3: M001 | D3: 36 | E3: BE | F3: 1 | G3: 1990 | H3: 46100 | I3: Đã gửi
A4: Hoàng Yến | B4: Giày howell | C4: M001 | D4: 35 | E4: ĐEN | F4: 1 | G4: 1990 | H4: 46104 | I4: Đã gửi
A5: Hoàng Yến | B5: Giày howell | C5: M001 | D5: 35 | E5: ĐEN | F5: 1 | G5: 1990 | H5: 46104 | I5: Đã gửi
A6: Hoàng Yến | B6: Giày howell | C6: M001 | D6: 35 | E6: ĐEN | F6: 1 | G6: 1990 | H6: 46104 | I6: Đã gửi
A7: Hoàng Yến | B7: Giày howell | C7: M001 | D7: 35 | E7: ĐEN | F7: 1 | G7: 1990 | H7: 46104 | I7: Đã gửi
A8: Hoàng Yến | B8: Giày howell | C8: M001 | D8: 35 | E8: ĐEN | F8: 1 | G8: 1990 | H8: 46104 | I8: Đã gửi
A9: Hột Mít | B9: Giày howell | C9: M001 | D9: 39 | E9: ĐEN | F9: 1 | G9: 1990 | H9: 46110 | I9: Đã gửi | J9: https://www.facebook.com/share/1GFVuaM7ZC/
A10: Hột Mít | B10: Giày howell | C10: M001 | D10: 39 | E10: ĐEN | F10: 1 | G10: 1990 | H10: 46110 | I10: Đã gửi | J10: https://www.facebook.com/share/1GFVuaM7ZC/
A11: Hột Mít | B11: Giày howell | C11: M001 | D11: 39 | E11: ĐEN | F11: 1 | G11: 1990 | H11: 46110 | I11: Đã gửi | J11: https://www.facebook.com/share/1GFVuaM7ZC/
A12: Hột Mít | B12: Giày howell | C12: M001 | D12: 39 | E12: ĐEN | F12: 1 | G12: 1990 | H12: 46110 | I12: Đã gửi | J12: https://www.facebook.com/share/1GFVuaM7ZC/
A13: Hột Mít | B13: Giày howell | C13: M001 | D13: 39 | E13: ĐEN | F13: 1 | G13: 1990 | H13: 46110 | I13: Đã gửi | J13: https://www.facebook.com/share/1GFVuaM7ZC/
A14: Hột Mít | B14: Giày howell | C14: M001 | D14: 39 | E14: ĐEN | F14: 1 | G14: 1990 | H14: 46110 | I14: Đã gửi | J14: https://www.facebook.com/share/1GFVuaM7ZC/
A15: HằnG Em | B15: Áo dây | C15: M006 | D15: FZ | E15: TRẮNG | F15: 1 | G15: 750 | H15: 46118 | I15: Đã gửi | J15: https://www.facebook.com/share/14e2CsYrAZ6/
A16: Đàm Chinh | B16: Áo dây | C16: M006 | D16: FZ | E16: XÁM | F16: 1 | G16: 750 | H16: 46118 | I16: Đã gửi | J16: https://www.facebook.com/share/1CYRqHhKAG/
A17: Đàm Chinh | B17: Áo dây | C17: M006 | D17: FZ | E17: XÁM | F17: 1 | G17: 750 | H17: 46118 | I17: Đã gửi | J17: https://www.facebook.com/share/1CYRqHhKAG/
A18: Đàm Chinh | B18: Áo dây | C18: M006 | D18: FZ | E18: XÁM | F18: 1 | G18: 750 | H18: 46118 | I18: Đã gửi | J18: https://www.facebook.com/share/1CYRqHhKAG/
A19: Đàm Chinh | B19: Áo dây | C19: M006 | D19: FZ | E19: XÁM | F19: 1 | G19: 750 | H19: 46118 | I19: Đã gửi | J19: https://www.facebook.com/share/1CYRqHhKAG/
A20: Trang Đoàn | B20: Mũ Polo | C20: MU01 | D20: FZ | E20: BE | F20: 1 | G20: 1200 | H20: 46123 | I20: Đã gửi | J20: https://www.facebook.com/share/1CJaXPJ5aQ/
A21: Trang Đoàn | B21: Mũ Polo | C21: MU01 | D21: FZ | E21: BE | F21: 1 | G21: 1200 | H21: 46123 | I21: Đã gửi | J21: https://www.facebook.com/share/1CJaXPJ5aQ/
A22: Ng Thị Hảo | B22: Jean lửng xanh đậm | C22: 8748 | D22: S | E22: XANH THAN | F22: 1 | G22: 1800 | H22: 46125 | I22: Đã gửi
A23: Ng Thị Hảo | B23: Jean lửng xanh đậm | C23: 8748 | D23: S | E23: XANH THAN | F23: 1 | G23: 1800 | H23: 46125 | I23: Đã gửi
A24: Ng Thị Hảo | B24: Jean lửng xanh đậm | C24: 8748 | D24: S | E24: XANH THAN | F24: 1 | G24: 1800 | H24: 46125 | I24: Đã gửi
A25: Minh Trang | B25: Jean lửng xanh đậm | C25: 8748 | D25: L | E25: XANH THAN | F25: 1 | G25: 1800 | H25: 46128 | I25: Đã gửi | J25: https://www.facebook.com/share/14bDUZJAxHW/
A26: Minh Trang | B26: Jean lửng xanh đậm | C26: 8748 | D26: L | E26: XANH THAN | F26: 1 | G26: 1800 | H26: 46128 | I26: Đã gửi | J26: https://www.facebook.com/share/14bDUZJAxHW/
A27: Minh Trang | B27: Jean lửng xanh đậm | C27: 8748 | D27: L | E27: XANH THAN | F27: 1 | G27: 1800 | H27: 46128 | I27: Đã gửi | J27: https://www.facebook.com/share/14bDUZJAxHW/
A28: Minh Trang | B28: Jean lửng xanh đậm | C28: 8748 | D28: L | E28: XANH THAN | F28: 1 | G28: 1800 | H28: 46128 | I28: Đã gửi | J28: https://www.facebook.com/share/14bDUZJAxHW/
A29: Minh Trang | B29: Jean lửng xanh đậm | C29: 8748 | D29: L | E29: XANH THAN | F29: 1 | G29: 1800 | H29: 46128 | I29: Đã gửi | J29: https://www.facebook.com/share/14bDUZJAxHW/
A30: Phan Hằng | B30: Giày howell | C30: M001 | D30: 36 | E30: ĐEN | F30: 1 | G30: 1990 | H30: 46133 | I30: Đã gửi
A31: Phan Hằng | B31: Giày howell | C31: M001 | D31: 36 | E31: ĐEN | F31: 1 | G31: 1990 | H31: 46133 | I31: Đã gửi
A32: Phan Hằng | B32: Giày howell | C32: M001 | D32: 36 | E32: ĐEN | F32: 1 | G32: 1990 | H32: 46133 | I32: Đã gửi
A33: Thu Phương | B33: Giày howell | C33: M001 | D33: 36 | E33: BE | F33: 1 | G33: 1990 | H33: 46136 | I33: Đã gửi | J33: https://www.facebook.com/share/1AznU6QD5p/
A34: Ngân | B34: jeep sandal | C34: PE232WAS632 | D34: 37 | E34: TÍM | F34: 1 | G34: 6800 | H34: 46137 | I34: Đã gửi
A35: Ngân | B35: jeep sandal | C35: PE232WAS632 | D35: 37 | E35: TÍM | F35: 1 | G35: 6800 | H35: 46137 | I35: Đã gửi
A36: Hạ Hạ | B36: Giày jeep bestseller | C36: P651W13112C | D36: 37 | E36: XANH NHẠT | F36: 1 | G36: 6990 | H36: 46139 | I36: Đã gửi
A37: Hạ Hạ | B37: Giày jeep bestseller | C37: P651W13112C | D37: 37 | E37: XANH NHẠT | F37: 1 | G37: 6990 | H37: 46139 | I37: Đã gửi
A38: Trần Thị Cẩm My | B38: Sữa tắm nước hoa | C38: M013 | D38: FZ | E38: NÂU | F38: 2 | G38: 1700 | H38: 46141 | I38: Đã gửi | J38: https://www.facebook.com/share/1BKnyGxqCz/
A39: Trần Thị Cẩm My | B39: Sữa tắm nước hoa | C39: M013 | D39: FZ | E39: NÂU | F39: 2 | G39: 1700 | H39: 46141 | I39: Đã gửi | J39: https://www.facebook.com/share/1BKnyGxqCz/
A40: Trần Thị Cẩm My | B40: Sữa tắm nước hoa | C40: M013 | D40: FZ | E40: NÂU | F40: 2 | G40: 1700 | H40: 46141 | I40: Đã gửi | J40: https://www.facebook.com/share/1BKnyGxqCz/
A41: Thương Bùi | B41: Giày howell | C41: M001 | D41: 39 | E41: ĐEN | F41: 1 | G41: 1990 | H41: 46144 | I41: Đã gửi | J41: https://www.facebook.com/share/1Ddu6gKtDs/
A42: Thương Bùi | B42: Giày howell | C42: M001 | D42: 39 | E42: ĐEN | F42: 1 | G42: 1990 | H42: 46144 | I42: Đã gửi | J42: https://www.facebook.com/share/1Ddu6gKtDs/
A43: Thương Bùi | B43: Giày howell | C43: M001 | D43: 39 | E43: ĐEN | F43: 1 | G43: 1990 | H43: 46144 | I43: Đã gửi | J43: https://www.facebook.com/share/1Ddu6gKtDs/
A44: Thương Bùi | B44: Giày howell | C44: M001 | D44: 39 | E44: ĐEN | F44: 1 | G44: 1990 | H44: 46144 | I44: Đã gửi | J44: https://www.facebook.com/share/1Ddu6gKtDs/
A45: Hoài Ý | B45: Quần loe đen Catkaiser | C45: CK98118 | D45: M | E45: ĐEN | F45: 1 | G45: 1800 | H45: 46148 | I45: Đã gửi | J45: https://www.facebook.com/share/178jkpzZUv/
A46: Hoài Ý | B46: Quần loe đen Catkaiser | C46: CK98118 | D46: M | E46: ĐEN | F46: 1 | G46: 1800 | H46: 46148 | I46: Đã gửi | J46: https://www.facebook.com/share/178jkpzZUv/
A47: Hoài Ý | B47: Quần loe đen Catkaiser | C47: CK98118 | D47: M | E47: ĐEN | F47: 1 | G47: 1800 | H47: 46148 | I47: Đã gửi | J47: https://www.facebook.com/share/178jkpzZUv/
A48: Hoài Ý | B48: Quần loe đen Catkaiser | C48: CK98118 | D48: M | E48: ĐEN | F48: 1 | G48: 1800 | H48: 46148 | I48: Đã gửi | J48: https://www.facebook.com/share/178jkpzZUv/
A49: Hoài Ý | B49: Quần loe đen Catkaiser | C49: CK98118 | D49: M | E49: ĐEN | F49: 1 | G49: 1800 | H49: 46148 | I49: Đã gửi | J49: https://www.facebook.com/share/178jkpzZUv/
A50: Hoài Ý | B50: Quần loe đen Catkaiser | C50: CK98118 | D50: M | E50: ĐEN | F50: 1 | G50: 1800 | H50: 46148 | I50: Đã gửi | J50: https://www.facebook.com/share/178jkpzZUv/
A51: Hoài Ý | B51: Quần loe đen Catkaiser | C51: CK98118 | D51: M | E51: ĐEN | F51: 1 | G51: 1800 | H51: 46148 | I51: Đã gửi | J51: https://www.facebook.com/share/178jkpzZUv/
A52: Hoài Ý | B52: Quần loe đen Catkaiser | C52: CK98118 | D52: M | E52: ĐEN | F52: 1 | G52: 1800 | H52: 46148 | I52: Đã gửi | J52: https://www.facebook.com/share/178jkpzZUv/
A53: Dương Ngọc Thảo | B53: Túi vải 2 mặt | C53: M012 | D53: FZ | E53: TÍM | F53: 1 | G53: 990 | H53: 46150 | I53: Đã gửi
A54: Dương Ngọc Thảo | B54: Túi vải 2 mặt | C54: M012 | D54: FZ | E54: TÍM | F54: 1 | G54: 990 | H54: 46150 | I54: Đã gửi
A55: Huyền Trang3 | B55: Áo dây | C55: M006 | D55: FZ | E55: BE | F55: 1 | G55: 750 | H55: 46158 | I55: Đã gửi
A56: Linh Chi | B56: Túi vải 2 mặt | C56: M012 | D56: FZ | E56: TÍM | F56: 1 | G56: 990 | H56: 46159 | I56: Đã gửi | J56: https://www.facebook.com/share/18WM8uv7fF/
A57: Vũ Minh Quỳnh | B57: Giày howell | C57: M001 | D57: 35 | E57: ĐEN | F57: 1 | G57: 1990 | H57: 46160 | I57: Đã gửi | J57: https://www.facebook.com/share/1Aen4qAdYq/
A58: Vũ Minh Quỳnh | B58: Giày howell | C58: M001 | D58: 35 | E58: ĐEN | F58: 1 | G58: 1990 | H58: 46160 | I58: Đã gửi | J58: https://www.facebook.com/share/1Aen4qAdYq/
A59: Ka Xu | B59: Quần loe đen Catkaiser | C59: CK98118 | D59: M | E59: ĐEN | F59: 1 | G59: 1800 | H59: 46162 | I59: Đã gửi | J59: https://www.facebook.com/share/18nQLAfLNh/
A60: Li Ly | B60: TÊN KHÁCH | C60: M007 | D60: 39 | E60: Onitsuka | F60: 1 | G60: 1 | H60: 46163 | I60: Đã gửi | J60: https://www.facebook.com/share/1EZ24v5RFB/
A61: Hương Hương | B61: Jean lửng xanh đậm | C61: 8748 | D61: M | E61: XANH THAN | F61: 1 | G61: 1800 | H61: 46164 | I61: Đã gửi | J61: https://www.facebook.com/share/1DA2igw8tf/
A62: Hương Hương | B62: Jean lửng xanh đậm | C62: 8748 | D62: M | E62: XANH THAN | F62: 1 | G62: 1800 | H62: 46164 | I62: Đã gửi | J62: https://www.facebook.com/share/1DA2igw8tf/
A63: Thắmm Thắmm | B63: Giày jeep quai chéo | C63: P661W13310 | D63: 37 | E63: BE | F63: 1 | G63: 7000 | H63: 46166 | I63: Đã gửi | J63: https://www.facebook.com/share/1E5L6upzSm/
A64: Thắmm Thắmm | B64: Giày jeep quai chéo | C64: P661W13310 | D64: 37 | E64: BE | F64: 1 | G64: 7000 | H64: 46166 | I64: Đã gửi | J64: https://www.facebook.com/share/1E5L6upzSm/
A65: Yến Nhi | B65: Giày howell | C65: M001 | D65: 36 | E65: ĐEN | F65: 1 | G65: 1990 | H65: 46168 | I65: Đã gửi
A66: Yến Nhi | B66: Giày howell | C66: M001 | D66: 36 | E66: ĐEN | F66: 1 | G66: 1990 | H66: 46168 | I66: Đã gửi
A67: Yến Nhi | B67: Giày howell | C67: M001 | D67: 36 | E67: ĐEN | F67: 1 | G67: 1990 | H67: 46168 | I67: Đã gửi
A68: Yến Nhi | B68: Giày howell | C68: M001 | D68: 36 | E68: ĐEN | F68: 1 | G68: 1990 | H68: 46168 | I68: Đã gửi
A69: Yến Nhi | B69: Giày howell | C69: M001 | D69: 36 | E69: ĐEN | F69: 1 | G69: 1990 | H69: 46168 | I69: Đã gửi
A70: Yến Nhi | B70: Giày howell | C70: M001 | D70: 36 | E70: ĐEN | F70: 1 | G70: 1990 | H70: 46168 | I70: Đã gửi
A71: Huỳnh Thư | B71: TÊN KHÁCH | C71: M007 | D71: 37 | E71: ONITSUKA | F71: 1 | G71: 1 | H71: 46174 | I71: Đã gửi
A72: Huỳnh Thư | B72: TÊN KHÁCH | C72: M007 | D72: 37 | E72: ONITSUKA | F72: 1 | G72: 1 | H72: 46174 | I72: Đã gửi
A73: Yến Phi | B73: Ba Lỗ có mút | C73: 8876 | D73: M | E73: ĐEN | F73: 1 | G73: 990 | H73: 46176 | I73: Đã gửi | J73: https://www.facebook.com/share/1LQbv6gYi3/
A74: Nguyễn Hồng Đào | B74: Áo ba lỗ có móc treo | C74: 6612 | D74: FZ | E74: 5 | F74: 1 | G74: 850 | H74: 46177 | I74: Đã gửi
A75: Bích Phượng | B75: Bộ Nỉ | C75: 9094 | D75: M | E75: XANH THAN | F75: 1 | G75: 2400 | H75: 46178 | I75: Đã gửi | J75: https://www.facebook.com/share/18NDLeTSvX/
A76: Bích Phượng | B76: Bộ Nỉ | C76: 9094 | D76: M | E76: XANH THAN | F76: 1 | G76: 2400 | H76: 46178 | I76: Đã gửi | J76: https://www.facebook.com/share/18NDLeTSvX/

Sheet KHO HÀNG
A1: Mã SP | B1: Size | C1: Color | D1: Số lượng nhập | E1: Ngày nhập | F1: Ghi chú
A2: 7398 | B2: S | C2: TRẮNG | D2: 1 | E2: 46098
A3: 7436 | B3: M | C3: XANH THAN | D3: 1 | E3: 46098
A4: 7458 | B4: S | C4: ĐEN | D4: 2 | E4: 46098
A5: 7910 | B5: M | C5: TRẮNG | D5: 1 | E5: 46098
A6: 7910 | B6: S | C6: ĐEN | D6: 1 | E6: 46098
A7: 7910 | B7: S | C7: NÂU | D7: 1 | E7: 46098
A8: 8625 | B8: S | C8: XANH THAN | D8: 4 | E8: 46098
A9: 8625 | B9: M | C9: XANH THAN | D9: 1 | E9: 46098
A10: 7398 | B10: S | C10: ĐEN | D10: 2 | E10: 46098
A11: 7398 | B11: S | C11: XÁM | D11: 1 | E11: 46098
A12: 7458 | B12: M | C12: ĐEN | D12: 3 | E12: 46098
A13: 7859 | B13: FZ | C13: HỒNG | D13: 7 | E13: 46098
... A90: 8876 | B90: S | C90: NÂU | D90: 3 | E90: 46109
A91: M001 | B91: 40 | C91: BE | D91: 1 | E91: 46109
A92: M001 | B92: 38 | C92: ĐEN | D92: 4 | E92: 46109
A93: M001 | B93: 35 | C93: BE | D93: 1 | E93: 46109
A94: M001 | B94: 39 | C94: ĐEN | D94: 4 | E94: 46109
A95: M001 | B95: 36 | C95: BE | D95: 1 | E95: 46109
A96: M001 | B96: 36 | C96: BE | D96: 2 | E96: 46109
A97: M001 | B97: 38 | C97: BE | D97: 4 | E97: 46109
A98: M001 | B98: 39 | C98: BE | D98: 1 | E98: 46109
A99: M001 | B99: 37 | C99: ĐEN | D99: 3 | E99: 46109
A100: 8748 | B100: S | C100: XANH THAN | D100: 1 | E100: 46109
A101: 8876 | B101: M | C101: TÍM | D101: 2 | E101: 46109
A102: 8521 | B102: S | C102: NÂU | D102: 1 | E102: 46111
A103: 8521 | B103: M | C103: NÂU | D103: 1 | E103: 46111
A104: 8867 | B104: S | C104: HỒNG | D104: 3 | E104: 46111
A105: 8867 | B105: S | C105: XANH THAN | D105: 2 | E105: 46111
A106: 7307 | B106: S | C106: BE | D106: 1 | E106: 46111
A107: 7307 | B107: M | C107: NÂU | D107: 1 | E107: 46111
A108: 9369 | B108: M | C108: XANH THAN | D108: 1 | E108: 46111
A109: 9369 | B109: S | C109: XANH THAN | D109: 1 | E109: 46111
A110: 7137 | B110: S | C110: XANH THAN | D110: 2 | E110: 46111
A111: M001 | B111: 37 | C111: BE | D111: 2 | E111: 46111
A112: M001 | B112: 36 | C112: BE | D112: 1 | E112: 46111
A113: M001 | B113: 39 | C113: BE | D113: 2 | E113: 46111
A114: M001 | B114: 40 | C114: BE | D114: 1 | E114: 46111
A115: M001 | B115: 35 | C115: ĐEN | D115: 2 | E115: 46111
A116: M001 | B116: 36 | C116: ĐEN | D116: 2 | E116: 46111
A117: M001 | B117: 37 | C117: ĐEN | D117: 2 | E117: 46111
A118: M001 | B118: 39 | C118: ĐEN | D118: 4 | E118: 46111
A119: 8319 | B119: S | C119: XANH THAN | D119: 1 | E119: 46112
A120: 7957 | B120: M | C120: ĐEN | D120: 1 | E120: 46112
A121: 8748 | B121: S | C121: XANH THAN | D121: 1 | E121: 46112
A122: 5709 | B122: S | C122: XANH NHẠT | D122: 4 | E122: 46114
A123: 5709 | B123: M | C123: XANH NHẠT | D123: 5 | E123: 46114
A124: 5709 | B124: L | C124: XANH NHẠT | D124: 2 | E124: 46114
A125: M006 | B125: FZ | C125: XÁM | D125: 25 | E125: 46114
A126: M006 | B126: FZ | C126: ĐEN | D126: 45 | E126: 46114
A127: M006 | B127: FZ | C127: TRẮNG | D127: 50 | E127: 46114
A128: M006 | B128: FZ | C128: BE | D128: 20 | E128: 46114
A129: M001 | B129: 38 | C129: ĐEN | D129: 3 | E129: 46114
A130: M001 | B130: 39 | C130: ĐEN | D130: 1 | E130: 46114
A131: M001 | B131: 36 | C131: BE | D131: 1 | E131: 46114
A132: M001 | B132: 37 | C132: BE | D132: 1 | E132: 46114
A133: M001 | B133: 38 | C133: BE | D133: 2 | E133: 46114
A134: M001 | B134: 37 | C134: ĐEN | D134: 2 | E134: 46114
A135: M001 | B135: 35 | C135: ĐEN | D135: 1 | E135: 46114
A136: M001 | B136: 36 | C136: ĐEN | D136: 1 | E136: 46116
A137: M001 | B137: 37 | C137: ĐEN | D137: 7 | E137: 46116
A138: M001 | B138: 38 | C138: ĐEN | D138: 2 | E138: 46116
A139: M001 | B139: 39 | C139: ĐEN | D139: 3 | E139: 46116
A140: M001 | B140: 36 | C140: BE | D140: 4 | E140: 46116
... A143: M001 | B143: 39 | C143: BE | D143: 3 | E143: 46116
A144: M004 | B144: FZ | C144: XANH NHẠT | D144: 6 | E144: 46116
A145: M004 | B145: FZ | C145: HỒNG | D145: 5 | E145: 46116
A146: M004 | B146: FZ | C146: VÀNG | D146: 1 | E146: 46116
A147: 81813 | B147: FZ | C147: TRẮNG | D147: 6 | E147: 46116
A148: 81813 | B148: FZ | C148: ĐEN | D148: 4 | E148: 46116
A149: 81813 | B149: FZ | C149: XÁM | D149: 3 | E149: 46116
A150: 81813 | B150: FZ | C150: XANH NHẠT | D150: 1 | E150: 46116
A151: 81813 | B151: FZ | C151: ĐỎ | D151: 1 | E151: 46116
A152: 81813 | B152: FZ | C152: VÀNG | D152: 4 | E152: 46116
A153: 81813 | B153: FZ | C153: HỒNG | D153: 14 | E153: 46116
A154: 8748 | B154: L | C154: XANH THAN | D154: 1 | E154: 46117
A155: M003 | B155: L | C155: ĐEN | D155: 1 | E155: 46118
A156: 7249 | B156: S | C156: XANH THAN | D156: 1 | E156: 46120
A157: M006 | B157: FZ | C157: ĐEN | D157: 4 | E157: 46123
A158: M006 | B158: FZ | C158: TRẮNG | D158: 3 | E158: 46123
A159: M006 | B159: FZ | C159: BE | D159: 1 | E159: 46123
A160: TRA1 | B160: FZ | C160: VÀNG | D160: 26 | E160: 46123
A161: MU01 | B161: FZ | C161: NÂU | D161: 1 | E161: 46123
A162: MU01 | B162: FZ | C162: NÂU | D162: 1 | E162: 46123
A163: MU01 | B163: FZ | C163: NÂU | D163: 1 | E163: 46123
A164: MU01 | B164: FZ | C164: NÂU | D164: 1 | E164: 46123
A165: MU01 | B165: FZ | C165: BE | D165: 3 | E165: 46123
A166: M005 | B166: 38 | C166: NÂU | D166: 2 | E166: 46123
A167: M005 | B167: 35 | C167: NÂU | D167: 2 | E167: 46123
A168: M005 | B168: 37 | C168: NÂU | D168: 1 | E168: 46123
A169: M005 | B169: 37 | C169: BE | D169: 1 | E169: 46123
A170: M005 | B170: 37 | C170: ĐEN | D170: 1 | E170: 46123
A171: M005 | B171: 39 | C171: NÂU | D171: 1 | E171: 46123
A172: MU01 | B172: FZ | C172: NÂU | D172: 22 | E172: 46123
A173: MU01 | B173: FZ | C173: HỒNG | D173: 2 | E173: 46123
A174: MU01 | B174: FZ | C174: NÂU NHẠT | D174: 15 | E174: 46123
A175: MU01 | B175: FZ | C175: BE | D175: 22 | E175: 46123
A176: 8876 | B176: M | C176: ĐEN | D176: 11 | E176: 46123
A177: 9094 | B177: S | C177: XÁM | D177: 5 | E177: 46123
A178: 8867 | B178: S | C178: TRẮNG | D178: 5 | E178: 46123
...

Sheet LỆNH GỬI HÀNG
A1: Tên khách | B1: Tổng hàng order | C1: Trạng thái hàng | D1: Đã gửi | E1: Ngày gửi
A2: =IFERROR(__xludf.DUMMYFUNCTION("UNIQUE(FILTER('NHẬP ĐƠN'!A2:A1501, 'NHẬP ĐƠN'!A2:A1501<>""""))"),"Ngọc Thuý Trần") -> Ngọc Thuý Trần | B2: {=MAP(A2:A1501, LAMBDA(khach, IF(khach="",, COUNTIF('NHẬP ĐƠN'!A2:A1501, khach))))} -> 14 | C2: =IFERROR(__xludf.DUMMYFUNCTION("MAP(A2:A1501, LAMBDA(khach, IF(khach="""", """", LET( ma_sp, IFERROR(FILTER('NHẬP ĐƠN'!C2:C1501, IFERROR('NHẬP ĐƠN'!A2:A1501 = khach, FALSE)), """"), IF(INDEX(ma_sp, 1) = """", ""❌ KHÔNG CÓ TRONG NHẬP ĐƠN"", LET( "&" size_sp, FILTER('NHẬP ĐƠN'!D2:D1501, IFERROR('NHẬP ĐƠN'!A2:A1501 = khach, FALSE)), color_sp, FILTER('NHẬP ĐƠN'!E2:E1501, IFERROR('NHẬP ĐƠN'!A2:A1501 = khach, FALSE)), luy_ke, FILTER('NHẬP ĐƠN'!K2:K1501, IFERROR('NHẬP ĐƠN'!A2:A1501 = "&"khach, FALSE)), so_mon_dat, ROWS(ma_sp), kiem_tra, MAP(ma_sp, size_sp, color_sp, luy_ke, LAMBDA(m, s, c, lk, LET( ton_kho, SUMIFS('KHO HÀNG'!D:D, 'KHO HÀNG'!A:A, m, 'KHO HÀNG'!B:B, s, 'KHO HÀNG'!C:C"&", c), IF(ton_kho >= lk, 1, 0) ) )), so_mon_du, SUM(kiem_tra), IF(so_mon_du = so_mon_dat, ""✅ ĐỦ HÀNG"", ""❌ THIẾU "" & (so_mon_dat - so_mon_du) & "" MÓN"") ) ) ) ) ))"),"✅ ĐỦ HÀNG") -> ✅ ĐỦ HÀNG
A3: =IFERROR(__xludf.DUMMYFUNCTION("""COMPUTED_VALUE"""),"Uyên Lê") -> Uyên Lê | B3: 6 | C3: =IFERROR(__xludf.DUMMYFUNCTION("""COMPUTED_VALUE"""),"✅ ĐỦ HÀNG") -> ✅ ĐỦ HÀNG
A4: =IFERROR(__xludf.DUMMYFUNCTION("""COMPUTED_VALUE"""),"Hà Giang") -> Hà Giang | B4: 5 | C4: =IFERROR(__xludf.DUMMYFUNCTION("""COMPUTED_VALUE"""),"✅ ĐỦ HÀNG") -> ✅ ĐỦ HÀNG
A5: =IFERROR(__xludf.DUMMYFUNCTION("""COMPUTED_VALUE"""),"Bùi Thị Ngọc Hân") -> Bùi Thị Ngọc Hân | B5: 1 | C5: =IFERROR(__xludf.DUMMYFUNCTION("""COMPUTED_VALUE"""),"✅ ĐỦ HÀNG") -> ✅ ĐỦ HÀNG
A6: =IFERROR(__xludf.DUMMYFUNCTION("""COMPUTED_VALUE"""),"Trang Mẩu") -> Trang Mẩu | B6: 11 | C6: =IFERROR(__xludf.DUMMYFUNCTION("""COMPUTED_VALUE"""),"✅ ĐỦ HÀNG") -> ✅ ĐỦ HÀNG
A7: =IFERROR(__xludf.DUMMYFUNCTION("""COMPUTED_VALUE"""),"Nguyễn Phương Vy") -> Nguyễn Phương Vy | B7: 3 | C7: =IFERROR(__xludf.DUMMYFUNCTION("""COMPUTED_VALUE"""),"✅ ĐỦ HÀNG") -> ✅ ĐỦ HÀNG
A8: =IFERROR(__xludf.DUMMYFUNCTION("""COMPUTED_VALUE"""),"Lily") -> Lily | B8: 2 | C8: =IFERROR(__xludf.DUMMYFUNCTION("""COMPUTED_VALUE"""),"✅ ĐỦ HÀNG") -> ✅ ĐỦ HÀNG
A9: =IFERROR(__xludf.DUMMYFUNCTION("""COMPUTED_VALUE"""),"Thanh Hang Huang") -> Thanh Hang Huang | B9: 2 | C9: =IFERROR(__xludf.DUMMYFUNCTION("""COMPUTED_VALUE"""),"✅ ĐỦ HÀNG") -> ✅ ĐỦ HÀNG
A10: =IFERROR(__xludf.DUMMYFUNCTION("""COMPUTED_VALUE"""),"Kim Cúc") -> Kim Cúc | B10: 2 | C10: =IFERROR(__xludf.DUMMYFUNCTION("""COMPUTED_VALUE"""),"✅ ĐỦ HÀNG") -> ✅ ĐỦ HÀNG
A11: =IFERROR(__xludf.DUMMYFUNCTION("""COMPUTED_VALUE"""),"Lê Thuỳ Dương") -> Lê Thuỳ Dương | B11: 19 | C11: =IFERROR(__xludf.DUMMYFUNCTION("""COMPUTED_VALUE"""),"✅ ĐỦ HÀNG") -> ✅ ĐỦ HÀNG
A12: =IFERROR(__xludf.DUMMYFUNCTION("""COMPUTED_VALUE"""),"Trần Kiều Giang") -> Trần Kiều Giang | B12: 2 | C12: =IFERROR(__xludf.DUMMYFUNCTION("""COMPUTED_VALUE"""),"✅ ĐỦ HÀNG") -> ✅ ĐỦ HÀNG
A13: =IFERROR(__xludf.DUMMYFUNCTION("""COMPUTED_VALUE"""),"Phạm Thị Như Ý") -> Phạm Thị Như Ý | B13: 5 | C13: =IFERROR(__xludf.DUMMYFUNCTION("""COMPUTED_VALUE"""),"✅ ĐỦ HÀNG") -> ✅ ĐỦ HÀNG
A14: =IFERROR(__xludf.DUMMYFUNCTION("""COMPUTED_VALUE"""),"Nguyễn Thu") -> Nguyễn Thu | B14: 7 | C14: =IFERROR(__xludf.DUMMYFUNCTION("""COMPUTED_VALUE"""),"✅ ĐỦ HÀNG") -> ✅ ĐỦ HÀNG
A15: =IFERROR(__xludf.DUMMYFUNCTION("""COMPUTED_VALUE"""),"Ngọc Huyền") -> Ngọc Huyền | B15: 10 | C15: =IFERROR(__xludf.DUMMYFUNCTION("""COMPUTED_VALUE"""),"✅ ĐỦ HÀNG") -> ✅ ĐỦ HÀNG
A16: =IFERROR(__xludf.DUMMYFUNCTION("""COMPUTED_VALUE"""),"Dang Minh") -> Dang Minh | B16: 13 | C16: =IFERROR(__xludf.DUMMYFUNCTION("""COMPUTED_VALUE"""),"✅ ĐỦ HÀNG") -> ✅ ĐỦ HÀNG
A17: =IFERROR(__xludf.DUMMYFUNCTION("""COMPUTED_VALUE"""),"Trần Thị Thu") -> Trần Thị Thu | B17: 4 | C17: =IFERROR(__xludf.DUMMYFUNCTION("""COMPUTED_VALUE"""),"✅ ĐỦ HÀNG") -> ✅ ĐỦ HÀNG
A18: =IFERROR(__xludf.DUMMYFUNCTION("""COMPUTED_VALUE"""),"Bích Thuỷ") -> Bích Thuỷ | B18: 2 | C18: =IFERROR(__xludf.DUMMYFUNCTION("""COMPUTED_VALUE"""),"✅ ĐỦ HÀNG") -> ✅ ĐỦ HÀNG
A19: =IFERROR(__xludf.DUMMYFUNCTION("""COMPUTED_VALUE"""),"Vũ Hà Thu") -> Vũ Hà Thu | B19: 3 | C19: =IFERROR(__xludf.DUMMYFUNCTION("""COMPUTED_VALUE"""),"✅ ĐỦ HÀNG") -> ✅ ĐỦ HÀNG
A20: =IFERROR(__xludf.DUMMYFUNCTION("""COMPUTED_VALUE"""),"Ng Hà Phương") -> Ng Hà Phương | B20: 4 | C20: =IFERROR(__xludf.DUMMYFUNCTION("""COMPUTED_VALUE"""),"✅ ĐỦ HÀNG") -> ✅ ĐỦ HÀNG
A21: =IFERROR(__xludf.DUMMYFUNCTION("""COMPUTED_VALUE"""),"Nguyễn Hương") -> Nguyễn Hương | B21: 7 | C21: =IFERROR(__xludf.DUMMYFUNCTION("""COMPUTED_VALUE"""),"✅ ĐỦ HÀNG") -> ✅ ĐỦ HÀNG
A22: =IFERROR(__xludf.DUMMYFUNCTION("""COMPUTED_VALUE"""),"Hương Cherry") -> Hương Cherry | B22: 1 | C22: =IFERROR(__xludf.DUMMYFUNCTION("""COMPUTED_VALUE"""),"✅ ĐỦ HÀNG") -> ✅ ĐỦ HÀNG
A23: =IFERROR(__xludf.DUMMYFUNCTION("""COMPUTED_VALUE"""),"Hoàng Yếnn") -> Hoàng Yếnn | B23: 8 | C23: =IFERROR(__xludf.DUMMYFUNCTION("""COMPUTED_VALUE"""),"✅ ĐỦ HÀNG") -> ✅ ĐỦ HÀNG
A24: =IFERROR(__xludf.DUMMYFUNCTION("""COMPUTED_VALUE"""),"Lộc Tâm") -> Lộc Tâm | B24: 6 | C24: =IFERROR(__xludf.DUMMYFUNCTION("""COMPUTED_VALUE"""),"✅ ĐỦ HÀNG") -> ✅ ĐỦ HÀNG
A25: =IFERROR(__xludf.DUMMYFUNCTION("""COMPUTED_VALUE"""),"Ngọc Hà") -> Ngọc Hà | B25: 16 | C25: =IFERROR(__xludf.DUMMYFUNCTION("""COMPUTED_VALUE"""),"✅ ĐỦ HÀNG") -> ✅ ĐỦ HÀNG
A26: =IFERROR(__xludf.DUMMYFUNCTION("""COMPUTED_VALUE"""),"Phương Nga") -> Phương Nga | B26: 5 | C26: =IFERROR(__xludf.DUMMYFUNCTION("""COMPUTED_VALUE"""),"✅ ĐỦ HÀNG") -> ✅ ĐỦ HÀNG
A27: =IFERROR(__xludf.DUMMYFUNCTION("""COMPUTED_VALUE"""),"Lụa Mỹ") -> Lụa Mỹ | B27: 2 | C27: =IFERROR(__xludf.DUMMYFUNCTION("""COMPUTED_VALUE"""),"✅ ĐỦ HÀNG") -> ✅ ĐỦ HÀNG | D27: Da gui | E27: 19:24:41 18/3/2026
A28: =IFERROR(__xludf.DUMMYFUNCTION("""COMPUTED_VALUE"""),"Phạm Hoàn") -> Phạm Hoàn | B28: 5 | C28: =IFERROR(__xludf.DUMMYFUNCTION("""COMPUTED_VALUE"""),"✅ ĐỦ HÀNG") -> ✅ ĐỦ HÀNG | D28: Da gui | E28: 16:06:00 21/3/2026
A29: =IFERROR(__xludf.DUMMYFUNCTION("""COMPUTED_VALUE"""),"Hà Oanh") -> Hà Oanh | B29: 3 | C29: =IFERROR(__xludf.DUMMYFUNCTION("""COMPUTED_VALUE"""),"✅ ĐỦ HÀNG") -> ✅ ĐỦ HÀNG | D29: Da gui | E29: 19:24:44 18/3/2026
A30: =IFERROR(__xludf.DUMMYFUNCTION("""COMPUTED_VALUE"""),"Thuỳ Trang") -> Thuỳ Trang | B30: 8 | C30: =IFERROR(__xludf.DUMMYFUNCTION("""COMPUTED_VALUE"""),"✅ ĐỦ HÀNG") -> ✅ ĐỦ HÀNG
A31: =IFERROR(__xludf.DUMMYFUNCTION("""COMPUTED_VALUE"""),"Tâm Tâm") -> Tâm Tâm | B31: 3 | C31: =IFERROR(__xludf.DUMMYFUNCTION("""COMPUTED_VALUE"""),"✅ ĐỦ HÀNG") -> ✅ ĐỦ HÀNG
A32: =IFERROR(__xludf.DUMMYFUNCTION("""COMPUTED_VALUE"""),"Trang Minn") -> Trang Minn | B32: 2 | C32: =IFERROR(__xludf.DUMMYFUNCTION("""COMPUTED_VALUE"""),"✅ ĐỦ HÀNG") -> ✅ ĐỦ HÀNG
A33: =IFERROR(__xludf.DUMMYFUNCTION("""COMPUTED_VALUE"""),"Phan Nhung ") -> Phan Nhung | B33: 2 | C33: =IFERROR(__xludf.DUMMYFUNCTION("""COMPUTED_VALUE"""),"✅ ĐỦ HÀNG") -> ✅ ĐỦ HÀNG
A34: =IFERROR(__xludf.DUMMYFUNCTION("""COMPUTED_VALUE"""),"GiangHoang Vu") -> GiangHoang Vu | B34: 1 | C34: =IFERROR(__xludf.DUMMYFUNCTION("""COMPUTED_VALUE"""),"✅ ĐỦ HÀNG") -> ✅ ĐỦ HÀNG
A35: =IFERROR(__xludf.DUMMYFUNCTION("""COMPUTED_VALUE"""),"Trang Đoàn") -> Trang Đoàn | B35: 11 | C35: =IFERROR(__xludf.DUMMYFUNCTION("""COMPUTED_VALUE"""),"✅ ĐỦ HÀNG") -> ✅ ĐỦ HÀNG
A36: =IFERROR(__xludf.DUMMYFUNCTION("""COMPUTED_VALUE"""),"Hoàng Nhật Mai") -> Hoàng Nhật Mai | B36: 3 | C36: =IFERROR(__xludf.DUMMYFUNCTION("""COMPUTED_VALUE"""),"✅ ĐỦ HÀNG") -> ✅ ĐỦ HÀNG
A37: =IFERROR(__xludf.DUMMYFUNCTION("""COMPUTED_VALUE"""),"Hong Doan") -> Hong Doan | B37: 8 | C37: =IFERROR(__xludf.DUMMYFUNCTION("""COMPUTED_VALUE"""),"✅ ĐỦ HÀNG") -> ✅ ĐỦ HÀNG
A38: =IFERROR(__xludf.DUMMYFUNCTION("""COMPUTED_VALUE"""),"Cao The") -> Cao The | B38: 1 | C38: =IFERROR(__xludf.DUMMYFUNCTION("""COMPUTED_VALUE"""),"✅ ĐỦ HÀNG") -> ✅ ĐỦ HÀNG
A39: =IFERROR(__xludf.DUMMYFUNCTION("""COMPUTED_VALUE"""),"Ngọc Hiền") -> Ngọc Hiền | B39: 8 | C39: =IFERROR(__xludf.DUMMYFUNCTION("""COMPUTED_VALUE"""),"✅ ĐỦ HÀNG") -> ✅ ĐỦ HÀNG
A40: =IFERROR(__xludf.DUMMYFUNCTION("""COMPUTED_VALUE"""),"Huyền Trang") -> Huyền Trang | B40: 11 | C40: =IFERROR(__xludf.DUMMYFUNCTION("""COMPUTED_VALUE"""),"✅ ĐỦ HÀNG") -> ✅ ĐỦ HÀNG
A41: =IFERROR(__xludf.DUMMYFUNCTION("""COMPUTED_VALUE"""),"Li Ly") -> Li Ly | B41: 30 | C41: =IFERROR(__xludf.DUMMYFUNCTION("""COMPUTED_VALUE"""),"✅ ĐỦ HÀNG") -> ✅ ĐỦ HÀNG
A42: =IFERROR(__xludf.DUMMYFUNCTION("""COMPUTED_VALUE"""),"Thảo Huyền ") -> Thảo Huyền | B42: 1 | C42: =IFERROR(__xludf.DUMMYFUNCTION("""COMPUTED_VALUE"""),"✅ ĐỦ HÀNG") -> ✅ ĐỦ HÀNG
A43: =IFERROR(__xludf.DUMMYFUNCTION("""COMPUTED_VALUE"""),"Huyền Thỏ") -> Huyền Thỏ | B43: 8 | C43: =IFERROR(__xludf.DUMMYFUNCTION("""COMPUTED_VALUE"""),"✅ ĐỦ HÀNG") -> ✅ ĐỦ HÀNG
A44: =IFERROR(__xludf.DUMMYFUNCTION("""COMPUTED_VALUE"""),"Trà Mei") -> Trà Mei | B44: 1 | C44: =IFERROR(__xludf.DUMMYFUNCTION("""COMPUTED_VALUE"""),"✅ ĐỦ HÀNG") -> ✅ ĐỦ HÀNG
A45: =IFERROR(__xludf.DUMMYFUNCTION("""COMPUTED_VALUE"""),"Vân Trang ") -> Vân Trang | B45: 1 | C45: =IFERROR(__xludf.DUMMYFUNCTION("""COMPUTED_VALUE"""),"✅ ĐỦ HÀNG") -> ✅ ĐỦ HÀNG
A46: =IFERROR(__xludf.DUMMYFUNCTION("""COMPUTED_VALUE"""),"Nguyễn Hoàng") -> Nguyễn Hoàng | B46: 2 | C46: =IFERROR(__xludf.DUMMYFUNCTION("""COMPUTED_VALUE"""),"✅ ĐỦ HÀNG") -> ✅ ĐỦ HÀNG
A47: =IFERROR(__xludf.DUMMYFUNCTION("""COMPUTED_VALUE"""),"Sami Sami") -> Sami Sami | B47: 4 | C47: =IFERROR(__xludf.DUMMYFUNCTION("""COMPUTED_VALUE"""),"✅ ĐỦ HÀNG") -> ✅ ĐỦ HÀNG
A48: =IFERROR(__xludf.DUMMYFUNCTION("""COMPUTED_VALUE"""),"Yến Nhi") -> Yến Nhi | B48: 15 | C48: =IFERROR(__xludf.DUMMYFUNCTION("""COMPUTED_VALUE"""),"✅ ĐỦ HÀNG") -> ✅ ĐỦ HÀNG
A49: =IFERROR(__xludf.DUMMYFUNCTION("""COMPUTED_VALUE"""),"Nhung Đỗ") -> Nhung Đỗ | B49: 23 | C49: =IFERROR(__xludf.DUMMYFUNCTION("""COMPUTED_VALUE"""),"✅ ĐỦ HÀNG") -> ✅ ĐỦ HÀNG
A50: =IFERROR(__xludf.DUMMYFUNCTION("""COMPUTED_VALUE"""),"Hà Nhi") -> Hà Nhi | B50: 2 | C50: =IFERROR(__xludf.DUMMYFUNCTION("""COMPUTED_VALUE"""),"✅ ĐỦ HÀNG") -> ✅ ĐỦ HÀNG
A51: =IFERROR(__xludf.DUMMYFUNCTION("""COMPUTED_VALUE"""),"Hương Nhật") -> Hương Nhật | B51: 7 | C51: =IFERROR(__xludf.DUMMYFUNCTION("""COMPUTED_VALUE"""),"✅ ĐỦ HÀNG") -> ✅ ĐỦ HÀNG
A52: =IFERROR(__xludf.DUMMYFUNCTION("""COMPUTED_VALUE"""),"Anh Kieu Bao") -> Anh Kieu Bao | B52: 1 | C52: =IFERROR(__xludf.DUMMYFUNCTION("""COMPUTED_VALUE"""),"✅ ĐỦ HÀNG") -> ✅ ĐỦ HÀNG
A53: =IFERROR(__xludf.DUMMYFUNCTION("""COMPUTED_VALUE"""),"Trangg Tũnn") -> Trangg Tũnn | B53: 3 | C53: =IFERROR(__xludf.DUMMYFUNCTION("""COMPUTED_VALUE"""),"✅ ĐỦ HÀNG") -> ✅ ĐỦ HÀNG
A54: =IFERROR(__xludf.DUMMYFUNCTION("""COMPUTED_VALUE"""),"Ngọc Dung") -> Ngọc Dung | B54: 4 | C54: =IFERROR(__xludf.DUMMYFUNCTION("""COMPUTED_VALUE"""),"✅ ĐỦ HÀNG") -> ✅ ĐỦ HÀNG | D54: Da gui | E54: 16:06:02 21/3/2026
A55: =IFERROR(__xludf.DUMMYFUNCTION("""COMPUTED_VALUE"""),"Nguyen Yen Nhi") -> Nguyen Yen Nhi | B55: 7 | C55: =IFERROR(__xludf.DUMMYFUNCTION("""COMPUTED_VALUE"""),"✅ ĐỦ HÀNG") -> ✅ ĐỦ HÀNG
A56: =IFERROR(__xludf.DUMMYFUNCTION("""COMPUTED_VALUE"""),"Khánh Hoà ") -> Khánh Hoà | B56: 1 | C56: =IFERROR(__xludf.DUMMYFUNCTION("""COMPUTED_VALUE"""),"✅ ĐỦ HÀNG") -> ✅ ĐỦ HÀNG
A57: =IFERROR(__xludf.DUMMYFUNCTION("""COMPUTED_VALUE"""),"Hồng Nhi") -> Hồng Nhi | B57: 2 | C57: =IFERROR(__xludf.DUMMYFUNCTION("""COMPUTED_VALUE"""),"✅ ĐỦ HÀNG") -> ✅ ĐỦ HÀNG
A58: =IFERROR(__xludf.DUMMYFUNCTION("""COMPUTED_VALUE"""),"Huyền Trang ") -> Huyền Trang | B58: 1 | C58: =IFERROR(__xludf.DUMMYFUNCTION("""COMPUTED_VALUE"""),"✅ ĐỦ HÀNG") -> ✅ ĐỦ HÀNG
A59: =IFERROR(__xludf.DUMMYFUNCTION("""COMPUTED_VALUE"""),"Hoàng Huyền") -> Hoàng Huyền | B59: 2 | C59: =IFERROR(__xludf.DUMMYFUNCTION("""COMPUTED_VALUE"""),"✅ ĐỦ HÀNG") -> ✅ ĐỦ HÀNG
A60: =IFERROR(__xludf.DUMMYFUNCTION("""COMPUTED_VALUE"""),"Trần T Thuỳ") -> Trần T Thuỳ | B60: 1 | C60: =IFERROR(__xludf.DUMMYFUNCTION("""COMPUTED_VALUE"""),"✅ ĐỦ HÀNG") -> ✅ ĐỦ HÀNG
A61: =IFERROR(__xludf.DUMMYFUNCTION("""COMPUTED_VALUE"""),"Ty Ty") -> Ty Ty | B61: 2 | C61: =IFERROR(__xludf.DUMMYFUNCTION("""COMPUTED_VALUE"""),"✅ ĐỦ HÀNG") -> ✅ ĐỦ HÀNG
A62: =IFERROR(__xludf.DUMMYFUNCTION("""COMPUTED_VALUE"""),"Phạm Thuý") -> Phạm Thuý | B62: 5 | C62: =IFERROR(__xludf.DUMMYFUNCTION("""COMPUTED_VALUE"""),"✅ ĐỦ HÀNG") -> ✅ ĐỦ HÀNG
A63: =IFERROR(__xludf.DUMMYFUNCTION("""COMPUTED_VALUE"""),"Chanh Lê") -> Chanh Lê | B63: 8 | C63: =IFERROR(__xludf.DUMMYFUNCTION("""COMPUTED_VALUE"""),"✅ ĐỦ HÀNG") -> ✅ ĐỦ HÀNG
A64: =IFERROR(__xludf.DUMMYFUNCTION("""COMPUTED_VALUE"""),"Thanh Tiền") -> Thanh Tiền | B64: 1 | C64: =IFERROR(__xludf.DUMMYFUNCTION("""COMPUTED_VALUE"""),"✅ ĐỦ HÀNG") -> ✅ ĐỦ HÀNG
A65: =IFERROR(__xludf.DUMMYFUNCTION("""COMPUTED_VALUE"""),"Bùi Thu Hiền") -> Bùi Thu Hiền | B65: 4 | C65: =IFERROR(__xludf.DUMMYFUNCTION("""COMPUTED_VALUE"""),"✅ ĐỦ HÀNG") -> ✅ ĐỦ HÀNG
A66: =IFERROR(__xludf.DUMMYFUNCTION("""COMPUTED_VALUE"""),"Thuận Lê") -> Thuận Lê | B66: 1 | C66: =IFERROR(__xludf.DUMMYFUNCTION("""COMPUTED_VALUE"""),"✅ ĐỦ HÀNG") -> ✅ ĐỦ HÀNG
A67: =IFERROR(__xludf.DUMMYFUNCTION("""COMPUTED_VALUE"""),"Hạ Trang") -> Hạ Trang | B67: 3 | C67: =IFERROR(__xludf.DUMMYFUNCTION("""COMPUTED_VALUE"""),"✅ ĐỦ HÀNG") -> ✅ ĐỦ HÀNG
A68: =IFERROR(__xludf.DUMMYFUNCTION("""COMPUTED_VALUE"""),"Huyền Nga") -> Huyền Nga | B68: 3 | C68: =IFERROR(__xludf.DUMMYFUNCTION("""COMPUTED_VALUE"""),"✅ ĐỦ HÀNG") -> ✅ ĐỦ HÀNG
A69: =IFERROR(__xludf.DUMMYFUNCTION("""COMPUTED_VALUE"""),"Thư Thư") -> Thư Thư | B69: 2 | C69: =IFERROR(__xludf.DUMMYFUNCTION("""COMPUTED_VALUE"""),"✅ ĐỦ HÀNG") -> ✅ ĐỦ HÀNG
A70: =IFERROR(__xludf.DUMMYFUNCTION("""COMPUTED_VALUE"""),"Vũ Tuyền") -> Vũ Tuyền | B70: 7 | C70: =IFERROR(__xludf.DUMMYFUNCTION("""COMPUTED_VALUE"""),"✅ ĐỦ HÀNG") -> ✅ ĐỦ HÀNG
A71: =IFERROR(__xludf.DUMMYFUNCTION("""COMPUTED_VALUE"""),"Hồ Thị Hải") -> Hồ Thị Hải | B71: 2 | C71: =IFERROR(__xludf.DUMMYFUNCTION("""COMPUTED_VALUE"""),"✅ ĐỦ HÀNG") -> ✅ ĐỦ HÀNG
A72: =IFERROR(__xludf.DUMMYFUNCTION("""COMPUTED_VALUE"""),"Linh Đa Trần") -> Linh Đa Trần | B72: 2 | C72: =IFERROR(__xludf.DUMMYFUNCTION("""COMPUTED_VALUE"""),"✅ ĐỦ HÀNG") -> ✅ ĐỦ HÀNG
A73: =IFERROR(__xludf.DUMMYFUNCTION("""COMPUTED_VALUE"""),"Tâm Hồ") -> Tâm Hồ | B73: 3 | C73: =IFERROR(__xludf.DUMMYFUNCTION("""COMPUTED_VALUE"""),"✅ ĐỦ HÀNG") -> ✅ ĐỦ HÀNG
A74: =IFERROR(__xludf.DUMMYFUNCTION("""COMPUTED_VALUE"""),"Ng T. Kim Dungg") -> Ng T. Kim Dungg | B74: 1 | C74: =IFERROR(__xludf.DUMMYFUNCTION("""COMPUTED_VALUE"""),"✅ ĐỦ HÀNG") -> ✅ ĐỦ HÀNG
A75: =IFERROR(__xludf.DUMMYFUNCTION("""COMPUTED_VALUE"""),"Minh Nguyệt") -> Minh Nguyệt | B75: 7 | C75: =IFERROR(__xludf.DUMMYFUNCTION("""COMPUTED_VALUE"""),"✅ ĐỦ HÀNG") -> ✅ ĐỦ HÀNG
A76: =IFERROR(__xludf.DUMMYFUNCTION("""COMPUTED_VALUE"""),"Kim Chi") -> Kim Chi | B76: 7 | C76: =IFERROR(__xludf.DUMMYFUNCTION("""COMPUTED_VALUE"""),"✅ ĐỦ HÀNG") -> ✅ ĐỦ HÀNG
A77: =IFERROR(__xludf.DUMMYFUNCTION("""COMPUTED_VALUE"""),"Huyền Trang 2") -> Huyền Trang 2 | B77: 2 | C77: =IFERROR(__xludf.DUMMYFUNCTION("""COMPUTED_VALUE"""),"✅ ĐỦ HÀNG") -> ✅ ĐỦ HÀNG
A78: =IFERROR(__xludf.DUMMYFUNCTION("""COMPUTED_VALUE"""),"Phạm Thị Diệu Linh") -> Phạm Thị Diệu Linh | B78: 1 | C78: =IFERROR(__xludf.DUMMYFUNCTION("""COMPUTED_VALUE"""),"✅ ĐỦ HÀNG") -> ✅ ĐỦ HÀNG
A79: =IFERROR(__xludf.DUMMYFUNCTION("""COMPUTED_VALUE"""),"Đàm Mai Lan") -> Đàm Mai Lan | B79: 1 | C79: =IFERROR(__xludf.DUMMYFUNCTION("""COMPUTED_VALUE"""),"✅ ĐỦ HÀNG") -> ✅ ĐỦ HÀNG
A80: =IFERROR(__xludf.DUMMYFUNCTION("""COMPUTED_VALUE"""),"Nguyễn Thị Hiền") -> Nguyễn Thị Hiền | B80: 5 | C80: =IFERROR(__xludf.DUMMYFUNCTION("""COMPUTED_VALUE"""),"✅ ĐỦ HÀNG") -> ✅ ĐỦ HÀNG
A81: =IFERROR(__xludf.DUMMYFUNCTION("""COMPUTED_VALUE"""),"Thiên An") -> Thiên An | B81: 3 | C81: =IFERROR(__xludf.DUMMYFUNCTION("""COMPUTED_VALUE"""),"✅ ĐỦ HÀNG") -> ✅ ĐỦ HÀNG
A82: =IFERROR(__xludf.DUMMYFUNCTION("""COMPUTED_VALUE"""),"Nhung Kul's") -> Nhung Kul's | B82: 1 | C82: =IFERROR(__xludf.DUMMYFUNCTION("""COMPUTED_VALUE"""),"✅ ĐỦ HÀNG") -> ✅ ĐỦ HÀNG
A83: =IFERROR(__xludf.DUMMYFUNCTION("""COMPUTED_VALUE"""),"Thiên Lý") -> Thiên Lý | B83: 1 | C83: =IFERROR(__xludf.DUMMYFUNCTION("""COMPUTED_VALUE"""),"✅ ĐỦ HÀNG") -> ✅ ĐỦ HÀNG
A84: =IFERROR(__xludf.DUMMYFUNCTION("""COMPUTED_VALUE"""),"Trang Trần") -> Trang Trần | B84: 6 | C84: =IFERROR(__xludf.DUMMYFUNCTION("""COMPUTED_VALUE"""),"✅ ĐỦ HÀNG") -> ✅ ĐỦ HÀNG
A85: =IFERROR(__xludf.DUMMYFUNCTION("""COMPUTED_VALUE"""),"Thu Hường Nguyễn") -> Thu Hường Nguyễn | B85: 12 | C85: =IFERROR(__xludf.DUMMYFUNCTION("""COMPUTED_VALUE"""),"✅ ĐỦ HÀNG") -> ✅ ĐỦ HÀNG
A86: =IFERROR(__xludf.DUMMYFUNCTION("""COMPUTED_VALUE"""),"Duong Cam Tu") -> Duong Cam Tu | B86: 3 | C86: =IFERROR(__xludf.DUMMYFUNCTION("""COMPUTED_VALUE"""),"✅ ĐỦ HÀNG") -> ✅ ĐỦ HÀNG
A87: =IFERROR(__xludf.DUMMYFUNCTION("""COMPUTED_VALUE"""),"Đỗ Duyên") -> Đỗ Duyên | B87: 4 | C87: =IFERROR(__xludf.DUMMYFUNCTION("""COMPUTED_VALUE"""),"✅ ĐỦ HÀNG") -> ✅ ĐỦ HÀNG
A88: =IFERROR(__xludf.DUMMYFUNCTION("""COMPUTED_VALUE"""),"Loan Trần") -> Loan Trần | B88: 5 | C88: =IFERROR(__xludf.DUMMYFUNCTION("""COMPUTED_VALUE"""),"✅ ĐỦ HÀNG") -> ✅ ĐỦ HÀNG
A89: =IFERROR(__xludf.DUMMYFUNCTION("""COMPUTED_VALUE"""),"Lê Hải Yến") -> Lê Hải Yến | B89: 4 | C89: =IFERROR(__xludf.DUMMYFUNCTION("""COMPUTED_VALUE"""),"✅ ĐỦ HÀNG") -> ✅ ĐỦ HÀNG
A90: =IFERROR(__xludf.DUMMYFUNCTION("""COMPUTED_VALUE"""),"Linh Nguyen") -> Linh Nguyen | B90: 11 | C90: =IFERROR(__xludf.DUMMYFUNCTION("""COMPUTED_VALUE"""),"✅ ĐỦ HÀNG") -> ✅ ĐỦ HÀNG
A91: =IFERROR(__xludf.DUMMYFUNCTION("""COMPUTED_VALUE"""),"Đào Thị Thu") -> Đào Thị Thu | B91: 1 | C91: =IFERROR(__xludf.DUMMYFUNCTION("""COMPUTED_VALUE"""),"✅ ĐỦ HÀNG") -> ✅ ĐỦ HÀNG
A92: =IFERROR(__xludf.DUMMYFUNCTION("""COMPUTED_VALUE"""),"Thuỳ Trangg") -> Thuỳ Trangg | B92: 5 | C92: =IFERROR(__xludf.DUMMYFUNCTION("""COMPUTED_VALUE"""),"✅ ĐỦ HÀNG") -> ✅ ĐỦ HÀNG
A93: =IFERROR(__xludf.DUMMYFUNCTION("""COMPUTED_VALUE"""),"Thuý Hạnh") -> Thuý Hạnh | B93: 3 | C93: =IFERROR(__xludf.DUMMYFUNCTION("""COMPUTED_VALUE"""),"✅ ĐỦ HÀNG") -> ✅ ĐỦ HÀNG
A94: =IFERROR(__xludf.DUMMYFUNCTION("""COMPUTED_VALUE"""),"chup bi Kiều") -> chup bi Kiều | B94: 1 | C94: =IFERROR(__xludf.DUMMYFUNCTION("""COMPUTED_VALUE"""),"✅ ĐỦ HÀNG") -> ✅ ĐỦ HÀNG
A95: =IFERROR(__xludf.DUMMYFUNCTION("""COMPUTED_VALUE"""),"Quỳnh Như") -> Quỳnh Như | B95: 1 | C95: =IFERROR(__xludf.DUMMYFUNCTION("""COMPUTED_VALUE"""),"✅ ĐỦ HÀNG") -> ✅ ĐỦ HÀNG
A96: =IFERROR(__xludf.DUMMYFUNCTION("""COMPUTED_VALUE"""),"Khánh Nhung") -> Khánh Nhung | B96: 2 | C96: =IFERROR(__xludf.DUMMYFUNCTION("""COMPUTED_VALUE"""),"✅ ĐỦ HÀNG") -> ✅ ĐỦ HÀNG
A97: =IFERROR(__xludf.DUMMYFUNCTION("""COMPUTED_VALUE"""),"Nguyễn Thu Thảo") -> Nguyễn Thu Thảo | B97: 1 | C97: =IFERROR(__xludf.DUMMYFUNCTION("""COMPUTED_VALUE"""),"✅ ĐỦ HÀNG") -> ✅ ĐỦ HÀNG
A98: =IFERROR(__xludf.DUMMYFUNCTION("""COMPUTED_VALUE"""),"Hằng Min's") -> Hằng Min's | B98: 1 | C98: =IFERROR(__xludf.DUMMYFUNCTION("""COMPUTED_VALUE"""),"✅ ĐỦ HÀNG") -> ✅ ĐỦ HÀNG
A99: =IFERROR(__xludf.DUMMYFUNCTION("""COMPUTED_VALUE"""),"Sáu Nguyễn") -> Sáu Nguyễn | B99: 1 | C99: =IFERROR(__xludf.DUMMYFUNCTION("""COMPUTED_VALUE"""),"✅ ĐỦ HÀNG") -> ✅ ĐỦ HÀNG
A100: =IFERROR(__xludf.DUMMYFUNCTION("""COMPUTED_VALUE"""),"Hà Trần") -> Hà Trần | B100: 6 | C100: =IFERROR(__xludf.DUMMYFUNCTION("""COMPUTED_VALUE"""),"✅ ĐỦ HÀNG") -> ✅ ĐỦ HÀNG
...

Sheet CATALOG
A1: Mã SP | B1: Tên SP | C1: Giá bán | D1: Giá nhập | E1: Lợi nhuận/SP | F1: Margin % | G1: Size | H1: Màu | I1: Đã bán | J1: Loại | K1: Cột 1
A2: M006 | B2: Áo dây | C2: 750 | D2: 350 | E2: 400 | F2: 0.53333333 | G2: FZ | H2: BE,TRẮNG,XÁM,ĐEN | I2: 129 | J2: Áo | K2: M006.jpg
A3: 8876 | B3: Ba Lỗ có mút | C3: 990 | D3: 500 | E3: 490 | F3: 0.49494949 | G3: M,S | H3: HỒNG,NÂU,TRẮNG,TÍM,ĐEN,ĐỎ | I3: 70 | J3: Áo
A4: M001 | B4: Giày howell | C4: 1990 | D4: 1340 | E4: 650 | F4: 0.32663317 | G4: 35,36,37,38,39,40 | H4: BE,ĐEN | I4: 67 | J4: Giày
A5: 8748 | B5: Jean lửng xanh đậm | C5: 1800 | D5: 1400 | E5: 400 | F5: 0.22222222 | G5: L,M,S | H5: XANH THAN | I5: 55 | J5: Quần
A6: 8740 | B6: Trắng xinh | C6: 1600 | D6: 1000 | E6: 600 | F6: 0.375 | G6: M,S | H6: BE,TRẮNG | I6: 45 | J6: Khác
A7: 8886 | B7: Phông trơn ngắn tay | C7: 1090 | D7: 650 | E7: 610 | F7: 0.55963303 | G7: M,S | H7: HỒNG,NÂU,TRẮNG,XÁM,XÁM ĐẬM,ĐEN,ĐỎ | I7: 41 | J7: Áo
A8: 81813 | B8: Phông giấy DM | C8: 1100 | D8: 600 | E8: 525 | F8: 0.47727273 | G8: FZ | H8: HỒNG,TRẮNG,VÀNG,XANH NHẠT,XÁM,ĐEN,ĐỎ | I8: 33 | J8: Áo
A9: 8865 | B9: Jean xanh đậm | C9: 2500 | D9: 2000 | E9: 500 | F9: 0.2 | G9: L,M,S | H9: XANH THAN | I9: 21 | J9: Quần
A10: 9369 | B10: Jean đậm 95cm | C10: 2600 | D10: 2000 | E10: 600 | F10: 0.23076923 | G10: M,S | H10: XANH THAN | I10: 20 | J10: Quần
A11: 8867 | B11: Phông ngựa | C11: 1200 | D11: 700 | E11: 500 | F11: 0.41666667 | G11: M,S | H11: HỒNG,TRẮNG,XANH THAN,XÁM,ĐEN | I11: 17 | J11: Áo
A12: 8319 | B12: Quần giả váy xanh | C12: 1900 | D12: 1420 | E12: 480 | F12: 0.25263158 | G12: M,S | H12: XANH THAN | I12: 15 | J12: Quần
A13: 7957 | B13: Đùi sơ mi | C13: 1400 | D13: 900 | E13: 900 | F13: 0.64285714 | G13: M,S | H13: TRẮNG,XÁM,ĐEN | I13: 13 | J13: Quần
A14: 5709 | B14: Jean EN&ER | C14: 2350 | D14: 1650 | E14: 700 | F14: 0.29787234 | G14: L,M,S | H14: XANH NHẠT | I14: 12 | J14: Quần
A15: 9094 | B15: Bộ Nỉ | C15: 2400 | D15: 1700 | E15: 700 | F15: 0.29166667 | G15: M,S | H15: HỒNG,XANH THAN,XÁM | I15: 12 | J15: Set/Bộ
A16: 7249 | B16: Jean rộng xanh | C16: 2300 | D16: 1800 | E16: 1800 | F16: 0.7826087 | G16: M,S | H16: XANH THAN | I16: 9 | J16: Quần
... A19: 9140 | B19: Hở vai | C19: 1500 | D19: 900 | E19: 600 | F19: 0.4 | G19: M,S | H19: ĐEN,ĐỎ | I19: 6 | J19: Áo
A20: M005 | B20: Giày Love | C20: 2350 | D20: 1750 | E20: 2350 | F20: 0 | G20: 35,36,37,38,39,40 | H20: BE,NÂU,ĐEN | I20: 6 | J20: Giày
A21: 7458 | B21: Set áo trễ vai | C21: 1600 | D21: 1100 | E21: 1100 | F21: 0.6875 | G21: M,S | H21: ĐEN | I21: 4 | J21: Áo
A22: 8625 | B22: Trễ vai xanh | C22: 1550 | D22: 1050 | E22: 1050 | F22: 0.67741935 | G22: M,S | H22: XANH THAN | I22: 4 | J22: Áo
A23: 8514 | B23: Áo Ren | C23: 1200 | D23: 700 | E23: 700 | F23: 0.58333333 | G23: M,S | H23: BE | I23: 3 | J23: Áo
A24: 7137 | B24: Jean xanh loe | C24: 2500 | D24: 2000 | E24: 1920 | F24: 0.768 | G24: S | H24: XANH THAN | I24: 2 | J24: Quần
A25: 7307 | B25: Loe nâu | C25: 2300 | D25: 1800 | E25: 1800 | F25: 0.7826087 | G25: M,S | H25: BE,NÂU | I25: 2 | J25: Quần
A26: 8521 | B26: Jean Rộng Nâu | C26: 2400 | D26: 1900 | E26: 1930 | F26: 0.80416667 | G26: M,S | H26: NÂU | I26: 2 | J26: Quần
A27: M003 | B27: Đồ ngủ | C27: 1290 | D27: 800 | E27: 790 | F27: 0.6124031 | G27: L | H27: ĐEN | I27: 2 | J27: Set/Bộ
A29: MU01 | B29: Mũ Polo | C29: 1200 | D29: 650 | E29: 550 | F29: 0.45833333 | H29: NÂU NHẠT,BE,NÂU,HỒNG | I29: 0 | J29: Khác
A30: TRA1 | B30: Trà Táo Đỏ | C30: 1390 | D30: 890 | E30: 500 | F30: 0.35971223 | I30: 0 | J30: Khác
A31: 8897 | B31: Áo trễ vai nơ | C31: 1200 | D31: 730 | E31: 470 | F31: 0.39166667 | G31: S,M | H31: TRẮNG | I31: 0 | J31: Áo
A32: BRA4 | B32: Bra set số 4 | C32: 1990 | D32: 1150 | E32: 840 | F32: 0.42211055 | I32: 0 | J32: Áo
A33: CHIP1 | B33: Set 10 quần lót | C33: 1550 | D33: 1050 | E33: 500 | F33: 0.32258065 | I33: 0 | J33: Quần
A34: BRA10 | B34: Set bra số 10 | C34: 1990 | D34: 1150 | E34: 840 | F34: 0.42211055 | I34: 0 | J34: Áo
A35: 9091 | B35: Quần đùi jean | C35: 1950 | D35: 1300 | E35: 650 | F35: 0.33333333 | G35: S,M,L | H35: XANH THAN | I35: 0 | J35: Quần
A36: 8116 | B36: Quần jean trơn | C36: 2490 | D36: 1700 | E36: 790 | F36: 0.31726908 | G36: S,M,L | H36: XANH THAN, TRẮNG | I36: 0 | J36: Quần
A37: 8558 | B37: Thun trơn có mút | C37: 1390 | D37: 790 | E37: 600 | F37: 0.43165468 | I37: 0 | J37: Áo
A38: M007 | B38: TÊN KHÁCH | C38: 1 | D38: 0 | E38: 1 | F38: 0 | I38: 0
A39: 9258 | B39: Quần jean khuy túi | C39: 2450 | D39: 1750 | E39: 700 | F39: 0.28571429 | I39: 0 | J39: Quần
A40: 8825 | B40: Áo chấm bi | C40: 1450 | D40: 800 | E40: 650 | F40: 0.44827586 | G40: S,M | H40: ĐEN, TRẮNG | I40: 0 | J40: Áo
A41: GIAY1 | B41: Giày bệt đính hoa | C41: 2200 | D41: 1500 | E41: 700 | F41: 0.31818182 | I41: 0 | K41: https://drive.google.com/uc?export=view&id=1gRZGgsaAlixTqG-fw_CaTSxsDz7UJNYp
A42: M008 | B42: Áo chống nắng Catkaiser | C42: 1650 | D42: 1000 | E42: 650 | F42: 0.39393939 | I42: 0 | K42: https://drive.google.com/uc?export=view&id=1qFN_ZPeHCdAPmzweF-E1DPzUDXD4-E0V
A43: GIAY2 | B43: Dép xỏ ngón | C43: 1950 | D43: 1300 | E43: 650 | F43: 0.33333333 | I43: 0
A44: 5022 | B44: Dép xỏ ngón | C44: 1950 | D44: 1300 | E44: 650 | F44: 0.33333333 | I44: 0
A45: 1302 | B45: Phông giấy dài tay | C45: 1200 | D45: 650 | E45: 550 | F45: 0.45833333 | I45: 0 | J45: Áo | K45: https://drive.google.com/uc?export=view&id=1haFrYlClnn_4SD0mDZyE7Hh2u-Z7ck-m
A46: 8610 | B46: Áo Thun Trơn basic | C46: 1190 | D46: 650 | E46: 540 | F46: 0.45378151 | I46: 0 | J46: Áo
A47: CK98118 | B47: Quần loe đen Catkaiser | C47: 1800 | D47: 1170 | E47: 630 | F47: 0.35 | I47: 0 | J47: Quần | K47: https://drive.google.com/uc?export=view&id=1TC0p5pIKaLn2YKGMcG7p1Qz8t23d-Wpi
A48: 8765 | B48: Áo sơ mi trắng ren | C48: 1800 | D48: 1280 | E48: 520 | F48: 0.28888889 | I48: 0 | J48: Áo
A49: 6612 | B49: Áo ba lỗ có móc treo | C49: 850 | D49: 470 | E49: 380 | F49: 0.44705882 | I49: 0 | J49: Áo | K49: https://drive.google.com/uc?export=view&id=1xYIx5Ce1_Q0-qJs8j00BOsARTmvE8Cnj
A50: 9425 | B50: Quần jean wgwe | C50: 2700 | D50: 2000 | E50: 700 | F50: 0.25925926 | I50: 0 | J50: Quần
A51: 3225 | B51: Jean EN&ER 98cm | C51: 2350 | D51: 1700 | E51: 650 | F51: 0.27659574 | I51: 0 | J51: Quần
A52: 8321 | B52: Áo Charm Paris | C52: 1350 | D52: 700 | E52: 650 | F52: 0.48148148 | I52: 0 | J52: Áo | K52: https://drive.google.com/uc?export=view&id=1iS2bq0Dpu0U_0XdwnAvNunOiNTedNO7n
A53: 9275 | B53: Wgwe trễ vai | C53: 1390 | D53: 750 | E53: 640 | F53: 0.46043165 | I53: 0 | K53: https://drive.google.com/uc?export=view&id=1WXriGQa1X6gRDHOPk2BM9dkamEwYh9Ro
A54: 9277 | B54: Wgwe Phông cổ ren | C54: 1415 | D54: 775 | E54: 640 | F54: 0.45229682 | I54: 0
A55: 9083 | B55: Wgwe quần jean Lửng | C55: 2400 | D55: 1800 | E55: 600 | F55: 0.25 | I55: 0
A56: 8770 | B56: Polo len tăm | C56: 1690 | D56: 1060 | E56: 630 | F56: 0.37278107 | I56: 0 | K56: https://drive.google.com/uc?export=view&id=1F-sa9s7-E_d_ZvUuuQ6OagclmipjD3ft
A57: BRA1 | B57: Bra cup ngực mẫu 1 | C57: 725 | D57: 325 | E57: 400 | F57: 0.55172414 | I57: 0 | J57: Áo | K57: https://drive.google.com/uc?export=view&id=1mlS03U1_3WXR4q6ElJiW72FpvKBnRDG5
A58: BRA2 | B58: bra hở lưng mẫu 2 | C58: 725 | D58: 325 | E58: 400 | F58: 0.55172414 | I58: 0
A59: M009 | B59: Quần đùi nam Jeep | C59: 845 | D59: 445 | E59: 400 | F59: 0.47337278 | I59: 0 | J59: Quần | K59: https://drive.google.com/uc?export=view&id=1iBcuXcyXFWfXE08ous3zNvzLLe1LVYCa
A60: 9301 | B60: Áo wgwe ren | C60: 1900 | D60: 1300 | E60: 600 | F60: 0.31578947 | I60: 0 | J60: Áo
A61: 9031 | B61: Áo ren wgwe | C61: 1900 | D61: 1300 | E61: 600 | F61: 0.31578947 | I61: 0 | J61: Áo | K61: https://drive.google.com/uc?export=view&id=1Cbq3Jpfow-D66QnxD2coy6f04UebXTbG
A62: BRA3 | B62: Bra độn | C62: 725 | D62: 325 | E62: 400 | F62: 0.55172414 | I62: 0 | J62: Áo
A63: 5007 | B63: Quần trơn wgwe | C63: 1800 | D63: 1200 | E63: 600 | F63: 0.33333333 | I63: 0
A64: 92212 | B64: Áo chống nắng hers | C64: 1700 | D64: 1100 | E64: 600 | F64: 0.35294118 | I64: 0 | J64: Áo
A65: M010 | B65: Set quần chip nơ 10c | C65: 1550 | D65: 950 | E65: 600 | F65: 0.38709677 | I65: 0
A66: QUAN1 | B66: Set 2 quần chip gen | C66: 1200 | D66: 590 | E66: 610 | F66: 0.50833333 | I66: 0
A67: P230MTX362-T800 | B67: Dép Jeep | C67: 2900 | D67: 2170 | E67: 730 | F67: 0.25172414 | I67: 0
A68: 8888 | B68: Áo voan chấm bi | C68: 1700 | D68: 1100 | E68: 600 | F68: 0.35294118 | I68: 0
A69: P661W12375 | B69: GIÀY JEEP HỒNG TÍM | C69: 7000 | D69: 5500 | E69: 1500 | F69: 0.21428571 | I69: 0
A70: M011 | B70: Set son 3ce | C70: 2900 | D70: 2200 | E70: 700 | F70: 0.24137931 | I70: 0
A71: P651W13129 | B71: Giày JEEP ĐẾ RẮNG | C71: 7000 | D71: 5500 | E71: 1500 | F71: 0.21428571 | I71: 0
A72: P661W13310 | B72: Giày jeep quai chéo | C72: 7000 | D72: 5500 | E72: 1500 | F72: 0.21428571 | I72: 0
A73: P661W13363 | B73: Giày jeep nơ | C73: 7000 | D73: 5500 | E73: 1500 | F73: 0.21428571 | I73: 0
A74: PE232WAS632 | B74: jeep sandal | C74: 6800 | D74: 5400 | E74: 1400 | F74: 0.20588235 | I74: 0
A75: P651W13112C | B75: Giày jeep bestseller | C75: 6990 | D75: 5400 | E75: 1590 | F75: 0.22746781 | I75: 0
A76: PX231WAS575 | B76: Jeep da lộn quai to | C76: 7600 | D76: 6300 | E76: 1300 | F76: 0.17105263 | I76: 0
A77: M012 | B77: Túi vải 2 mặt | C77: 990 | D77: 490 | E77: 500 | F77: 0.50505051 | I77: 0
A78: M013 | B78: Sữa tắm nước hoa | C78: 1700 | D78: 1200 | E78: 500 | F78: 0.29411765 | I78: 0
A79: 9500 | B79: Quần wgwe xanh nhạt | C79: 2690 | D79: 1990 | E79: 700 | F79: 0.26022305 | I79: 0
A80: M014 | B80: Bộ máy làm tóc | C80: 4200 | D80: 3300 | E80: 900 | F80: 0.21428571 | I80: 0
A81: DEP1 | B81: Dép xỏ độn 4p | C81: 1790 | D81: 1190 | E81: 600 | F81: 0.33519553 | I81: 0
A82: 8684 | B82: Áo váy wgwe | C82: 1950 | D82: 1350 | E82: 600 | F82: 0.30769231 | I82: 0
A83: 8657 | B83: Vây dây wgwe chấm bi | C83: 2100 | D83: 1500 | E83: 600 | F83: 0.28571429 | I83: 0
A84: M015 | B84: Áo chống nắng Jeep | C84: 1650 | D84: 1050 | E84: 609 | F84: 0.36708861 | I84: 0
A85: M016 | B85: Áo polo nam Jeep | C85: 1200 | D85: 770 | E85: 430 | F85: 0.35833333 | I85: 0
A86: M017 | B86: Bộ ngủ cộc | C86: 1100 | D86: 680 | E86: 420 | F86: 0.38181818 | I86: 0
A87: TUI1 | B87: Túi vải to | C87: 1700 | D87: 1100 | E87: 600 | F87: 0.35294118 | I87: 0
A88: 1653 | B88: Set áo trắng CV sọc | C88: 2500 | D88: 1700 | E88: 800 | F88: 0.32 | I88: 0
A89: M018 | B89: Set 3 hộp dán ngực | C89: 1200 | D89: 500 | E89: 700 | F89: 0.58333333 | I89: 0
A90: 9408 | B90: Quần Loe Nỉ wgwe | C90: 1650 | D90: 1050 | E90: 600 | F90: 0.36363636 | I90: 0
A91: DEP2 | B91: Dép nhựa crocs | C91: 1900 | D91: 1300 | E91: 600 | F91: 0.31578947 | I91: 0
A92: 9064 | B92: Áo ba lỗ xoè chấm bi | C92: 1590 | D92: 1000 | E92: 590 | F92: 0.37106918 | I92: 0
A93: M019 | B93: Giày lưới | C93: 2690 | D93: 2150 | E93: 540 | F93: 0.20074349 | I93: 0
A94: 9620 | B94: Set wgwe | C94: 2390 | D94: 1790 | E94: 600 | F94: 0.25104603 | I94: 0
A95: 5670 | B95: Set váy nơ chấm bi | C95: 2990 | D95: 2400 | E95: 590 | F95: 0.19732441 | I95: 0
A96: 1639 | B96: Set Áo cam quần trắng | C96: 2990 | D96: 2400 | E96: 590 | F96: 0.19732441 | I96: 0
A97: 9717 | B97: Áo phông xoăn wgwe | C97: 1200 | D97: 650 | E97: 550 | F97: 0.45833333 | I97: 0
A98: 9289 | B98: Áo phông giấy wgwe | C98: 1100 | D98: 650 | E98: 450 | F98: 0.40909091 | I98: 0
A99: 9930 | B99: Quần jean 9 tấc | C99: 2350 | D99: 1750 | E99: 600 | F99: 0.25531915 | I99: 0
A100: PX241WAS932 | B100: Giày jeep | C100: 7400 | D100: 5900 | E100: 1500 | F100: 0.2027027 | I100: 0
A101: P661W13404 | B101: Giày jeep | C101: 7000 | D101: 5500 | E101: 1500 | F101: 0.21428571 | I101: 0
A102: M020 | B102: Hộp 10 quần lót cotton | C102: 1550 | D102: 1015 | E102: 535 | F102: 0.34516129 | I102: 0
A103: 9831 | B103: Jean mỏng ren | C103: 2590 | D103: 1990 | E103: 600 | F103: 0.23166023 | I103: 0
...

Sheet THỐNG KÊ
A1: 📊 THỐNG KÊ
B3: CHỈ SỐ | C3: GIÁ TRỊ
A4: 📋 | B4: Tổng đơn | C4: =COUNTIFS('NHẬP ĐƠN'!A2:A1000,"<>",'NHẬP ĐƠN'!I2:I1000,"<>Đã xoá") -> 938
A5: 💰 | B5: Doanh thu (¥) | C5: =SUMPRODUCT(('NHẬP ĐƠN'!I$2:I$1000<>"Đã xoá")*('NHẬP ĐƠN'!G$2:G$1000)*('NHẬP ĐƠN'!F$2:F$1000)) -> 1459900
A6: 📈 | B6: Lợi nhuận (¥) | C6: =SUMPRODUCT(('NHẬP ĐƠN'!I$2:I$1000<>"Đã xoá")*('NHẬP ĐƠN'!G$2:G$1000-IFERROR(VLOOKUP('NHẬP ĐƠN'!C$2:C$1000,CATALOG!A:D,4,FALSE),0))*('NHẬP ĐƠN'!F$2:F$1000)) -> 618320
A7: 🚚 | B7: Về kho | C7: =COUNTIF('NHẬP ĐƠN'!I2:I1000,"Về kho") -> 5
A8: ✅ | B8: Đã gửi | C8: =COUNTIF('NHẬP ĐƠN'!I2:I1000,"Đã gửi") -> 933
B10: TRẠNG THÁI | C10: SỐ
A11: ⚪ | B11: Chưa đặt | C11: =COUNTIF('NHẬP ĐƠN'!I2:I1000,"CHƯA ĐẶT") -> 0
A12: 🟡 | B12: Chờ hàng | C12: =COUNTIF('NHẬP ĐƠN'!I2:I1000,"Chờ hàng") -> 0
A13: 🟣 | B13: Đang ship | C13: =COUNTIF('NHẬP ĐƠN'!I2:I1000,"Đang ship") -> 0
A14: 🔵 | B14: Về kho | C14: =COUNTIF('NHẬP ĐƠN'!I2:I1000,"Về kho") -> 5
A15: 🟢 | B15: Đã gửi | C15: =COUNTIF('NHẬP ĐƠN'!I2:I1000,"Đã gửi") -> 933

Sheet KHÁCH HÀNG
A1: Tên khách | B1: Số đơn | C1: Tổng SL | D1: Doanh thu (¥) | E1: Giá TB | F1: Link FB | G1: Hạng | H1: 〒 | I1: 都道府県 | J1: 市区町村 | K1: 番地 | L1: 電話 | M1: Link FB
A2: =IFERROR(__xludf.DUMMYFUNCTION("SORT(UNIQUE(FILTER('NHẬP ĐƠN'!A2:A661, 'NHẬP ĐƠN'!A2:A661<>"""", 'NHẬP ĐƠN'!I2:I661<>""Đã xoá"")))"),"#REF!") -> #REF! | B2: =IF(A2="","",COUNTIFS('NHẬP ĐƠN'!A:A,A2,'NHẬP ĐƠN'!I:I,"<>Đã xoá")) -> #REF! | C2: =IF(A2="","",SUMPRODUCT(('NHẬP ĐƠN'!A$2:A$1000=A2)*('NHẬP ĐƠN'!I$2:I$1000<>"Đã xoá")*('NHẬP ĐƠN'!F$2:F$1000))) -> #REF! | D2: =IF(A2="","",SUMPRODUCT(('NHẬP ĐƠN'!A$2:A$1000=A2)*('NHẬP ĐƠN'!I$2:I$1000<>"Đã xoá")*('NHẬP ĐƠN'!G$2:G$1000)*('NHẬP ĐƠN'!F$2:F$1000))) -> #REF! | E2: =IF(B2>0,D2/B2,"") -> #REF! | F2: =IFERROR(VLOOKUP(A2,'NHẬP ĐƠN'!A:J,10,FALSE),"") | G2: =IF(A2="","",IF(OR(D2>=10000,B2>=5),"⭐ VIP",IF(B2>=3,"💎 Thân thiết","👤 Thường"))) -> #REF! | H2: 660-0085 | I2: 兵庫県 | J2: 尼崎市 | K2: 元浜町5-46-5 ( Kurahashi)
B3: =IF(A3="","",COUNTIFS('NHẬP ĐƠN'!A:A,A3,'NHẬP ĐƠN'!I:I,"<>Đã xoá")) | C3: =IF(A3="","",SUMPRODUCT(('NHẬP ĐƠN'!A$2:A$1000=A3)*('NHẬP ĐƠN'!I$2:I$1000<>"Đã xoá")*('NHẬP ĐƠN'!F$2:F$1000))) | D3: =IF(A3="","",SUMPRODUCT(('NHẬP ĐƠN'!A$2:A$1000=A3)*('NHẬP ĐƠN'!I$2:I$1000<>"Đã xoá")*('NHẬP ĐƠN'!G$2:G$1000)*('NHẬP ĐƠN'!F$2:F$1000))) | E3: =IF(B3>0,D3/B3,"") -> #DIV/0! | F3: =IFERROR(VLOOKUP(A3,'NHẬP ĐƠN'!A:J,10,FALSE),"") | G3: =IF(A3="","",IF(OR(D3>=10000,B3>=5),"⭐ VIP",IF(B3>=3,"💎 Thân thiết","👤 Thường"))) | H3: 486-0932 | I3: 愛知県 | J3: 春日井市 | K3: 松河戸町4-6-5 サンシャイン松河202
B4: =IF(A4="","",COUNTIFS('NHẬP ĐƠN'!A:A,A4,'NHẬP ĐƠN'!I:I,"<>Đã xoá")) | C4: =IF(A4="","",SUMPRODUCT(('NHẬP ĐƠN'!A$2:A$1000=A4)*('NHẬP ĐƠN'!I$2:I$1000<>"Đã xoá")*('NHẬP ĐƠN'!F$2:F$1000))) | D4: =IF(A4="","",SUMPRODUCT(('NHẬP ĐƠN'!A$2:A$1000=A4)*('NHẬP ĐƠN'!I$2:I$1000<>"Đã xoá")*('NHẬP ĐƠN'!G$2:G$1000)*('NHẬP ĐƠN'!F$2:F$1000))) | E4: =IF(B4>0,D4/B4,"") -> #DIV/0! | F4: =IFERROR(VLOOKUP(A4,'NHẬP ĐƠN'!A:J,10,FALSE),"") | G4: =IF(A4="","",IF(OR(D4>=10000,B4>=5),"⭐ VIP",IF(B4>=3,"💎 Thân thiết","👤 Thường")))
B5: =IF(A5="","",COUNTIFS('NHẬP ĐƠN'!A:A,A5,'NHẬP ĐƠN'!I:I,"<>Đã xoá")) | C5: =IF(A5="","",SUMPRODUCT(('NHẬP ĐƠN'!A$2:A$1000=A5)*('NHẬP ĐƠN'!I$2:I$1000<>"Đã xoá")*('NHẬP ĐƠN'!F$2:F$1000))) | D5: =IF(A5="","",SUMPRODUCT(('NHẬP ĐƠN'!A$2:A$1000=A5)*('NHẬP ĐƠN'!I$2:I$1000<>"Đã xoá")*('NHẬP ĐƠN'!G$2:G$1000)*('NHẬP ĐƠN'!F$2:F$1000))) | E5: =IF(B5>0,D5/B5,"") -> #DIV/0! | F5: =IFERROR(VLOOKUP(A5,'NHẬP ĐƠN'!A:J,10,FALSE),"") | G5: =IF(A5="","",IF(OR(D5>=10000,B5>=5),"⭐ VIP",IF(B5>=3,"💎 Thân thiết","👤 Thường")))
B6: =IF(A6="","",COUNTIFS('NHẬP ĐƠN'!A:A,A6,'NHẬP ĐƠN'!I:I,"<>Đã xoá")) | C6: =IF(A6="","",SUMPRODUCT(('NHẬP ĐƠN'!A$2:A$1000=A6)*('NHẬP ĐƠN'!I$2:I$1000<>"Đã xoá")*('NHẬP ĐƠN'!F$2:F$1000))) | D6: =IF(A6="","",SUMPRODUCT(('NHẬP ĐƠN'!A$2:A$1000=A6)*('NHẬP ĐƠN'!I$2:I$1000<>"Đã xoá")*('NHẬP ĐƠN'!G$2:G$1000)*('NHẬP ĐƠN'!F$2:F$1000))) | E6: =IF(B6>0,D6/B6,"") -> #DIV/0! | F6: =IFERROR(VLOOKUP(A6,'NHẬP ĐƠN'!A:J,10,FALSE),"") | G6: =IF(A6="","",IF(OR(D6>=10000,B6>=5),"⭐ VIP",IF(B6>=3,"💎 Thân thiết","👤 Thường")))
B7: =IF(A7="","",COUNTIFS('NHẬP ĐƠN'!A:A,A7,'NHẬP ĐƠN'!I:I,"<>Đã xoá")) | C7: =IF(A7="","",SUMPRODUCT(('NHẬP ĐƠN'!A$2:A$1000=A7)*('NHẬP ĐƠN'!I$2:I$1000<>"Đã xoá")*('NHẬP ĐƠN'!F$2:F$1000))) | D7: =IF(A7="","",SUMPRODUCT(('NHẬP ĐƠN'!A$2:A$1000=A7)*('NHẬP ĐƠN'!I$2:I$1000<>"Đã xoá")*('NHẬP ĐƠN'!G$2:G$1000)*('NHẬP ĐƠN'!F$2:F$1000))) | E7: =IF(B7>0,D7/B7,"") -> #DIV/0! | F7: =IFERROR(VLOOKUP(A7,'NHẬP ĐƠN'!A:J,10,FALSE),"") | G7: =IF(A7="","",IF(OR(D7>=10000,B7>=5),"⭐ VIP",IF(B7>=3,"💎 Thân thiết","👤 Thường"))) | H7: 289-2102 | I7: 千葉県 | J7: 匝瑳市 | K7: 椿1473-1 カンプ.ノウA102号 | L7: 8080359847
B8: =IF(A8="","",COUNTIFS('NHẬP ĐƠN'!A:A,A8,'NHẬP ĐƠN'!I:I,"<>Đã xoá")) | C8: =IF(A8="","",SUMPRODUCT(('NHẬP ĐƠN'!A$2:A$1000=A8)*('NHẬP ĐƠN'!I$2:I$1000<>"Đã xoá")*('NHẬP ĐƠN'!F$2:F$1000))) | D8: =IF(A8="","",SUMPRODUCT(('NHẬP ĐƠN'!A$2:A$1000=A8)*('NHẬP ĐƠN'!I$2:I$1000<>"Đã xoá")*('NHẬP ĐƠN'!G$2:G$1000)*('NHẬP ĐƠN'!F$2:F$1000))) | E8: =IF(B8>0,D8/B8,"") -> #DIV/0! | F8: =IFERROR(VLOOKUP(A8,'NHẬP ĐƠN'!A:J,10,FALSE),"") | G8: =IF(A8="","",IF(OR(D8>=10000,B8>=5),"⭐ VIP",IF(B8>=3,"💎 Thân thiết","👤 Thường")))
B9: =IF(A9="","",COUNTIFS('NHẬP ĐƠN'!A:A,A9,'NHẬP ĐƠN'!I:I,"<>Đã xoá")) | C9: =IF(A9="","",SUMPRODUCT(('NHẬP ĐƠN'!A$2:A$1000=A9)*('NHẬP ĐƠN'!I$2:I$1000<>"Đã xoá")*('NHẬP ĐƠN'!F$2:F$1000))) | D9: =IF(A9="","",SUMPRODUCT(('NHẬP ĐƠN'!A$2:A$1000=A9)*('NHẬP ĐƠN'!I$2:I$1000<>"Đã xoá")*('NHẬP ĐƠN'!G$2:G$1000)*('NHẬP ĐƠN'!F$2:F$1000))) | E9: =IF(B9>0,D9/B9,"") -> #DIV/0! | F9: =IFERROR(VLOOKUP(A9,'NHẬP ĐƠN'!A:J,10,FALSE),"") | G9: =IF(A9="","",IF(OR(D9>=10000,B9>=5),"⭐ VIP",IF(B9>=3,"💎 Thân thiết","👤 Thường"))) | H9: 270-0032 | I9: 千葉県 | J9: 松戸市 | K9: 北2丁目11-1 ファミールハイツ3号棟 802 | L9: 8073500318
B10: =IF(A10="","",COUNTIFS('NHẬP ĐƠN'!A:A,A10,'NHẬP ĐƠN'!I:I,"<>Đã xoá")) | C10: =IF(A10="","",SUMPRODUCT(('NHẬP ĐƠN'!A$2:A$1000=A10)*('NHẬP ĐƠN'!I$2:I$1000<>"Đã xoá")*('NHẬP ĐƠN'!F$2:F$1000))) | D10: =IF(A10="","",SUMPRODUCT(('NHẬP ĐƠN'!A$2:A$1000=A10)*('NHẬP ĐƠN'!I$2:I$1000<>"Đã xoá")*('NHẬP ĐƠN'!G$2:G$1000)*('NHẬP ĐƠN'!F$2:F$1000))) | E10: =IF(B10>0,D10/B10,"") -> #DIV/0! | F10: =IFERROR(VLOOKUP(A10,'NHẬP ĐƠN'!A:J,10,FALSE),"") | G10: =IF(A10="","",IF(OR(D10>=10000,B10>=5),"⭐ VIP",IF(B10>=3,"💎 Thân thiết","👤 Thường"))) | H10: 545-0001 | I10: 大阪府 | J10: 大阪市阿倍野区 | K10: 天王寺町北２丁目12-2キッポ天王寺北202号 | L10: 9030991196
B11: =IF(A11="","",COUNTIFS('NHẬP ĐƠN'!A:A,A11,'NHẬP ĐƠN'!I:I,"<>Đã xoá")) | C11: =IF(A11="","",SUMPRODUCT(('NHẬP ĐƠN'!A$2:A$1000=A11)*('NHẬP ĐƠN'!I$2:I$1000<>"Đã xoá")*('NHẬP ĐƠN'!F$2:F$1000))) | D11: =IF(A11="","",SUMPRODUCT(('NHẬP ĐƠN'!A$2:A$1000=A11)*('NHẬP ĐƠN'!I$2:I$1000<>"Đã xoá")*('NHẬP ĐƠN'!G$2:G$1000)*('NHẬP ĐƠN'!F$2:F$1000))) | E11: =IF(B11>0,D11/B11,"") -> #DIV/0! | F11: =IFERROR(VLOOKUP(A11,'NHẬP ĐƠN'!A:J,10,FALSE),"") | G11: =IF(A11="","",IF(OR(D11>=10000,B11>=5),"⭐ VIP",IF(B11>=3,"💎 Thân thiết","👤 Thường")))
B12: =IF(A12="","",COUNTIFS('NHẬP ĐƠN'!A:A,A12,'NHẬP ĐƠN'!I:I,"<>Đã xoá")) | C12: =IF(A12="","",SUMPRODUCT(('NHẬP ĐƠN'!A$2:A$1000=A12)*('NHẬP ĐƠN'!I$2:I$1000<>"Đã xoá")*('NHẬP ĐƠN'!F$2:F$1000))) | D12: =IF(A12="","",SUMPRODUCT(('NHẬP ĐƠN'!A$2:A$1000=A12)*('NHẬP ĐƠN'!I$2:I$1000<>"Đã xoá")*('NHẬP ĐƠN'!G$2:G$1000)*('NHẬP ĐƠN'!F$2:F$1000))) | E12: =IF(B12>0,D12/B12,"") -> #DIV/0! | F12: =IFERROR(VLOOKUP(A12,'NHẬP ĐƠN'!A:J,10,FALSE),"") | G12: =IF(A12="","",IF(OR(D12>=10000,B12>=5),"⭐ VIP",IF(B12>=3,"💎 Thân thiết","👤 Thường"))) | H12: 134-0081 | I12: 東京都 | J12: 江戸川区 | K12: 2-11-21 ジャパンエクステージ203
B13: =IF(A13="","",COUNTIFS('NHẬP ĐƠN'!A:A,A13,'NHẬP ĐƠN'!I:I,"<>Đã xoá")) | C13: =IF(A13="","",SUMPRODUCT(('NHẬP ĐƠN'!A$2:A$1000=A13)*('NHẬP ĐƠN'!I$2:I$1000<>"Đã xoá")*('NHẬP ĐƠN'!F$2:F$1000))) | D13: =IF(A13="","",SUMPRODUCT(('NHẬP ĐƠN'!A$2:A$1000=A13)*('NHẬP ĐƠN'!I$2:I$1000<>"Đã xoá")*('NHẬP ĐƠN'!G$2:G$1000)*('NHẬP ĐƠN'!F$2:F$1000))) | E13: =IF(B13>0,D13/B13,"") -> #DIV/0! | F13: =IFERROR(VLOOKUP(A13,'NHẬP ĐƠN'!A:J,10,FALSE),"") | G13: =IF(A13="","",IF(OR(D13>=10000,B13>=5),"⭐ VIP",IF(B13>=3,"💎 Thân thiết","👤 Thường")))
B14: =IF(A14="","",COUNTIFS('NHẬP ĐƠN'!A:A,A14,'NHẬP ĐƠN'!I:I,"<>Đã xoá")) | C14: =IF(A14="","",SUMPRODUCT(('NHẬP ĐƠN'!A$2:A$1000=A14)*('NHẬP ĐƠN'!I$2:I$1000<>"Đã xoá")*('NHẬP ĐƠN'!F$2:F$1000))) | D14: =IF(A14="","",SUMPRODUCT(('NHẬP ĐƠN'!A$2:A$1000=A14)*('NHẬP ĐƠN'!I$2:I$1000<>"Đã xoá")*('NHẬP ĐƠN'!G$2:G$1000)*('NHẬP ĐƠN'!F$2:F$1000))) | E14: =IF(B14>0,D14/B14,"") -> #DIV/0! | F14: =IFERROR(VLOOKUP(A14,'NHẬP ĐƠN'!A:J,10,FALSE),"") | G14: =IF(A14="","",IF(OR(D14>=10000,B14>=5),"⭐ VIP",IF(B14>=3,"💎 Thân thiết","👤 Thường")))
B15: =IF(A15="","",COUNTIFS('NHẬP ĐƠN'!A:A,A15,'NHẬP ĐƠN'!I:I,"<>Đã xoá")) | C15: =IF(A15="","",SUMPRODUCT(('NHẬP ĐƠN'!A$2:A$1000=A15)*('NHẬP ĐƠN'!I$2:I$1000<>"Đã xoá")*('NHẬP ĐƠN'!F$2:F$1000))) | D15: =IF(A15="","",SUMPRODUCT(('NHẬP ĐƠN'!A$2:A$1000=A15)*('NHẬP ĐƠN'!I$2:I$1000<>"Đã xoá")*('NHẬP ĐƠN'!G$2:G$1000)*('NHẬP ĐƠN'!F$2:F$1000))) | E15: =IF(B15>0,D15/B15,"") -> #DIV/0! | F15: =IFERROR(VLOOKUP(A15,'NHẬP ĐƠN'!A:J,10,FALSE),"") | G15: =IF(A15="","",IF(OR(D15>=10000,B15>=5),"⭐ VIP",IF(B15>=3,"💎 Thân thiết","👤 Thường")))
B16: =IF(A16="","",COUNTIFS('NHẬP ĐƠN'!A:A,A16,'NHẬP ĐƠN'!I:I,"<>Đã xoá")) | C16: =IF(A16="","",SUMPRODUCT(('NHẬP ĐƠN'!A$2:A$1000=A16)*('NHẬP ĐƠN'!I$2:I$1000<>"Đã xoá")*('NHẬP ĐƠN'!F$2:F$1000))) | D16: =IF(A16="","",SUMPRODUCT(('NHẬP ĐƠN'!A$2:A$1000=A16)*('NHẬP ĐƠN'!I$2:I$1000<>"Đã xoá")*('NHẬP ĐƠN'!G$2:G$1000)*('NHẬP ĐƠN'!F$2:F$1000))) | E16: =IF(B16>0,D16/B16,"") -> #DIV/0! | F16: =IFERROR(VLOOKUP(A16,'NHẬP ĐƠN'!A:J,10,FALSE),"") | G16: =IF(A16="","",IF(OR(D16>=10000,B16>=5),"⭐ VIP",IF(B16>=3,"💎 Thân thiết","👤 Thường")))
B17: =IF(A17="","",COUNTIFS('NHẬP ĐƠN'!A:A,A17,'NHẬP ĐƠN'!I:I,"<>Đã xoá")) | C17: =IF(A17="","",SUMPRODUCT(('NHẬP ĐƠN'!A$2:A$1000=A17)*('NHẬP ĐƠN'!I$2:I$1000<>"Đã xoá")*('NHẬP ĐƠN'!F$2:F$1000))) | D17: =IF(A17="","",SUMPRODUCT(('NHẬP ĐƠN'!A$2:A$1000=A17)*('NHẬP ĐƠN'!I$2:I$1000<>"Đã xoá")*('NHẬP ĐƠN'!G$2:G$1000)*('NHẬP ĐƠN'!F$2:F$1000))) | E17: =IF(B17>0,D17/B17,"") -> #DIV/0! | F17: =IFERROR(VLOOKUP(A17,'NHẬP ĐƠN'!A:J,10,FALSE),"") | G17: =IF(A17="","",IF(OR(D17>=10000,B17>=5),"⭐ VIP",IF(B17>=3,"💎 Thân thiết","👤 Thường")))
B18: =IF(A18="","",COUNTIFS('NHẬP ĐƠN'!A:A,A18,'NHẬP ĐƠN'!I:I,"<>Đã xoá")) | C18: =IF(A18="","",SUMPRODUCT(('NHẬP ĐƠN'!A$2:A$1000=A18)*('NHẬP ĐƠN'!I$2:I$1000<>"Đã xoá")*('NHẬP ĐƠN'!F$2:F$1000))) | D18: =IF(A18="","",SUMPRODUCT(('NHẬP ĐƠN'!A$2:A$1000=A18)*('NHẬP ĐƠN'!I$2:I$1000<>"Đã xoá")*('NHẬP ĐƠN'!G$2:G$1000)*('NHẬP ĐƠN'!F$2:F$1000))) | E18: =IF(B18>0,D18/B18,"") -> #DIV/0! | F18: =IFERROR(VLOOKUP(A18,'NHẬP ĐƠN'!A:J,10,FALSE),"") | G18: =IF(A18="","",IF(OR(D18>=10000,B18>=5),"⭐ VIP",IF(B18>=3,"💎 Thân thiết","👤 Thường")))
B19: =IF(A19="","",COUNTIFS('NHẬP ĐƠN'!A:A,A19,'NHẬP ĐƠN'!I:I,"<>Đã xoá")) | C19: =IF(A19="","",SUMPRODUCT(('NHẬP ĐƠN'!A$2:A$1000=A19)*('NHẬP ĐƠN'!I$2:I$1000<>"Đã xoá")*('NHẬP ĐƠN'!F$2:F$1000))) | D19: =IF(A19="","",SUMPRODUCT(('NHẬP ĐƠN'!A$2:A$1000=A19)*('NHẬP ĐƠN'!I$2:I$1000<>"Đã xoá")*('NHẬP ĐƠN'!G$2:G$1000)*('NHẬP ĐƠN'!F$2:F$1000))) | E19: =IF(B19>0,D19/B19,"") -> #DIV/0! | F19: =IFERROR(VLOOKUP(A19,'NHẬP ĐƠN'!A:J,10,FALSE),"") | G19: =IF(A19="","",IF(OR(D19>=10000,B19>=5),"⭐ VIP",IF(B19>=3,"💎 Thân thiết","👤 Thường")))
B20: =IF(A20="","",COUNTIFS('NHẬP ĐƠN'!A:A,A20,'NHẬP ĐƠN'!I:I,"<>Đã xoá")) | C20: =IF(A20="","",SUMPRODUCT(('NHẬP ĐƠN'!A$2:A$1000=A20)*('NHẬP ĐƠN'!I$2:I$1000<>"Đã xoá")*('NHẬP ĐƠN'!F$2:F$1000))) | D20: =IF(A20="","",SUMPRODUCT(('NHẬP ĐƠN'!A$2:A$1000=A20)*('NHẬP ĐƠN'!I$2:I$1000<>"Đã xoá")*('NHẬP ĐƠN'!G$2:G$1000)*('NHẬP ĐƠN'!F$2:F$1000))) | E20: =IF(B20>0,D20/B20,"") -> #DIV/0! | F20: =IFERROR(VLOOKUP(A20,'NHẬP ĐƠN'!A:J,10,FALSE),"") | G20: =IF(A20="","",IF(OR(D20>=10000,B20>=5),"⭐ VIP",IF(B20>=3,"💎 Thân thiết","👤 Thường")))
B21: =IF(A21="","",COUNTIFS('NHẬP ĐƠN'!A:A,A21,'NHẬP ĐƠN'!I:I,"<>Đã xoá")) | C21: =IF(A21="","",SUMPRODUCT(('NHẬP ĐƠN'!A$2:A$1000=A21)*('NHẬP ĐƠN'!I$2:I$1000<>"Đã xoá")*('NHẬP ĐƠN'!F$2:F$1000))) | D21: =IF(A21="","",SUMPRODUCT(('NHẬP ĐƠN'!A$2:A$1000=A21)*('NHẬP ĐƠN'!I$2:I$1000<>"Đã xoá")*('NHẬP ĐƠN'!G$2:G$1000)*('NHẬP ĐƠN'!F$2:F$1000))) | E21: =IF(B21>0,D21/B21,"") -> #DIV/0! | F21: =IFERROR(VLOOKUP(A21,'NHẬP ĐƠN'!A:J,10,FALSE),"") | G21: =IF(A21="","",IF(OR(D21>=10000,B21>=5),"⭐ VIP",IF(B21>=3,"💎 Thân thiết","👤 Thường")))
B22: =IF(A22="","",COUNTIFS('NHẬP ĐƠN'!A:A,A22,'NHẬP ĐƠN'!I:I,"<>Đã xoá")) | C22: =IF(A22="","",SUMPRODUCT(('NHẬP ĐƠN'!A$2:A$1000=A22)*('NHẬP ĐƠN'!I$2:I$1000<>"Đã xoá")*('NHẬP ĐƠN'!F$2:F$1000))) | D22: =IF(A22="","",SUMPRODUCT(('NHẬP ĐƠN'!A$2:A$1000=A22)*('NHẬP ĐƠN'!I$2:I$1000<>"Đã xoá")*('NHẬP ĐƠN'!G$2:G$1000)*('NHẬP ĐƠN'!F$2:F$1000))) | E22: =IF(B22>0,D22/B22,"") -> #DIV/0! | F22: =IFERROR(VLOOKUP(A22,'NHẬP ĐƠN'!A:J,10,FALSE),"") | G22: =IF(A22="","",IF(OR(D22>=10000,B22>=5),"⭐ VIP",IF(B22>=3,"💎 Thân thiết","👤 Thường")))
B23: =IF(A23="","",COUNTIFS('NHẬP ĐƠN'!A:A,A23,'NHẬP ĐƠN'!I:I,"<>Đã xoá")) | C23: =IF(A23="","",SUMPRODUCT(('NHẬP ĐƠN'!A$2:A$1000=A23)*('NHẬP ĐƠN'!I$2:I$1000<>"Đã xoá")*('NHẬP ĐƠN'!F$2:F$1000))) | D23: =IF(A23="","",SUMPRODUCT(('NHẬP ĐƠN'!A$2:A$1000=A23)*('NHẬP ĐƠN'!I$2:I$1000<>"Đã xoá")*('NHẬP ĐƠN'!G$2:G$1000)*('NHẬP ĐƠN'!F$2:F$1000))) | E23: =IF(B23>0,D23/B23,"") -> #DIV/0! | F23: =IFERROR(VLOOKUP(A23,'NHẬP ĐƠN'!A:J,10,FALSE),"") | G23: =IF(A23="","",IF(OR(D23>=10000,B23>=5),"⭐ VIP",IF(B23>=3,"💎 Thân thiết","👤 Thường")))
B24: =IF(A24="","",COUNTIFS('NHẬP ĐƠN'!A:A,A24,'NHẬP ĐƠN'!I:I,"<>Đã xoá")) | C24: =IF(A24="","",SUMPRODUCT(('NHẬP ĐƠN'!A$2:A$1000=A24)*('NHẬP ĐƠN'!I$2:I$1000<>"Đã xoá")*('NHẬP ĐƠN'!F$2:F$1000))) | D24: =IF(A24="","",SUMPRODUCT(('NHẬP ĐƠN'!A$2:A$1000=A24)*('NHẬP ĐƠN'!I$2:I$1000<>"Đã xoá")*('NHẬP ĐƠN'!G$2:G$1000)*('NHẬP ĐƠN'!F$2:F$1000))) | E24: =IF(B24>0,D24/B24,"") -> #DIV/0! | F24: =IFERROR(VLOOKUP(A24,'NHẬP ĐƠN'!A:J,10,FALSE),"") | G24: =IF(A24="","",IF(OR(D24>=10000,B24>=5),"⭐ VIP",IF(B24>=3,"💎 Thân thiết","👤 Thường")))
... B29: =IF(A29="","",COUNTIFS('NHẬP ĐƠN'!A:A,A29,'NHẬP ĐƠN'!I:I,"<>Đã xoá")) | C29: =IF(A29="","",SUMPRODUCT(('NHẬP ĐƠN'!A$2:A$1000=A29)*('NHẬP ĐƠN'!I$2:I$1000<>"Đã xoá")*('NHẬP ĐƠN'!F$2:F$1000))) | D29: =IF(A29="","",SUMPRODUCT(('NHẬP ĐƠN'!A$2:A$1000=A29)*('NHẬP ĐƠN'!I$2:I$1000<>"Đã xoá")*('NHẬP ĐƠN'!G$2:G$1000)*('NHẬP ĐƠN'!F$2:F$1000))) | E29: =IF(B29>0,D29/B29,"") -> #DIV/0! | F29: =IFERROR(VLOOKUP(A29,'NHẬP ĐƠN'!A:J,10,FALSE),"") | G29: =IF(A29="","",IF(OR(D29>=10000,B29>=5),"⭐ VIP",IF(B29>=3,"💎 Thân thiết","👤 Thường")))
B30: =IF(A30="","",COUNTIFS('NHẬP ĐƠN'!A:A,A30,'NHẬP ĐƠN'!I:I,"<>Đã xoá")) | C30: =IF(A30="","",SUMPRODUCT(('NHẬP ĐƠN'!A$2:A$1000=A30)*('NHẬP ĐƠN'!I$2:I$1000<>"Đã xoá")*('NHẬP ĐƠN'!F$2:F$1000))) | D30: =IF(A30="","",SUMPRODUCT(('NHẬP ĐƠN'!A$2:A$1000=A30)*('NHẬP ĐƠN'!I$2:I$1000<>"Đã xoá")*('NHẬP ĐƠN'!G$2:G$1000)*('NHẬP ĐƠN'!F$2:F$1000))) | E30: =IF(B30>0,D30/B30,"") -> #DIV/0! | F30: =IFERROR(VLOOKUP(A30,'NHẬP ĐƠN'!A:J,10,FALSE),"") | G30: =IF(A30="","",IF(OR(D30>=10000,B30>=5),"⭐ VIP",IF(B30>=3,"💎 Thân thiết","👤 Thường"))) | H30: 214-0039 | I30: 神奈川県 | J30: 川崎市多摩区 | K30: 栗谷3丁目2番11リズ生田505号
B31: =IF(A31="","",COUNTIFS('NHẬP ĐƠN'!A:A,A31,'NHẬP ĐƠN'!I:I,"<>Đã xoá")) | C31: =IF(A31="","",SUMPRODUCT(('NHẬP ĐƠN'!A$2:A$1000=A31)*('NHẬP ĐƠN'!I$2:I$1000<>"Đã xoá")*('NHẬP ĐƠN'!F$2:F$1000))) | D31: =IF(A31="","",SUMPRODUCT(('NHẬP ĐƠN'!A$2:A$1000=A31)*('NHẬP ĐƠN'!I$2:I$1000<>"Đã xoá")*('NHẬP ĐƠN'!G$2:G$1000)*('NHẬP ĐƠN'!F$2:F$1000))) | E31: =IF(B31>0,D31/B31,"") -> #DIV/0! | F31: =IFERROR(VLOOKUP(A31,'NHẬP ĐƠN'!A:J,10,FALSE),"") | G31: =IF(A31="","",IF(OR(D31>=10000,B31>=5),"⭐ VIP",IF(B31>=3,"💎 Thân thiết","👤 Thường"))) | H31: 574-0025 | I31: 大阪府 | J31: 大東市 | K31: 4-4-42 | L31: 8069613369
B32: =IF(A32="","",COUNTIFS('NHẬP ĐƠN'!A:A,A32,'NHẬP ĐƠN'!I:I,"<>Đã xoá")) | C32: =IF(A32="","",SUMPRODUCT(('NHẬP ĐƠN'!A$2:A$1000=A32)*('NHẬP ĐƠN'!I$2:I$1000<>"Đã xoá")*('NHẬP ĐƠN'!F$2:F$1000))) | D32: =IF(A32="","",SUMPRODUCT(('NHẬP ĐƠN'!A$2:A$1000=A32)*('NHẬP ĐƠN'!I$2:I$1000<>"Đã xoá")*('NHẬP ĐƠN'!G$2:G$1000)*('NHẬP ĐƠN'!F$2:F$1000))) | E32: =IF(B32>0,D32/B32,"") -> #DIV/0! | F32: =IFERROR(VLOOKUP(A32,'NHẬP ĐƠN'!A:J,10,FALSE),"") | G32: =IF(A32="","",IF(OR(D32>=10000,B32>=5),"⭐ VIP",IF(B32>=3,"💎 Thân thiết","👤 Thường")))
B33: =IF(A33="","",COUNTIFS('NHẬP ĐƠN'!A:A,A33,'NHẬP ĐƠN'!I:I,"<>Đã xoá")) | C33: =IF(A33="","",SUMPRODUCT(('NHẬP ĐƠN'!A$2:A$1000=A33)*('NHẬP ĐƠN'!I$2:I$1000<>"Đã xoá")*('NHẬP ĐƠN'!F$2:F$1000))) | D33: =IF(A33="","",SUMPRODUCT(('NHẬP ĐƠN'!A$2:A$1000=A33)*('NHẬP ĐƠN'!I$2:I$1000<>"Đã xoá")*('NHẬP ĐƠN'!G$2:G$1000)*('NHẬP ĐƠN'!F$2:F$1000))) | E33: =IF(B33>0,D33/B33,"") -> #DIV/0! | F33: =IFERROR(VLOOKUP(A33,'NHẬP ĐƠN'!A:J,10,FALSE),"") | G33: =IF(A33="","",IF(OR(D33>=10000,B33>=5),"⭐ VIP",IF(B33>=3,"💎 Thân thiết","👤 Thường"))) | H33: 193-0931 | I33: 東京都 | J33: 八王子市 | K33: 台町1-22-20コーポセイウン102号 | L33: 9030991196
B34: =IF(A34="","",COUNTIFS('NHẬP ĐƠN'!A:A,A34,'NHẬP ĐƠN'!I:I,"<>Đã xoá")) | C34: =IF(A34="","",SUMPRODUCT(('NHẬP ĐƠN'!A$2:A$1000=A34)*('NHẬP ĐƠN'!I$2:I$1000<>"Đã xoá")*('NHẬP ĐƠN'!F$2:F$1000))) | D34: =IF(A34="","",SUMPRODUCT(('NHẬP ĐƠN'!A$2:A$1000=A34)*('NHẬP ĐƠN'!I$2:I$1000<>"Đã xoá")*('NHẬP ĐƠN'!G$2:G$1000)*('NHẬP ĐƠN'!F$2:F$1000))) | E34: =IF(B34>0,D34/B34,"") -> #DIV/0! | F34: =IFERROR(VLOOKUP(A34,'NHẬP ĐƠN'!A:J,10,FALSE),"") | G34: =IF(A34="","",IF(OR(D34>=10000,B34>=5),"⭐ VIP",IF(B34>=3,"💎 Thân thiết","👤 Thường"))) | H34: 168-0071 | I34: 東京都 | J34: 杉並区 | K34: 西3-8-9パレス高井戸 201号室 | L34: 9030991196
B35: =IF(A35="","",COUNTIFS('NHẬP ĐƠN'!A:A,A35,'NHẬP ĐƠN'!I:I,"<>Đã xoá")) | C35: =IF(A35="","",SUMPRODUCT(('NHẬP ĐƠN'!A$2:A$1000=A35)*('NHẬP ĐƠN'!I$2:I$1000<>"Đã xoá")*('NHẬP ĐƠN'!F$2:F$1000))) | D35: =IF(A35="","",SUMPRODUCT(('NHẬP ĐƠN'!A$2:A$1000=A35)*('NHẬP ĐƠN'!I$2:I$1000<>"Đã xoá")*('NHẬP ĐƠN'!G$2:G$1000)*('NHẬP ĐƠN'!F$2:F$1000))) | E35: =IF(B35>0,D35/B35,"") -> #DIV/0! | F35: =IFERROR(VLOOKUP(A35,'NHẬP ĐƠN'!A:J,10,FALSE),"") | G35: =IF(A35="","",IF(OR(D35>=10000,B35>=5),"⭐ VIP",IF(B35>=3,"💎 Thân thiết","👤 Thường"))) | H35: 193-0931 | I35: 東京都 | J35: 八王子市 | K35: 台町1-22-20コーポセイウン102号
B36: =IF(A36="","",COUNTIFS('NHẬP ĐƠN'!A:A,A36,'NHẬP ĐƠN'!I:I,"<>Đã xoá")) | C36: =IF(A36="","",SUMPRODUCT(('NHẬP ĐƠN'!A$2:A$1000=A36)*('NHẬP ĐƠN'!I$2:I$1000<>"Đã xoá")*('NHẬP ĐƠN'!F$2:F$1000))) | D36: =IF(A36="","",SUMPRODUCT(('NHẬP ĐƠN'!A$2:A$1000=A36)*('NHẬP ĐƠN'!I$2:I$1000<>"Đã xoá")*('NHẬP ĐƠN'!G$2:G$1000)*('NHẬP ĐƠN'!F$2:F$1000))) | E36: =IF(B36>0,D36/B36,"") -> #DIV/0! | F36: =IFERROR(VLOOKUP(A36,'NHẬP ĐƠN'!A:J,10,FALSE),"") | G36: =IF(A36="","",IF(OR(D36>=10000,B36>=5),"⭐ VIP",IF(B36>=3,"💎 Thân thiết","👤 Thường")))
B37: =IF(A37="","",COUNTIFS('NHẬP ĐƠN'!A:A,A37,'NHẬP ĐƠN'!I:I,"<>Đã xoá")) | C37: =IF(A37="","",SUMPRODUCT(('NHẬP ĐƠN'!A$2:A$1000=A37)*('NHẬP ĐƠN'!I$2:I$1000<>"Đã xoá")*('NHẬP ĐƠN'!F$2:F$1000))) | D37: =IF(A37="","",SUMPRODUCT(('NHẬP ĐƠN'!A$2:A$1000=A37)*('NHẬP ĐƠN'!I$2:I$1000<>"Đã xoá")*('NHẬP ĐƠN'!G$2:G$1000)*('NHẬP ĐƠN'!F$2:F$1000))) | E37: =IF(B37>0,D37/B37,"") -> #DIV/0! | F37: =IFERROR(VLOOKUP(A37,'NHẬP ĐƠN'!A:J,10,FALSE),"") | G37: =IF(A37="","",IF(OR(D37>=10000,B37>=5),"⭐ VIP",IF(B37>=3,"💎 Thân thiết","👤 Thường")))
B38: =IF(A38="","",COUNTIFS('NHẬP ĐƠN'!A:A,A38,'NHẬP ĐƠN'!I:I,"<>Đã xoá")) | C38: =IF(A38="","",SUMPRODUCT(('NHẬP ĐƠN'!A$2:A$1000=A38)*('NHẬP ĐƠN'!I$2:I$1000<>"Đã xoá")*('NHẬP ĐƠN'!F$2:F$1000))) | D38: =IF(A38="","",SUMPRODUCT(('NHẬP ĐƠN'!A$2:A$1000=A38)*('NHẬP ĐƠN'!I$2:I$1000<>"Đã xoá")*('NHẬP ĐƠN'!G$2:G$1000)*('NHẬP ĐƠN'!F$2:F$1000))) | E38: =IF(B38>0,D38/B38,"") -> #DIV/0! | F38: =IFERROR(VLOOKUP(A38,'NHẬP ĐƠN'!A:J,10,FALSE),"") | G38: =IF(A38="","",IF(OR(D38>=10000,B38>=5),"⭐ VIP",IF(B38>=3,"💎 Thân thiết","👤 Thường")))
B39: =IF(A39="","",COUNTIFS('NHẬP ĐƠN'!A:A,A39,'NHẬP ĐƠN'!I:I,"<>Đã xoá")) | C39: =IF(A39="","",SUMPRODUCT(('NHẬP ĐƠN'!A$2:A$1000=A39)*('NHẬP ĐƠN'!I$2:I$1000<>"Đã xoá")*('NHẬP ĐƠN'!F$2:F$1000))) | D39: =IF(A39="","",SUMPRODUCT(('NHẬP ĐƠN'!A$2:A$1000=A39)*('NHẬP ĐƠN'!I$2:I$1000<>"Đã xoá")*('NHẬP ĐƠN'!G$2:G$1000)*('NHẬP ĐƠN'!F$2:F$1000))) | E39: =IF(B39>0,D39/B39,"") -> #DIV/0! | F39: =IFERROR(VLOOKUP(A39,'NHẬP ĐƠN'!A:J,10,FALSE),"") | G39: =IF(A39="","",IF(OR(D39>=10000,B39>=5),"⭐ VIP",IF(B39>=3,"💎 Thân thiết","👤 Thường")))
B40: =IF(A40="","",COUNTIFS('NHẬP ĐƠN'!A:A,A40,'NHẬP ĐƠN'!I:I,"<>Đã xoá")) | C40: =IF(A40="","",SUMPRODUCT(('NHẬP ĐƠN'!A$2:A$1000=A40)*('NHẬP ĐƠN'!I$2:I$1000<>"Đã xoá")*('NHẬP ĐƠN'!F$2:F$1000))) | D40: =IF(A40="","",SUMPRODUCT(('NHẬP ĐƠN'!A$2:A$1000=A40)*('NHẬP ĐƠN'!I$2:I$1000<>"Đã xoá")*('NHẬP ĐƠN'!G$2:G$1000)*('NHẬP ĐƠN'!F$2:F$1000))) | E40: =IF(B40>0,D40/B40,"") -> #DIV/0! | F40: =IFERROR(VLOOKUP(A40,'NHẬP ĐƠN'!A:J,10,FALSE),"") | G40: =IF(A40="","",IF(OR(D40>=10000,B40>=5),"⭐ VIP",IF(B40>=3,"💎 Thân thiết","👤 Thường")))
B41: =IF(A41="","",COUNTIFS('NHẬP ĐƠN'!A:A,A41,'NHẬP ĐƠN'!I:I,"<>Đã xoá")) | C41: =IF(A41="","",SUMPRODUCT(('NHẬP ĐƠN'!A$2:A$1000=A41)*('NHẬP ĐƠN'!I$2:I$1000<>"Đã xoá")*('NHẬP ĐƠN'!F$2:F$1000))) | D41: =IF(A41="","",SUMPRODUCT(('NHẬP ĐƠN'!A$2:A$1000=A41)*('NHẬP ĐƠN'!I$2:I$1000<>"Đã xoá")*('NHẬP ĐƠN'!G$2:G$1000)*('NHẬP ĐƠN'!F$2:F$1000))) | E41: =IF(B41>0,D41/B41,"") -> #DIV/0! | F41: =IFERROR(VLOOKUP(A41,'NHẬP ĐƠN'!A:J,10,FALSE),"") | G41: =IF(A41="","",IF(OR(D41>=10000,B41>=5),"⭐ VIP",IF(B41>=3,"💎 Thân thiết","👤 Thường"))) | H41: 220-0074 | I41: 神奈川県 | J41: 横浜市西区 | K41: 南浅間町4番地10 TS横浜第一101号 | L41: 9030991196
B42: =IF(A42="","",COUNTIFS('NHẬP ĐƠN'!A:A,A42,'NHẬP ĐƠN'!I:I,"<>Đã xoá")) | C42: =IF(A42="","",SUMPRODUCT(('NHẬP ĐƠN'!A$2:A$1000=A42)*('NHẬP ĐƠN'!I$2:I$1000<>"Đã xoá")*('NHẬP ĐƠN'!F$2:F$1000))) | D42: =IF(A42="","",SUMPRODUCT(('NHẬP ĐƠN'!A$2:A$1000=A42)*('NHẬP ĐƠN'!I$2:I$1000<>"Đã xoá")*('NHẬP ĐƠN'!G$2:G$1000)*('NHẬP ĐƠN'!F$2:F$1000))) | E42: =IF(B42>0,D42/B42,"") -> #DIV/0! | F42: =IFERROR(VLOOKUP(A42,'NHẬP ĐƠN'!A:J,10,FALSE),"") | G42: =IF(A42="","",IF(OR(D42>=10000,B42>=5),"⭐ VIP",IF(B42>=3,"💎 Thân thiết","👤 Thường")))
B43: =IF(A43="","",COUNTIFS('NHẬP ĐƠN'!A:A,A43,'NHẬP ĐƠN'!I:I,"<>Đã xoá")) | C43: =IF(A43="","",SUMPRODUCT(('NHẬP ĐƠN'!A$2:A$1000=A43)*('NHẬP ĐƠN'!I$2:I$1000<>"Đã xoá")*('NHẬP ĐƠN'!F$2:F$1000))) | D43: =IF(A43="","",SUMPRODUCT(('NHẬP ĐƠN'!A$2:A$1000=A43)*('NHẬP ĐƠN'!I$2:I$1000<>"Đã xoá")*('NHẬP ĐƠN'!G$2:G$1000)*('NHẬP ĐƠN'!F$2:F$1000))) | E43: =IF(B43>0,D43/B43,"") -> #DIV/0! | F43: =IFERROR(VLOOKUP(A43,'NHẬP ĐƠN'!A:J,10,FALSE),"") | G43: =IF(A43="","",IF(OR(D43>=10000,B43>=5),"⭐ VIP",IF(B43>=3,"💎 Thân thiết","👤 Thường")))
B44: =IF(A44="","",COUNTIFS('NHẬP ĐƠN'!A:A,A44,'NHẬP ĐƠN'!I:I,"<>Đã xoá")) | C44: =IF(A44="","",SUMPRODUCT(('NHẬP ĐƠN'!A$2:A$1000=A44)*('NHẬP ĐƠN'!I$2:I$1000<>"Đã xoá")*('NHẬP ĐƠN'!F$2:F$1000))) | D44: =IF(A44="","",SUMPRODUCT(('NHẬP ĐƠN'!A$2:A$1000=A44)*('NHẬP ĐƠN'!I$2:I$1000<>"Đã xoá")*('NHẬP ĐƠN'!G$2:G$1000)*('NHẬP ĐƠN'!F$2:F$1000))) | E44: =IF(B44>0,D44/B44,"") -> #DIV/0! | F44: =IFERROR(VLOOKUP(A44,'NHẬP ĐƠN'!A:J,10,FALSE),"") | G44: =IF(A44="","",IF(OR(D44>=10000,B44>=5),"⭐ VIP",IF(B44>=3,"💎 Thân thiết","👤 Thường")))
B45: =IF(A45="","",COUNTIFS('NHẬP ĐƠN'!A:A,A45,'NHẬP ĐƠN'!I:I,"<>Đã xoá")) | C45: =IF(A45="","",SUMPRODUCT(('NHẬP ĐƠN'!A$2:A$1000=A45)*('NHẬP ĐƠN'!I$2:I$1000<>"Đã xoá")*('NHẬP ĐƠN'!F$2:F$1000))) | D45: =IF(A45="","",SUMPRODUCT(('NHẬP ĐƠN'!A$2:A$1000=A45)*('NHẬP ĐƠN'!I$2:I$1000<>"Đã xoá")*('NHẬP ĐƠN'!G$2:G$1000)*('NHẬP ĐƠN'!F$2:F$1000))) | E45: =IF(B45>0,D45/B45,"") -> #DIV/0! | F45: =IFERROR(VLOOKUP(A45,'NHẬP ĐƠN'!A:J,10,FALSE),"") | G45: =IF(A45="","",IF(OR(D45>=10000,B45>=5),"⭐ VIP",IF(B45>=3,"💎 Thân thiết","👤 Thường"))) | H45: 738-0203 | I45: 広島県 | J45: 廿日市 | K45: 市友田131 | L45: 829742200
B46: =IF(A46="","",COUNTIFS('NHẬP ĐƠN'!A:A,A46,'NHẬP ĐƠN'!I:I,"<>Đã xoá")) | C46: =IF(A46="","",SUMPRODUCT(('NHẬP ĐƠN'!A$2:A$1000=A46)*('NHẬP ĐƠN'!I$2:I$1000<>"Đã xoá")*('NHẬP ĐƠN'!F$2:F$1000))) | D46: =IF(A46="","",SUMPRODUCT(('NHẬP ĐƠN'!A$2:A$1000=A46)*('NHẬP ĐƠN'!I$2:I$1000<>"Đã xoá")*('NHẬP ĐƠN'!G$2:G$1000)*('NHẬP ĐƠN'!F$2:F$1000))) | E46: =IF(B46>0,D46/B46,"") -> #DIV/0! | F46: =IFERROR(VLOOKUP(A46,'NHẬP ĐƠN'!A:J,10,FALSE),"") | G46: =IF(A46="","",IF(OR(D46>=10000,B46>=5),"⭐ VIP",IF(B46>=3,"💎 Thân thiết","👤 Thường")))
B47: =IF(A47="","",COUNTIFS('NHẬP ĐƠN'!A:A,A47,'NHẬP ĐƠN'!I:I,"<>Đã xoá")) | C47: =IF(A47="","",SUMPRODUCT(('NHẬP ĐƠN'!A$2:A$1000=A47)*('NHẬP ĐƠN'!I$2:I$1000<>"Đã xoá")*('NHẬP ĐƠN'!F$2:F$1000))) | D47: =IF(A47="","",SUMPRODUCT(('NHẬP ĐƠN'!A$2:A$1000=A47)*('NHẬP ĐƠN'!I$2:I$1000<>"Đã xoá")*('NHẬP ĐƠN'!G$2:G$1000)*('NHẬP ĐƠN'!F$2:F$1000))) | E47: =IF(B47>0,D47/B47,"") -> #DIV/0! | F47: =IFERROR(VLOOKUP(A47,'NHẬP ĐƠN'!A:J,10,FALSE),"") | G47: =IF(A47="","",IF(OR(D47>=10000,B47>=5),"⭐ VIP",IF(B47>=3,"💎 Thân thiết","👤 Thường")))
B48: =IF(A48="","",COUNTIFS('NHẬP ĐƠN'!A:A,A48,'NHẬP ĐƠN'!I:I,"<>Đã xoá")) | C48: =IF(A48="","",SUMPRODUCT(('NHẬP ĐƠN'!A$2:A$1000=A48)*('NHẬP ĐƠN'!I$2:I$1000<>"Đã xoá")*('NHẬP ĐƠN'!F$2:F$1000))) | D48: =IF(A48="","",SUMPRODUCT(('NHẬP ĐƠN'!A$2:A$1000=A48)*('NHẬP ĐƠN'!I$2:I$1000<>"Đã xoá")*('NHẬP ĐƠN'!G$2:G$1000)*('NHẬP ĐƠN'!F$2:F$1000))) | E48: =IF(B48>0,D48/B48,"") -> #DIV/0! | F48: =IFERROR(VLOOKUP(A48,'NHẬP ĐƠN'!A:J,10,FALSE),"") | G48: =IF(A48="","",IF(OR(D48>=10000,B48>=5),"⭐ VIP",IF(B48>=3,"💎 Thân thiết","👤 Thường"))) | H48: 401-0337 | I48: 山梨県 | J48: 南都留郡富士河口湖町 | K48: 本栖218-4 | L48: 9030991196
B49: =IF(A49="","",COUNTIFS('NHẬP ĐƠN'!A:A,A49,'NHẬP ĐƠN'!I:I,"<>Đã xoá")) | C49: =IF(A49="","",SUMPRODUCT(('NHẬP ĐƠN'!A$2:A$1000=A49)*('NHẬP ĐƠN'!I$2:I$1000<>"Đã xoá")*('NHẬP ĐƠN'!F$2:F$1000))) | D49: =IF(A49="","",SUMPRODUCT(('NHẬP ĐƠN'!A$2:A$1000=A49)*('NHẬP ĐƠN'!I$2:I$1000<>"Đã xoá")*('NHẬP ĐƠN'!G$2:G$1000)*('NHẬP ĐƠN'!F$2:F$1000))) | E49: =IF(B49>0,D49/B49,"") -> #DIV/0! | F49: =IFERROR(VLOOKUP(A49,'NHẬP ĐƠN'!A:J,10,FALSE),"") | G49: =IF(A49="","",IF(OR(D49>=10000,B49>=5),"⭐ VIP",IF(B49>=3,"💎 Thân thiết","👤 Thường")))
B50: =IF(A50="","",COUNTIFS('NHẬP ĐƠN'!A:A,A50,'NHẬP ĐƠN'!I:I,"<>Đã xoá")) | C50: =IF(A50="","",SUMPRODUCT(('NHẬP ĐƠN'!A$2:A$1000=A50)*('NHẬP ĐƠN'!I$2:I$1000<>"Đã xoá")*('NHẬP ĐƠN'!F$2:F$1000))) | D50: =IF(A50="","",SUMPRODUCT(('NHẬP ĐƠN'!A$2:A$1000=A50)*('NHẬP ĐƠN'!I$2:I$1000<>"Đã xoá")*('NHẬP ĐƠN'!G$2:G$1000)*('NHẬP ĐƠN'!F$2:F$1000))) | E50: =IF(B50>0,D50/B50,"") -> #DIV/0! | F50: =IFERROR(VLOOKUP(A50,'NHẬP ĐƠN'!A:J,10,FALSE),"") | G50: =IF(A50="","",IF(OR(D50>=10000,B50>=5),"⭐ VIP",IF(B50>=3,"💎 Thân thiết","👤 Thường")))
B51: =IF(A51="","",COUNTIFS('NHẬP ĐƠN'!A:A,A51,'NHẬP ĐƠN'!I:I,"<>Đã xoá")) | C51: =IF(A51="","",SUMPRODUCT(('NHẬP ĐƠN'!A$2:A$1000=A51)*('NHẬP ĐƠN'!I$2:I$1000<>"Đã xoá")*('NHẬP ĐƠN'!F$2:F$1000))) | D51: =IF(A51="","",SUMPRODUCT(('NHẬP ĐƠN'!A$2:A$1000=A51)*('NHẬP ĐƠN'!I$2:I$1000<>"Đã xoá")*('NHẬP ĐƠN'!G$2:G$1000)*('NHẬP ĐƠN'!F$2:F$1000))) | E51: =IF(B51>0,D51/B51,"") -> #DIV/0! | F51: =IFERROR(VLOOKUP(A51,'NHẬP ĐƠN'!A:J,10,FALSE),"") | G51: =IF(A51="","",IF(OR(D51>=10000,B51>=5),"⭐ VIP",IF(B51>=3,"💎 Thân thiết","👤 Thường")))
B52: =IF(A52="","",COUNTIFS('NHẬP ĐƠN'!A:A,A52,'NHẬP ĐƠN'!I:I,"<>Đã xoá")) | C52: =IF(A52="","",SUMPRODUCT(('NHẬP ĐƠN'!A$2:A$1000=A52)*('NHẬP ĐƠN'!I$2:I$1000<>"Đã xoá")*('NHẬP ĐƠN'!F$2:F$1000))) | D52: =IF(A52="","",SUMPRODUCT(('NHẬP ĐƠN'!A$2:A$1000=A52)*('NHẬP ĐƠN'!I$2:I$1000<>"Đã xoá")*('NHẬP ĐƠN'!G$2:G$1000)*('NHẬP ĐƠN'!F$2:F$1000))) | E52: =IF(B52>0,D52/B52,"") -> #DIV/0! | F52: =IFERROR(VLOOKUP(A52,'NHẬP ĐƠN'!A:J,10,FALSE),"") | G52: =IF(A52="","",IF(OR(D52>=10000,B52>=5),"⭐ VIP",IF(B52>=3,"💎 Thân thiết","👤 Thường")))
B53: =IF(A53="","",COUNTIFS('NHẬP ĐƠN'!A:A,A53,'NHẬP ĐƠN'!I:I,"<>Đã xoá")) | C53: =IF(A53="","",SUMPRODUCT(('NHẬP ĐƠN'!A$2:A$1000=A53)*('NHẬP ĐƠN'!I$2:I$1000<>"Đã xoá")*('NHẬP ĐƠN'!F$2:F$1000))) | D53: =IF(A53="","",SUMPRODUCT(('NHẬP ĐƠN'!A$2:A$1000=A53)*('NHẬP ĐƠN'!I$2:I$1000<>"Đã xoá")*('NHẬP ĐƠN'!G$2:G$1000)*('NHẬP ĐƠN'!F$2:F$1000))) | E53: =IF(B53>0,D53/B53,"") -> #DIV/0! | F53: =IFERROR(VLOOKUP(A53,'NHẬP ĐƠN'!A:J,10,FALSE),"") | G53: =IF(A53="","",IF(OR(D53>=10000,B53>=5),"⭐ VIP",IF(B53>=3,"💎 Thân thiết","👤 Thường"))) | H53: 547-0012 | I53: 大阪府 | J53: 大阪市平野区 | K53: 長吉六反5丁目9−31ロイヤル長吉 202号室 | L53: 9030991196
B54: =IF(A54="","",COUNTIFS('NHẬP ĐƠN'!A:A,A54,'NHẬP ĐƠN'!I:I,"<>Đã xoá")) | C54: =IF(A54="","",SUMPRODUCT(('NHẬP ĐƠN'!A$2:A$1000=A54)*('NHẬP ĐƠN'!I$2:I$1000<>"Đã xoá")*('NHẬP ĐƠN'!F$2:F$1000))) | D54: =IF(A54="","",SUMPRODUCT(('NHẬP ĐƠN'!A$2:A$1000=A54)*('NHẬP ĐƠN'!I$2:I$1000<>"Đã xoá")*('NHẬP ĐƠN'!G$2:G$1000)*('NHẬP ĐƠN'!F$2:F$1000))) | E54: =IF(B54>0,D54/B54,"") -> #DIV/0! | F54: =IFERROR(VLOOKUP(A54,'NHẬP ĐƠN'!A:J,10,FALSE),"") | G54: =IF(A54="","",IF(OR(D54>=10000,B54>=5),"⭐ VIP",IF(B54>=3,"💎 Thân thiết","👤 Thường")))
B55: =IF(A55="","",COUNTIFS('NHẬP ĐƠN'!A:A,A55,'NHẬP ĐƠN'!I:I,"<>Đã xoá")) | C55: =IF(A55="","",SUMPRODUCT(('NHẬP ĐƠN'!A$2:A$1000=A55)*('NHẬP ĐƠN'!I$2:I$1000<>"Đã xoá")*('NHẬP ĐƠN'!F$2:F$1000))) | D55: =IF(A55="","",SUMPRODUCT(('NHẬP ĐƠN'!A$2:A$1000=A55)*('NHẬP ĐƠN'!I$2:I$1000<>"Đã xoá")*('NHẬP ĐƠN'!G$2:G$1000)*('NHẬP ĐƠN'!F$2:F$1000))) | E55: =IF(B55>0,D55/B55,"") -> #DIV/0! | F55: =IFERROR(VLOOKUP(A55,'NHẬP ĐƠN'!A:J,10,FALSE),"") | G55: =IF(A55="","",IF(OR(D55>=10000,B55>=5),"⭐ VIP",IF(B55>=3,"💎 Thân thiết","👤 Thường")))
B56: =IF(A56="","",COUNTIFS('NHẬP ĐƠN'!A:A,A56,'NHẬP ĐƠN'!I:I,"<>Đã xoá")) | C56: =IF(A56="","",SUMPRODUCT(('NHẬP ĐƠN'!A$2:A$1000=A56)*('NHẬP ĐƠN'!I$2:I$1000<>"Đã xoá")*('NHẬP ĐƠN'!F$2:F$1000))) | D56: =IF(A56="","",SUMPRODUCT(('NHẬP ĐƠN'!A$2:A$1000=A56)*('NHẬP ĐƠN'!I$2:I$1000<>"Đã xoá")*('NHẬP ĐƠN'!G$2:G$1000)*('NHẬP ĐƠN'!F$2:F$1000))) | E56: =IF(B56>0,D56/B56,"") -> #DIV/0! | F56: =IFERROR(VLOOKUP(A56,'NHẬP ĐƠN'!A:J,10,FALSE),"") | G56: =IF(A56="","",IF(OR(D56>=10000,B56>=5),"⭐ VIP",IF(B56>=3,"💎 Thân thiết","👤 Thường")))
B57: =IF(A57="","",COUNTIFS('NHẬP ĐƠN'!A:A,A57,'NHẬP ĐƠN'!I:I,"<>Đã xoá")) | C57: =IF(A57="","",SUMPRODUCT(('NHẬP ĐƠN'!A$2:A$1000=A57)*('NHẬP ĐƠN'!I$2:I$1000<>"Đã xoá")*('NHẬP ĐƠN'!F$2:F$1000))) | D57: =IF(A57="","",SUMPRODUCT(('NHẬP ĐƠN'!A$2:A$1000=A57)*('NHẬP ĐƠN'!I$2:I$1000<>"Đã xoá")*('NHẬP ĐƠN'!G$2:G$1000)*('NHẬP ĐƠN'!F$2:F$1000))) | E57: =IF(B57>0,D57/B57,"") -> #DIV/0! | F57: =IFERROR(VLOOKUP(A57,'NHẬP ĐƠN'!A:J,10,FALSE),"") | G57: =IF(A57="","",IF(OR(D57>=10000,B57>=5),"⭐ VIP",IF(B57>=3,"💎 Thân thiết","👤 Thường"))) | H57: 300-0011 | I57: 茨城県 | J57: 土浦市 | K57: 央3-19-10 シティハイムサンフィールド202号 | L57: 070 8394 9980
B58: =IF(A58="","",COUNTIFS('NHẬP ĐƠN'!A:A,A58,'NHẬP ĐƠN'!I:I,"<>Đã xoá")) | C58: =IF(A58="","",SUMPRODUCT(('NHẬP ĐƠN'!A$2:A$1000=A58)*('NHẬP ĐƠN'!I$2:I$1000<>"Đã xoá")*('NHẬP ĐƠN'!F$2:F$1000))) | D58: =IF(A58="","",SUMPRODUCT(('NHẬP ĐƠN'!A$2:A$1000=A58)*('NHẬP ĐƠN'!I$2:I$1000<>"Đã xoá")*('NHẬP ĐƠN'!G$2:G$1000)*('NHẬP ĐƠN'!F$2:F$1000))) | E58: =IF(B58>0,D58/B58,"") -> #DIV/0! | F58: =IFERROR(VLOOKUP(A58,'NHẬP ĐƠN'!A:J,10,FALSE),"") | G58: =IF(A58="","",IF(OR(D58>=10000,B58>=5),"⭐ VIP",IF(B58>=3,"💎 Thân thiết","👤 Thường")))
B59: =IF(A59="","",COUNTIFS('NHẬP ĐƠN'!A:A,A59,'NHẬP ĐƠN'!I:I,"<>Đã xoá")) | C59: =IF(A59="","",SUMPRODUCT(('NHẬP ĐƠN'!A$2:A$1000=A59)*('NHẬP ĐƠN'!I$2:I$1000<>"Đã xoá")*('NHẬP ĐƠN'!F$2:F$1000))) | D59: =IF(A59="","",SUMPRODUCT(('NHẬP ĐƠN'!A$2:A$1000=A59)*('NHẬP ĐƠN'!I$2:I$1000<>"Đã xoá")*('NHẬP ĐƠN'!G$2:G$1000)*('NHẬP ĐƠN'!F$2:F$1000))) | E59: =IF(B59>0,D59/B59,"") -> #DIV/0! | F59: =IFERROR(VLOOKUP(A59,'NHẬP ĐƠN'!A:J,10,FALSE),"") | G59: =IF(A59="","",IF(OR(D59>=10000,B59>=5),"⭐ VIP",IF(B59>=3,"💎 Thân thiết","👤 Thường"))) | H59: 134-0081 | I59: 東京都 | J59: 江戸川区 | K59: 北葛西５－２６－７ワイツハイム ４０４ | L59: 8080359847
B60: =IF(A60="","",COUNTIFS('NHẬP ĐƠN'!A:A,A60,'NHẬP ĐƠN'!I:I,"<>Đã xoá")) | C60: =IF(A60="","",SUMPRODUCT(('NHẬP ĐƠN'!A$2:A$1000=A60)*('NHẬP ĐƠN'!I$2:I$1000<>"Đã xoá")*('NHẬP ĐƠN'!F$2:F$1000))) | D60: =IF(A60="","",SUMPRODUCT(('NHẬP ĐƠN'!A$2:A$1000=A60)*('NHẬP ĐƠN'!I$2:I$1000<>"Đã xoá")*('NHẬP ĐƠN'!G$2:G$1000)*('NHẬP ĐƠN'!F$2:F$1000))) | E60: =IF(B60>0,D60/B60,"") -> #DIV/0! | F60: =IFERROR(VLOOKUP(A60,'NHẬP ĐƠN'!A:J,10,FALSE),"") | G60: =IF(A60="","",IF(OR(D60>=10000,B60>=5),"⭐ VIP",IF(B60>=3,"💎 Thân thiết","👤 Thường")))
B61: =IF(A61="","",COUNTIFS('NHẬP ĐƠN'!A:A,A61,'NHẬP ĐƠN'!I:I,"<>Đã xoá")) | C61: =IF(A61="","",SUMPRODUCT(('NHẬP ĐƠN'!A$2:A$1000=A61)*('NHẬP ĐƠN'!I$2:I$1000<>"Đã xoá")*('NHẬP ĐƠN'!F$2:F$1000))) | D61: =IF(A61="","",SUMPRODUCT(('NHẬP ĐƠN'!A$2:A$1000=A61)*('NHẬP ĐƠN'!I$2:I$1000<>"Đã xoá")*('NHẬP ĐƠN'!G$2:G$1000)*('NHẬP ĐƠN'!F$2:F$1000))) | E61: =IF(B61>0,D61/B61,"") -> #DIV/0! | F61: =IFERROR(VLOOKUP(A61,'NHẬP ĐƠN'!A:J,10,FALSE),"") | G61: =IF(A61="","",IF(OR(D61>=10000,B61>=5),"⭐ VIP",IF(B61>=3,"💎 Thân thiết","👤 Thường")))
B62: =IF(A62="","",COUNTIFS('NHẬP ĐƠN'!A:A,A62,'NHẬP ĐƠN'!I:I,"<>Đã xoá")) | C62: =IF(A62="","",SUMPRODUCT(('NHẬP ĐƠN'!A$2:A$1000=A62)*('NHẬP ĐƠN'!I$2:I$1000<>"Đã xoá")*('NHẬP ĐƠN'!F$2:F$1000))) | D62: =IF(A62="","",SUMPRODUCT(('NHẬP ĐƠN'!A$2:A$1000=A62)*('NHẬP ĐƠN'!I$2:I$1000<>"Đã xoá")*('NHẬP ĐƠN'!G$2:G$1000)*('NHẬP ĐƠN'!F$2:F$1000))) | E62: =IF(B62>0,D62/B62,"") -> #DIV/0! | F62: =IFERROR(VLOOKUP(A62,'NHẬP ĐƠN'!A:J,10,FALSE),"") | G62: =IF(A62="","",IF(OR(D62>=10000,B62>=5),"⭐ VIP",IF(B62>=3,"💎 Thân thiết","👤 Thường")))
B63: =IF(A63="","",COUNTIFS('NHẬP ĐƠN'!A:A,A63,'NHẬP ĐƠN'!I:I,"<>Đã xoá")) | C63: =IF(A63="","",SUMPRODUCT(('NHẬP ĐƠN'!A$2:A$1000=A63)*('NHẬP ĐƠN'!I$2:I$1000<>"Đã xoá")*('NHẬP ĐƠN'!F$2:F$1000))) | D63: =IF(A63="","",SUMPRODUCT(('NHẬP ĐƠN'!A$2:A$1000=A63)*('NHẬP ĐƠN'!I$2:I$1000<>"Đã xoá")*('NHẬP ĐƠN'!G$2:G$1000)*('NHẬP ĐƠN'!F$2:F$1000))) | E63: =IF(B63>0,D63/B63,"") -> #DIV/0! | F63: =IFERROR(VLOOKUP(A63,'NHẬP ĐƠN'!A:J,10,FALSE),"") | G63: =IF(A63="","",IF(OR(D63>=10000,B63>=5),"⭐ VIP",IF(B63>=3,"💎 Thân thiết","👤 Thường"))) | H63: 555-0032 | I63: 大阪府 | J63: 大阪市西淀川区 | K63: 大和田 | L63: 8080359847
B64: =IF(A64="","",COUNTIFS('NHẬP ĐƠN'!A:A,A64,'NHẬP ĐƠN'!I:I,"<>Đã xoá")) | C64: =IF(A64="","",SUMPRODUCT(('NHẬP ĐƠN'!A$2:A$1000=A64)*('NHẬP ĐƠN'!I$2:I$1000<>"Đã xoá")*('NHẬP ĐƠN'!F$2:F$1000))) | D64: =IF(A64="","",SUMPRODUCT(('NHẬP ĐƠN'!A$2:A$1000=A64)*('NHẬP ĐƠN'!I$2:I$1000<>"Đã xoá")*('NHẬP ĐƠN'!G$2:G$1000)*('NHẬP ĐƠN'!F$2:F$1000))) | E64: =IF(B64>0,D64/B64,"") -> #DIV/0! | F64: =IFERROR(VLOOKUP(A64,'NHẬP ĐƠN'!A:J,10,FALSE),"") | G64: =IF(A64="","",IF(OR(D64>=10000,B64>=5),"⭐ VIP",IF(B64>=3,"💎 Thân thiết","👤 Thường")))
B65: =IF(A65="","",COUNTIFS('NHẬP ĐƠN'!A:A,A65,'NHẬP ĐƠN'!I:I,"<>Đã xoá")) | C65: =IF(A65="","",SUMPRODUCT(('NHẬP ĐƠN'!A$2:A$1000=A65)*('NHẬP ĐƠN'!I$2:I$1000<>"Đã xoá")*('NHẬP ĐƠN'!F$2:F$1000))) | D65: =IF(A65="","",SUMPRODUCT(('NHẬP ĐƠN'!A$2:A$1000=A65)*('NHẬP ĐƠN'!I$2:I$1000<>"Đã xoá")*('NHẬP ĐƠN'!G$2:G$1000)*('NHẬP ĐƠN'!F$2:F$1000))) | E65: =IF(B65>0,D65/B65,"") -> #DIV/0! | F65: =IFERROR(VLOOKUP(A65,'NHẬP ĐƠN'!A:J,10,FALSE),"") | G65: =IF(A65="","",IF(OR(D65>=10000,B65>=5),"⭐ VIP",IF(B65>=3,"💎 Thân thiết","👤 Thường")))
B66: =IF(A66="","",COUNTIFS('NHẬP ĐƠN'!A:A,A66,'NHẬP ĐƠN'!I:I,"<>Đã xoá")) | C66: =IF(A66="","",SUMPRODUCT(('NHẬP ĐƠN'!A$2:A$1000=A66)*('NHẬP ĐƠN'!I$2:I$1000<>"Đã xoá")*('NHẬP ĐƠN'!F$2:F$1000))) | D66: =IF(A66="","",SUMPRODUCT(('NHẬP ĐƠN'!A$2:A$1000=A66)*('NHẬP ĐƠN'!I$2:I$1000<>"Đã xoá")*('NHẬP ĐƠN'!G$2:G$1000)*('NHẬP ĐƠN'!F$2:F$1000))) | E66: =IF(B66>0,D66/B66,"") -> #DIV/0! | F66: =IFERROR(VLOOKUP(A66,'NHẬP ĐƠN'!A:J,10,FALSE),"") | G66: =IF(A66="","",IF(OR(D66>=10000,B66>=5),"⭐ VIP",IF(B66>=3,"💎 Thân thiết","👤 Thường")))
B67: =IF(A67="","",COUNTIFS('NHẬP ĐƠN'!A:A,A67,'NHẬP ĐƠN'!I:I,"<>Đã xoá")) | C67: =IF(A67="","",SUMPRODUCT(('NHẬP ĐƠN'!A$2:A$1000=A67)*('NHẬP ĐƠN'!I$2:I$1000<>"Đã xoá")*('NHẬP ĐƠN'!F$2:F$1000))) | D67: =IF(A67="","",SUMPRODUCT(('NHẬP ĐƠN'!A$2:A$1000=A67)*('NHẬP ĐƠN'!I$2:I$1000<>"Đã xoá")*('NHẬP ĐƠN'!G$2:G$1000)*('NHẬP ĐƠN'!F$2:F$1000))) | E67: =IF(B67>0,D67/B67,"") -> #DIV/0! | F67: =IFERROR(VLOOKUP(A67,'NHẬP ĐƠN'!A:J,10,FALSE),"") | G67: =IF(A67="","",IF(OR(D67>=10000,B67>=5),"⭐ VIP",IF(B67>=3,"💎 Thân thiết","👤 Thường"))) | H67: 520-2434 | I67: 滋賀県 | J67: 野洲市 | K67: 比江916-4 | L67: 9030991196
B68: =IF(A68="","",COUNTIFS('NHẬP ĐƠN'!A:A,A68,'NHẬP ĐƠN'!I:I,"<>Đã xoá")) | C68: =IF(A68="","",SUMPRODUCT(('NHẬP ĐƠN'!A$2:A$1000=A68)*('NHẬP ĐƠN'!I$2:I$1000<>"Đã xoá")*('NHẬP ĐƠN'!F$2:F$1000))) | D68: =IF(A68="","",SUMPRODUCT(('NHẬP ĐƠN'!A$2:A$1000=A68)*('NHẬP ĐƠN'!I$2:I$1000<>"Đã xoá")*('NHẬP ĐƠN'!G$2:G$1000)*('NHẬP ĐƠN'!F$2:F$1000))) | E68: =IF(B68>0,D68/B68,"") -> #DIV/0! | F68: =IFERROR(VLOOKUP(A68,'NHẬP ĐƠN'!A:J,10,FALSE),"") | G68: =IF(A68="","",IF(OR(D68>=10000,B68>=5),"⭐ VIP",IF(B68>=3,"💎 Thân thiết","👤 Thường"))) | H68: 270-0034 | I68: 千葉県 | J68: 松戸市 | K68: 新松戸7丁目183-1セジュールビューラー203 | L68: 9030991196
B69: =IF(A69="","",COUNTIFS('NHẬP ĐƠN'!A:A,A69,'NHẬP ĐƠN'!I:I,"<>Đã xoá")) | C69: =IF(A69="","",SUMPRODUCT(('NHẬP ĐƠN'!A$2:A$1000=A69)*('NHẬP ĐƠN'!I$2:I$1000<>"Đã xoá")*('NHẬP ĐƠN'!F$2:F$1000))) | D69: =IF(A69="","",SUMPRODUCT(('NHẬP ĐƠN'!A$2:A$1000=A69)*('NHẬP ĐƠN'!I$2:I$1000<>"Đã xoá")*('NHẬP ĐƠN'!G$2:G$1000)*('NHẬP ĐƠN'!F$2:F$1000))) | E69: =IF(B69>0,D69/B69,"") -> #DIV/0! | F69: =IFERROR(VLOOKUP(A69,'NHẬP ĐƠN'!A:J,10,FALSE),"") | G69: =IF(A69="","",IF(OR(D69>=10000,B69>=5),"⭐ VIP",IF(B69>=3,"💎 Thân thiết","👤 Thường")))
B70: =IF(A70="","",COUNTIFS('NHẬP ĐƠN'!A:A,A70,'NHẬP ĐƠN'!I:I,"<>Đã xoá")) | C70: =IF(A70="","",SUMPRODUCT(('NHẬP ĐƠN'!A$2:A$1000=A70)*('NHẬP ĐƠN'!I$2:I$1000<>"Đã xoá")*('NHẬP ĐƠN'!F$2:F$1000))) | D70: =IF(A70="","",SUMPRODUCT(('NHẬP ĐƠN'!A$2:A$1000=A70)*('NHẬP ĐƠN'!I$2:I$1000<>"Đã xoá")*('NHẬP ĐƠN'!G$2:G$1000)*('NHẬP ĐƠN'!F$2:F$1000))) | E70: =IF(B70>0,D70/B70,"") -> #DIV/0! | F70: =IFERROR(VLOOKUP(A70,'NHẬP ĐƠN'!A:J,10,FALSE),"") | G70: =IF(A70="","",IF(OR(D70>=10000,B70>=5),"⭐ VIP",IF(B70>=3,"💎 Thân thiết","👤 Thường")))
B71: =IF(A71="","",COUNTIFS('NHẬP ĐƠN'!A:A,A71,'NHẬP ĐƠN'!I:I,"<>Đã xoá")) | C71: =IF(A71="","",SUMPRODUCT(('NHẬP ĐƠN'!A$2:A$1000=A71)*('NHẬP ĐƠN'!I$2:I$1000<>"Đã xoá")*('NHẬP ĐƠN'!F$2:F$1000))) | D71: =IF(A71="","",SUMPRODUCT(('NHẬP ĐƠN'!A$2:A$1000=A71)*('NHẬP ĐƠN'!I$2:I$1000<>"Đã xoá")*('NHẬP ĐƠN'!G$2:G$1000)*('NHẬP ĐƠN'!F$2:F$1000))) | E71: =IF(B71>0,D71/B71,"") -> #DIV/0! | F71: =IFERROR(VLOOKUP(A71,'NHẬP ĐƠN'!A:J,10,FALSE),"") | G71: =IF(A71="","",IF(OR(D71>=10000,B71>=5),"⭐ VIP",IF(B71>=3,"💎 Thân thiết","👤 Thường")))
B72: =IF(A72="","",COUNTIFS('NHẬP ĐƠN'!A:A,A72,'NHẬP ĐƠN'!I:I,"<>Đã xoá")) | C72: =IF(A72="","",SUMPRODUCT(('NHẬP ĐƠN'!A$2:A$1000=A72)*('NHẬP ĐƠN'!I$2:I$1000<>"Đã xoá")*('NHẬP ĐƠN'!F$2:F$1000))) | D72: =IF(A72="","",SUMPRODUCT(('NHẬP ĐƠN'!A$2:A$1000=A72)*('NHẬP ĐƠN'!I$2:I$1000<>"Đã xoá")*('NHẬP ĐƠN'!G$2:G$1000)*('NHẬP ĐƠN'!F$2:F$1000))) | E72: =IF(B72>0,D72/B72,"") -> #DIV/0! | F72: =IFERROR(VLOOKUP(A72,'NHẬP ĐƠN'!A:J,10,FALSE),"") | G72: =IF(A72="","",IF(OR(D72>=10000,B72>=5),"⭐ VIP",IF(B72>=3,"💎 Thân thiết","👤 Thường")))
B73: =IF(A73="","",COUNTIFS('NHẬP ĐƠN'!A:A,A73,'NHẬP ĐƠN'!I:I,"<>Đã xoá")) | C73: =IF(A73="","",SUMPRODUCT(('NHẬP ĐƠN'!A$2:A$1000=A73)*('NHẬP ĐƠN'!I$2:I$1000<>"Đã xoá")*('NHẬP ĐƠN'!F$2:F$1000))) | D73: =IF(A73="","",SUMPRODUCT(('NHẬP ĐƠN'!A$2:A$1000=A73)*('NHẬP ĐƠN'!I$2:I$1000<>"Đã xoá")*('NHẬP ĐƠN'!G$2:G$1000)*('NHẬP ĐƠN'!F$2:F$1000))) | E73: =IF(B73>0,D73/B73,"") -> #DIV/0! | F73: =IFERROR(VLOOKUP(A73,'NHẬP ĐƠN'!A:J,10,FALSE),"") | G73: =IF(A73="","",IF(OR(D73>=10000,B73>=5),"⭐ VIP",IF(B73>=3,"💎 Thân thiết","👤 Thường")))
B74: =IF(A74="","",COUNTIFS('NHẬP ĐƠN'!A:A,A74,'NHẬP ĐƠN'!I:I,"<>Đã xoá")) | C74: =IF(A74="","",SUMPRODUCT(('NHẬP ĐƠN'!A$2:A$1000=A74)*('NHẬP ĐƠN'!I$2:I$1000<>"Đã xoá")*('NHẬP ĐƠN'!F$2:F$1000))) | D74: =IF(A74="","",SUMPRODUCT(('NHẬP ĐƠN'!A$2:A$1000=A74)*('NHẬP ĐƠN'!I$2:I$1000<>"Đã xoá")*('NHẬP ĐƠN'!G$2:G$1000)*('NHẬP ĐƠN'!F$2:F$1000))) | E74: =IF(B74>0,D74/B74,"") -> #DIV/0! | F74: =IFERROR(VLOOKUP(A74,'NHẬP ĐƠN'!A:J,10,FALSE),"") | G74: =IF(A74="","",IF(OR(D74>=10000,B74>=5),"⭐ VIP",IF(B74>=3,"💎 Thân thiết","👤 Thường")))
B75: =IF(A75="","",COUNTIFS('NHẬP ĐƠN'!A:A,A75,'NHẬP ĐƠN'!I:I,"<>Đã xoá")) | C75: =IF(A75="","",SUMPRODUCT(('NHẬP ĐƠN'!A$2:A$1000=A75)*('NHẬP ĐƠN'!I$2:I$1000<>"Đã xoá")*('NHẬP ĐƠN'!F$2:F$1000))) | D75: =IF(A75="","",SUMPRODUCT(('NHẬP ĐƠN'!A$2:A$1000=A75)*('NHẬP ĐƠN'!I$2:I$1000<>"Đã xoá")*('NHẬP ĐƠN'!G$2:G$1000)*('NHẬP ĐƠN'!F$2:F$1000))) | E75: =IF(B75>0,D75/B75,"") -> #DIV/0! | F75: =IFERROR(VLOOKUP(A75,'NHẬP ĐƠN'!A:J,10,FALSE),"") | G75: =IF(A75="","",IF(OR(D75>=10000,B75>=5),"⭐ VIP",IF(B75>=3,"💎 Thân thiết","👤 Thường")))
B76: =IF(A76="","",COUNTIFS('NHẬP ĐƠN'!A:A,A76,'NHẬP ĐƠN'!I:I,"<>Đã xoá")) | C76: =IF(A76="","",SUMPRODUCT(('NHẬP ĐƠN'!A$2:A$1000=A76)*('NHẬP ĐƠN'!I$2:I$1000<>"Đã xoá")*('NHẬP ĐƠN'!F$2:F$1000))) | D76: =IF(A76="","",SUMPRODUCT(('NHẬP ĐƠN'!A$2:A$1000=A76)*('NHẬP ĐƠN'!I$2:I$1000<>"Đã xoá")*('NHẬP ĐƠN'!G$2:G$1000)*('NHẬP ĐƠN'!F$2:F$1000))) | E76: =IF(B76>0,D76/B76,"") -> #DIV/0! | F76: =IFERROR(VLOOKUP(A76,'NHẬP ĐƠN'!A:J,10,FALSE),"") | G76: =IF(A76="","",IF(OR(D76>=10000,B76>=5),"⭐ VIP",IF(B76>=3,"💎 Thân thiết","👤 Thường")))
B77: =IF(A77="","",COUNTIFS('NHẬP ĐƠN'!A:A,A77,'NHẬP ĐƠN'!I:I,"<>Đã xoá")) | C77: =IF(A77="","",SUMPRODUCT(('NHẬP ĐƠN'!A$2:A$1000=A77)*('NHẬP ĐƠN'!I$2:I$1000<>"Đã xoá")*('NHẬP ĐƠN'!F$2:F$1000))) | D77: =IF(A77="","",SUMPRODUCT(('NHẬP ĐƠN'!A$2:A$1000=A77)*('NHẬP ĐƠN'!I$2:I$1000<>"Đã xoá")*('NHẬP ĐƠN'!G$2:G$1000)*('NHẬP ĐƠN'!F$2:F$1000))) | E77: =IF(B77>0,D77/B77,"") -> #DIV/0! | F77: =IFERROR(VLOOKUP(A77,'NHẬP ĐƠN'!A:J,10,FALSE),"") | G77: =IF(A77="","",IF(OR(D77>=10000,B77>=5),"⭐ VIP",IF(B77>=3,"💎 Thân thiết","👤 Thường"))) | H77: 251-0057 | I77: 神奈川県 | J77: 藤沢市 | K77: -10-33エストレージャ湘南216 | L77: 8080359847
B78: =IF(A78="","",COUNTIFS('NHẬP ĐƠN'!A:A,A78,'NHẬP ĐƠN'!I:I,"<>Đã xoá")) | C78: =IF(A78="","",SUMPRODUCT(('NHẬP ĐƠN'!A$2:A$1000=A78)*('NHẬP ĐƠN'!I$2:I$1000<>"Đã xoá")*('NHẬP ĐƠN'!F$2:F$1000))) | D78: =IF(A78="","",SUMPRODUCT(('NHẬP ĐƠN'!A$2:A$1000=A78)*('NHẬP ĐƠN'!I$2:I$1000<>"Đã xoá")*('NHẬP ĐƠN'!G$2:G$1000)*('NHẬP ĐƠN'!F$2:F$1000))) | E78: =IF(B78>0,D78/B78,"") -> #DIV/0! | F78: =IFERROR(VLOOKUP(A78,'NHẬP ĐƠN'!A:J,10,FALSE),"") | G78: =IF(A78="","",IF(OR(D78>=10000,B78>=5),"⭐ VIP",IF(B78>=3,"💎 Thân thiết","👤 Thường")))
B79: =IF(A79="","",COUNTIFS('NHẬP ĐƠN'!A:A,A79,'NHẬP ĐƠN'!I:I,"<>Đã xoá")) | C79: =IF(A79="","",SUMPRODUCT(('NHẬP ĐƠN'!A$2:A$1000=A79)*('NHẬP ĐƠN'!I$2:I$1000<>"Đã xoá")*('NHẬP ĐƠN'!F$2:F$1000))) | D79: =IF(A79="","",SUMPRODUCT(('NHẬP ĐƠN'!A$2:A$1000=A79)*('NHẬP ĐƠN'!I$2:I$1000<>"Đã xoá")*('NHẬP ĐƠN'!G$2:G$1000)*('NHẬP ĐƠN'!F$2:F$1000))) | E79: =IF(B79>0,D79/B79,"") -> #DIV/0! | F79: =IFERROR(VLOOKUP(A79,'NHẬP ĐƠN'!A:J,10,FALSE),"") | G79: =IF(A79="","",IF(OR(D79>=10000,B79>=5),"⭐ VIP",IF(B79>=3,"💎 Thân thiết","👤 Thường")))
B80: =IF(A80="","",COUNTIFS('NHẬP ĐƠN'!A:A,A80,'NHẬP ĐƠN'!I:I,"<>Đã xoá")) | C80: =IF(A80="","",SUMPRODUCT(('NHẬP ĐƠN'!A$2:A$1000=A80)*('NHẬP ĐƠN'!I$2:I$1000<>"Đã xoá")*('NHẬP ĐƠN'!F$2:F$1000))) | D80: =IF(A80="","",SUMPRODUCT(('NHẬP ĐƠN'!A$2:A$1000=A80)*('NHẬP ĐƠN'!I$2:I$1000<>"Đã xoá")*('NHẬP ĐƠN'!G$2:G$1000)*('NHẬP ĐƠN'!F$2:F$1000))) | E80: =IF(B80>0,D80/B80,"") -> #DIV/0! | F80: =IFERROR(VLOOKUP(A80,'NHẬP ĐƠN'!A:J,10,FALSE),"") | G80: =IF(A80="","",IF(OR(D80>=10000,B80>=5),"⭐ VIP",IF(B80>=3,"💎 Thân thiết","👤 Thường")))
B81: =IF(A81="","",COUNTIFS('NHẬP ĐƠN'!A:A,A81,'NHẬP ĐƠN'!I:I,"<>Đã xoá")) | C81: =IF(A81="","",SUMPRODUCT(('NHẬP ĐƠN'!A$2:A$1000=A81)*('NHẬP ĐƠN'!I$2:I$1000<>"Đã xoá")*('NHẬP ĐƠN'!F$2:F$1000))) | D81: =IF(A81="","",SUMPRODUCT(('NHẬP ĐƠN'!A$2:A$1000=A81)*('NHẬP ĐƠN'!I$2:I$1000<>"Đã xoá")*('NHẬP ĐƠN'!G$2:G$1000)*('NHẬP ĐƠN'!F$2:F$1000))) | E81: =IF(B81>0,D81/B81,"") -> #DIV/0! | F81: =IFERROR(VLOOKUP(A81,'NHẬP ĐƠN'!A:J,10,FALSE),"") | G81: =IF(A81="","",IF(OR(D81>=10000,B81>=5),"⭐ VIP",IF(B81>=3,"💎 Thân thiết","👤 Thường")))
B82: =IF(A82="","",COUNTIFS('NHẬP ĐƠN'!A:A,A82,'NHẬP ĐƠN'!I:I,"<>Đã xoá")) | C82: =IF(A82="","",SUMPRODUCT(('NHẬP ĐƠN'!A$2:A$1000=A82)*('NHẬP ĐƠN'!I$2:I$1000<>"Đã xoá")*('NHẬP ĐƠN'!F$2:F$1000))) | D82: =IF(A82="","",SUMPRODUCT(('NHẬP ĐƠN'!A$2:A$1000=A82)*('NHẬP ĐƠN'!I$2:I$1000<>"Đã xoá")*('NHẬP ĐƠN'!G$2:G$1000)*('NHẬP ĐƠN'!F$2:F$1000))) | E82: =IF(B82>0,D82/B82,"") -> #DIV/0! | F82: =IFERROR(VLOOKUP(A82,'NHẬP ĐƠN'!A:J,10,FALSE),"") | G82: =IF(A82="","",IF(OR(D82>=10000,B82>=5),"⭐ VIP",IF(B82>=3,"💎 Thân thiết","👤 Thường")))
B83: =IF(A83="","",COUNTIFS('NHẬP ĐƠN'!A:A,A83,'NHẬP ĐƠN'!I:I,"<>Đã xoá")) | C83: =IF(A83="","",SUMPRODUCT(('NHẬP ĐƠN'!A$2:A$1000=A83)*('NHẬP ĐƠN'!I$2:I$1000<>"Đã xoá")*('NHẬP ĐƠN'!F$2:F$1000))) | D83: =IF(A83="","",SUMPRODUCT(('NHẬP ĐƠN'!A$2:A$1000=A83)*('NHẬP ĐƠN'!I$2:I$1000<>"Đã xoá")*('NHẬP ĐƠN'!G$2:G$1000)*('NHẬP ĐƠN'!F$2:F$1000))) | E83: =IF(B83>0,D83/B83,"") -> #DIV/0! | F83: =IFERROR(VLOOKUP(A83,'NHẬP ĐƠN'!A:J,10,FALSE),"") | G83: =IF(A83="","",IF(OR(D83>=10000,B83>=5),"⭐ VIP",IF(B83>=3,"💎 Thân thiết","👤 Thường")))
B84: =IF(A84="","",COUNTIFS('NHẬP ĐƠN'!A:A,A84,'NHẬP ĐƠN'!I:I,"<>Đã xoá")) | C84: =IF(A84="","",SUMPRODUCT(('NHẬP ĐƠN'!A$2:A$1000=A84)*('NHẬP ĐƠN'!I$2:I$1000<>"Đã xoá")*('NHẬP ĐƠN'!F$2:F$1000))) | D84: =IF(A84="","",SUMPRODUCT(('NHẬP ĐƠN'!A$2:A$1000=A84)*('NHẬP ĐƠN'!I$2:I$1000<>"Đã xoá")*('NHẬP ĐƠN'!G$2:G$1000)*('NHẬP ĐƠN'!F$2:F$1000))) | E84: =IF(B84>0,D84/B84,"") -> #DIV/0! | F84: =IFERROR(VLOOKUP(A84,'NHẬP ĐƠN'!A:J,10,FALSE),"") | G84: =IF(A84="","",IF(OR(D84>=10000,B84>=5),"⭐ VIP",IF(B84>=3,"💎 Thân thiết","👤 Thường")))
B85: =IF(A85="","",COUNTIFS('NHẬP ĐƠN'!A:A,A85,'NHẬP ĐƠN'!I:I,"<>Đã xoá")) | C85: =IF(A85="","",SUMPRODUCT(('NHẬP ĐƠN'!A$2:A$1000=A85)*('NHẬP ĐƠN'!I$2:I$1000<>"Đã xoá")*('NHẬP ĐƠN'!F$2:F$1000))) | D85: =IF(A85="","",SUMPRODUCT(('NHẬP ĐƠN'!A$2:A$1000=A85)*('NHẬP ĐƠN'!I$2:I$1000<>"Đã xoá")*('NHẬP ĐƠN'!G$2:G$1000)*('NHẬP ĐƠN'!F$2:F$1000))) | E85: =IF(B85>0,D85/B85,"") -> #DIV/0! | F85: =IFERROR(VLOOKUP(A85,'NHẬP ĐƠN'!A:J,10,FALSE),"") | G85: =IF(A85="","",IF(OR(D85>=10000,B85>=5),"⭐ VIP",IF(B85>=3,"💎 Thân thiết","👤 Thường")))
B86: =IF(A86="","",COUNTIFS('NHẬP ĐƠN'!A:A,A86,'NHẬP ĐƠN'!I:I,"<>Đã xoá")) | C86: =IF(A86="","",SUMPRODUCT(('NHẬP ĐƠN'!A$2:A$1000=A86)*('NHẬP ĐƠN'!I$2:I$1000<>"Đã xoá")*('NHẬP ĐƠN'!F$2:F$1000))) | D86: =IF(A86="","",SUMPRODUCT(('NHẬP ĐƠN'!A$2:A$1000=A86)*('NHẬP ĐƠN'!I$2:I$1000<>"Đã xoá")*('NHẬP ĐƠN'!G$2:G$1000)*('NHẬP ĐƠN'!F$2:F$1000))) | E86: =IF(B86>0,D86/B86,"") -> #DIV/0! | F86: =IFERROR(VLOOKUP(A86,'NHẬP ĐƠN'!A:J,10,FALSE),"") | G86: =IF(A86="","",IF(OR(D86>=10000,B86>=5),"⭐ VIP",IF(B86>=3,"💎 Thân thiết","👤 Thường"))) | H86: 733-0012 | I86: 広島県 | J86: 広島市西区 | K86: 中広町3丁目2-1-704 | L86: 9030991196
B87: =IF(A87="","",COUNTIFS('NHẬP ĐƠN'!A:A,A87,'NHẬP ĐƠN'!I:I,"<>Đã xoá")) | C87: =IF(A87="","",SUMPRODUCT(('NHẬP ĐƠN'!A$2:A$1000=A87)*('NHẬP ĐƠN'!I$2:I$1000<>"Đã xoá")*('NHẬP ĐƠN'!F$2:F$1000))) | D87: =IF(A87="","",SUMPRODUCT(('NHẬP ĐƠN'!A$2:A$1000=A87)*('NHẬP ĐƠN'!I$2:I$1000<>"Đã xoá")*('NHẬP ĐƠN'!G$2:G$1000)*('NHẬP ĐƠN'!F$2:F$1000))) | E87: =IF(B87>0,D87/B87,"") -> #DIV/0! | F87: =IFERROR(VLOOKUP(A87,'NHẬP ĐƠN'!A:J,10,FALSE),"") | G87: =IF(A87="","",IF(OR(D87>=10000,B87>=5),"⭐ VIP",IF(B87>=3,"💎 Thân thiết","👤 Thường"))) | H87: 270-0006 | I87: 千葉県 | J87: 松戸市 | K87: 大金4-250-1市川マンション102号 | L87: 9030991196
B88: =IF(A88="","",COUNTIFS('NHẬP ĐƠN'!A:A,A88,'NHẬP ĐƠN'!I:I,"<>Đã xoá")) | C88: =IF(A88="","",SUMPRODUCT(('NHẬP ĐƠN'!A$2:A$1000=A88)*('NHẬP ĐƠN'!I$2:I$1000<>"Đã xoá")*('NHẬP ĐƠN'!F$2:F$1000))) | D88: =IF(A88="","",SUMPRODUCT(('NHẬP ĐƠN'!A$2:A$1000=A88)*('NHẬP ĐƠN'!I$2:I$1000<>"Đã xoá")*('NHẬP ĐƠN'!G$2:G$1000)*('NHẬP ĐƠN'!F$2:F$1000))) | E88: =IF(B88>0,D88/B88,"") -> #DIV/0! | F88: =IFERROR(VLOOKUP(A88,'NHẬP ĐƠN'!A:J,10,FALSE),"") | G88: =IF(A88="","",IF(OR(D88>=10000,B88>=5),"⭐ VIP",IF(B88>=3,"💎 Thân thiết","👤 Thường"))) | H88: 370-2454 | I88: 群馬県 | J88: 富岡市 | K88: 田島300番地スクエア浅川A-3 | L88: 9030991196
B89: =IF(A89="","",COUNTIFS('NHẬP ĐƠN'!A:A,A89,'NHẬP ĐƠN'!I:I,"<>Đã xoá")) | C89: =IF(A89="","",SUMPRODUCT(('NHẬP ĐƠN'!A$2:A$1000=A89)*('NHẬP ĐƠN'!I$2:I$1000<>"Đã xoá")*('NHẬP ĐƠN'!F$2:F$1000))) | D89: =IF(A89="","",SUMPRODUCT(('NHẬP ĐƠN'!A$2:A$1000=A89)*('NHẬP ĐƠN'!I$2:I$1000<>"Đã xoá")*('NHẬP ĐƠN'!G$2:G$1000)*('NHẬP ĐƠN'!F$2:F$1000))) | E89: =IF(B89>0,D89/B89,"") -> #DIV/0! | F89: =IFERROR(VLOOKUP(A89,'NHẬP ĐƠN'!A:J,10,FALSE),"") | G89: =IF(A89="","",IF(OR(D89>=10000,B89>=5),"⭐ VIP",IF(B89>=3,"💎 Thân thiết","👤 Thường")))
B90: =IF(A90="","",COUNTIFS('NHẬP ĐƠN'!A:A,A90,'NHẬP ĐƠN'!I:I,"<>Đã xoá")) | C90: =IF(A90="","",SUMPRODUCT(('NHẬP ĐƠN'!A$2:A$1000=A90)*('NHẬP ĐƠN'!I$2:I$1000<>"Đã xoá")*('NHẬP ĐƠN'!F$2:F$1000))) | D90: =IF(A90="","",SUMPRODUCT(('NHẬP ĐƠN'!A$2:A$1000=A90)*('NHẬP ĐƠN'!I$2:I$1000<>"Đã xoá")*('NHẬP ĐƠN'!G$2:G$1000)*('NHẬP ĐƠN'!F$2:F$1000))) | E90: =IF(B90>0,D90/B90,"") -> #DIV/0! | F90: =IFERROR(VLOOKUP(A90,'NHẬP ĐƠN'!A:J,10,FALSE),"") | G90: =IF(A90="","",IF(OR(D90>=10000,B90>=5),"⭐ VIP",IF(B90>=3,"💎 Thân thiết","👤 Thường")))
B91: =IF(A91="","",COUNTIFS('NHẬP ĐƠN'!A:A,A91,'NHẬP ĐƠN'!I:I,"<>Đã xoá")) | C91: =IF(A91="","",SUMPRODUCT(('NHẬP ĐƠN'!A$2:A$1000=A91)*('NHẬP ĐƠN'!I$2:I$1000<>"Đã xoá")*('NHẬP ĐƠN'!F$2:F$1000))) | D91: =IF(A91="","",SUMPRODUCT(('NHẬP ĐƠN'!A$2:A$1000=A91)*('NHẬP ĐƠN'!I$2:I$1000<>"Đã xoá")*('NHẬP ĐƠN'!G$2:G$1000)*('NHẬP ĐƠN'!F$2:F$1000))) | E91: =IF(B91>0,D91/B91,"") -> #DIV/0! | F91: =IFERROR(VLOOKUP(A91,'NHẬP ĐƠN'!A:J,10,FALSE),"") | G91: =IF(A91="","",IF(OR(D91>=10000,B91>=5),"⭐ VIP",IF(B91>=3,"💎 Thân thiết","👤 Thường")))
B92: =IF(A92="","",COUNTIFS('NHẬP ĐƠN'!A:A,A92,'NHẬP ĐƠN'!I:I,"<>Đã xoá")) | C92: =IF(A92="","",SUMPRODUCT(('NHẬP ĐƠN'!A$2:A$1000=A92)*('NHẬP ĐƠN'!I$2:I$1000<>"Đã xoá")*('NHẬP ĐƠN'!F$2:F$1000))) | D92: =IF(A92="","",SUMPRODUCT(('NHẬP ĐƠN'!A$2:A$1000=A92)*('NHẬP ĐƠN'!I$2:I$1000<>"Đã xoá")*('NHẬP ĐƠN'!G$2:G$1000)*('NHẬP ĐƠN'!F$2:F$1000))) | E92: =IF(B92>0,D92/B92,"") -> #DIV/0! | F92: =IFERROR(VLOOKUP(A92,'NHẬP ĐƠN'!A:J,10,FALSE),"") | G92: =IF(A92="","",IF(OR(D92>=10000,B92>=5),"⭐ VIP",IF(B92>=3,"💎 Thân thiết","👤 Thường")))
B93: =IF(A93="","",COUNTIFS('NHẬP ĐƠN'!A:A,A93,'NHẬP ĐƠN'!I:I,"<>Đã xoá")) | C93: =IF(A93="","",SUMPRODUCT(('NHẬP ĐƠN'!A$2:A$1000=A93)*('NHẬP ĐƠN'!I$2:I$1000<>"Đã xoá")*('NHẬP ĐƠN'!F$2:F$1000))) | D93: =IF(A93="","",SUMPRODUCT(('NHẬP ĐƠN'!A$2:A$1000=A93)*('NHẬP ĐƠN'!I$2:I$1000<>"Đã xoá")*('NHẬP ĐƠN'!G$2:G$1000)*('NHẬP ĐƠN'!F$2:F$1000))) | E93: =IF(B93>0,D93/B93,"") -> #DIV/0! | F93: =IFERROR(VLOOKUP(A93,'NHẬP ĐƠN'!A:J,10,FALSE),"") | G93: =IF(A93="","",IF(OR(D93>=10000,B93>=5),"⭐ VIP",IF(B93>=3,"💎 Thân thiết","👤 Thường")))
B94: =IF(A94="","",COUNTIFS('NHẬP ĐƠN'!A:A,A94,'NHẬP ĐƠN'!I:I,"<>Đã xoá")) | C94: =IF(A94="","",SUMPRODUCT(('NHẬP ĐƠN'!A$2:A$1000=A94)*('NHẬP ĐƠN'!I$2:I$1000<>"Đã xoá")*('NHẬP ĐƠN'!F$2:F$1000))) | D94: =IF(A94="","",SUMPRODUCT(('NHẬP ĐƠN'!A$2:A$1000=A94)*('NHẬP ĐƠN'!I$2:I$1000<>"Đã xoá")*('NHẬP ĐƠN'!G$2:G$1000)*('NHẬP ĐƠN'!F$2:F$1000))) | E94: =IF(B94>0,D94/B94,"") -> #DIV/0! | F94: =IFERROR(VLOOKUP(A94,'NHẬP ĐƠN'!A:J,10,FALSE),"") | G94: =IF(A94="","",IF(OR(D94>=10000,B94>=5),"⭐ VIP",IF(B94>=3,"💎 Thân thiết","👤 Thường")))
B95: =IF(A95="","",COUNTIFS('NHẬP ĐƠN'!A:A,A95,'NHẬP ĐƠN'!I:I,"<>Đã xoá")) | C95: =IF(A95="","",SUMPRODUCT(('NHẬP ĐƠN'!A$2:A$1000=A95)*('NHẬP ĐƠN'!I$2:I$1000<>"Đã xoá")*('NHẬP ĐƠN'!F$2:F$1000))) | D95: =IF(A95="","",SUMPRODUCT(('NHẬP ĐƠN'!A$2:A$1000=A95)*('NHẬP ĐƠN'!I$2:I$1000<>"Đã xoá")*('NHẬP ĐƠN'!G$2:G$1000)*('NHẬP ĐƠN'!F$2:F$1000))) | E95: =IF(B95>0,D95/B95,"") -> #DIV/0! | F95: =IFERROR(VLOOKUP(A95,'NHẬP ĐƠN'!A:J,10,FALSE),"") | G95: =IF(A95="","",IF(OR(D95>=10000,B95>=5),"⭐ VIP",IF(B95>=3,"💎 Thân thiết","👤 Thường")))
B96: =IF(A96="","",COUNTIFS('NHẬP ĐƠN'!A:A,A96,'NHẬP ĐƠN'!I:I,"<>Đã xoá")) | C96: =IF(A96="","",SUMPRODUCT(('NHẬP ĐƠN'!A$2:A$1000=A96)*('NHẬP ĐƠN'!I$2:I$1000<>"Đã xoá")*('NHẬP ĐƠN'!F$2:F$1000))) | D96: =IF(A96="","",SUMPRODUCT(('NHẬP ĐƠN'!A$2:A$1000=A96)*('NHẬP ĐƠN'!I$2:I$1000<>"Đã xoá")*('NHẬP ĐƠN'!G$2:G$1000)*('NHẬP ĐƠN'!F$2:F$1000))) | E96: =IF(B96>0,D96/B96,"") -> #DIV/0! | F96: =IFERROR(VLOOKUP(A96,'NHẬP ĐƠN'!A:J,10,FALSE),"") | G96: =IF(A96="","",IF(OR(D96>=10000,B96>=5),"⭐ VIP",IF(B96>=3,"💎 Thân thiết","👤 Thường"))) | H96: 436-0027 | I96: 静岡県 | J96: 掛川市 | K96: 2-21-13ティアラ103号 | L96: 070 9186 1846
B97: =IF(A97="","",COUNTIFS('NHẬP ĐƠN'!A:A,A97,'NHẬP ĐƠN'!I:I,"<>Đã xoá")) | C97: =IF(A97="","",SUMPRODUCT(('NHẬP ĐƠN'!A$2:A$1000=A97)*('NHẬP ĐƠN'!I$2:I$1000<>"Đã xoá")*('NHẬP ĐƠN'!F$2:F$1000))) | D97: =IF(A97="","",SUMPRODUCT(('NHẬP ĐƠN'!A$2:A$1000=A97)*('NHẬP ĐƠN'!I$2:I$1000<>"Đã xoá")*('NHẬP ĐƠN'!G$2:G$1000)*('NHẬP ĐƠN'!F$2:F$1000))) | E97: =IF(B97>0,D97/B97,"") -> #DIV/0! | F97: =IFERROR(VLOOKUP(A97,'NHẬP ĐƠN'!A:J,10,FALSE),"") | G97: =IF(A97="","",IF(OR(D97>=10000,B97>=5),"⭐ VIP",IF(B97>=3,"💎 Thân thiết","👤 Thường"))) | H97: 436-0027 | I97: 静岡県 | J97: 掛川市 | K97: -21-13 ティアラ103号 | L97: 070 9186 1846
B98: =IF(A98="","",COUNTIFS('NHẬP ĐƠN'!A:A,A98,'NHẬP ĐƠN'!I:I,"<>Đã xoá")) | C98: =IF(A98="","",SUMPRODUCT(('NHẬP ĐƠN'!A$2:A$1000=A98)*('NHẬP ĐƠN'!I$2:I$1000<>"Đã xoá")*('NHẬP ĐƠN'!F$2:F$1000))) | D98: =IF(A98="","",SUMPRODUCT(('NHẬP ĐƠN'!A$2:A$1000=A98)*('NHẬP ĐƠN'!I$2:I$1000<>"Đã xoá")*('NHẬP ĐƠN'!G$2:G$1000)*('NHẬP ĐƠN'!F$2:F$1000))) | E98: =IF(B98>0,D98/B98,"") -> #DIV/0! | F98: =IFERROR(VLOOKUP(A98,'NHẬP ĐƠN'!A:J,10,FALSE),"") | G98: =IF(A98="","",IF(OR(D98>=10000,B98>=5),"⭐ VIP",IF(B98>=3,"💎 Thân thiết","👤 Thường"))) | H98: 511-0818 | I98: 三重県 | J98: 桑名市 | K98: 高塚町１丁目52 ビゥーテラス202号室 | L98: 9030991196
B99: =IF(A99="","",COUNTIFS('NHẬP ĐƠN'!A:A,A99,'NHẬP ĐƠN'!I:I,"<>Đã xoá")) | C99: =IF(A99="","",SUMPRODUCT(('NHẬP ĐƠN'!A$2:A$1000=A99)*('NHẬP ĐƠN'!I$2:I$1000<>"Đã xoá")*('NHẬP ĐƠN'!F$2:F$1000))) | D99: =IF(A99="","",SUMPRODUCT(('NHẬP ĐƠN'!A$2:A$1000=A99)*('NHẬP ĐƠN'!I$2:I$1000<>"Đã xoá")*('NHẬP ĐƠN'!G$2:G$1000)*('NHẬP ĐƠN'!F$2:F$1000))) | E99: =IF(B99>0,D99/B99,"") -> #DIV/0! | F99: =IFERROR(VLOOKUP(A99,'NHẬP ĐƠN'!A:J,10,FALSE),"") | G99: =IF(A99="","",IF(OR(D99>=10000,B99>=5),"⭐ VIP",IF(B99>=3,"💎 Thân thiết","👤 Thường")))
B100: =IF(A100="","",COUNTIFS('NHẬP ĐƠN'!A:A,A100,'NHẬP ĐƠN'!I:I,"<>Đã xoá")) | C100: =IF(A100="","",SUMPRODUCT(('NHẬP ĐƠN'!A$2:A$1000=A100)*('NHẬP ĐƠN'!I$2:I$1000<>"Đã xoá")*('NHẬP ĐƠN'!F$2:F$1000))) | D100: =IF(A100="","",SUMPRODUCT(('NHẬP ĐƠN'!A$2:A$1000=A100)*('NHẬP ĐƠN'!I$2:I$1000<>"Đã xoá")*('NHẬP ĐƠN'!G$2:G$1000)*('NHẬP ĐƠN'!F$2:F$1000))) | E100: =IF(B100>0,D100/B100,"") -> #DIV/0! | F100: =IFERROR(VLOOKUP(A100,'NHẬP ĐƠN'!A:J,10,FALSE),"") | G100: =IF(A100="","",IF(OR(D100>=10000,B100>=5),"⭐ VIP",IF(B100>=3,"💎 Thân thiết","👤 Thường")))
B101: =IF(A101="","",COUNTIFS('NHẬP ĐƠN'!A:A,A101,'NHẬP ĐƠN'!I:I,"<>Đã xoá")) | C101: =IF(A101="","",SUMPRODUCT(('NHẬP ĐƠN'!A$2:A$1000=A101)*('NHẬP ĐƠN'!I$2:I$1000<>"Đã xoá")*('NHẬP ĐƠN'!F$2:F$1000))) | D101: =IF(A101="","",SUMPRODUCT(('NHẬP ĐƠN'!A$2:A$1000=A101)*('NHẬP ĐƠN'!I$2:I$1000<>"Đã xoá")*('NHẬP ĐƠN'!G$2:G$1000)*('NHẬP ĐƠN'!F$2:F$1000))) | E101: =IF(B101>0,D101/B101,"") -> #DIV/0! | F101: =IFERROR(VLOOKUP(A101,'NHẬP ĐƠN'!A:J,10,FALSE),"") | G101: =IF(A101="","",IF(OR(D101>=10000,B101>=5),"⭐ VIP",IF(B101>=3,"💎 Thân thiết","👤 Thường")))
B102: =IF(A102="","",COUNTIFS('NHẬP ĐƠN'!A:A,A102,'NHẬP ĐƠN'!I:I,"<>Đã xoá")) | C102: =IF(A102="","",SUMPRODUCT(('NHẬP ĐƠN'!A$2:A$1000=A102)*('NHẬP ĐƠN'!I$2:I$1000<>"Đã xoá")*('NHẬP ĐƠN'!F$2:F$1000))) | D102: =IF(A102="","",SUMPRODUCT(('NHẬP ĐƠN'!A$2:A$1000=A102)*('NHẬP ĐƠN'!I$2:I$1000<>"Đã xoá")*('NHẬP ĐƠN'!G$2:G$1000)*('NHẬP ĐƠN'!F$2:F$1000))) | E102: =IF(B102>0,D102/B102,"") -> #DIV/0! | F102: =IFERROR(VLOOKUP(A102,'NHẬP ĐƠN'!A:J,10,FALSE),"") | G102: =IF(A102="","",IF(OR(D102>=10000,B102>=5),"⭐ VIP",IF(B102>=3,"💎 Thân thiết","👤 Thường"))) | H102: 507-0053 | I102: 岐阜県 | J102: 多治見市 | K102: 若松町1-18-1 ( MIKA ) | L102: 9030991196
B103: =IF(A103="","",COUNTIFS('NHẬP ĐƠN'!A:A,A103,'NHẬP ĐƠN'!I:I,"<>Đã xoá")) | C103: =IF(A103="","",SUMPRODUCT(('NHẬP ĐƠN'!A$2:A$1000=A103)*('NHẬP ĐƠN'!I$2:I$1000<>"Đã xoá")*('NHẬP ĐƠN'!F$2:F$1000))) | D103: =IF(A103="","",SUMPRODUCT(('NHẬP ĐƠN'!A$2:A$1000=A103)*('NHẬP ĐƠN'!I$2:I$1000<>"Đã xoá")*('NHẬP ĐƠN'!G$2:G$1000)*('NHẬP ĐƠN'!F$2:F$1000))) | E103: =IF(B103>0,D103/B103,"") -> #DIV/0! | F103: =IFERROR(VLOOKUP(A103,'NHẬP ĐƠN'!A:J,10,FALSE),"") | G103: =IF(A103="","",IF(OR(D103>=10000,B103>=5),"⭐ VIP",IF(B103>=3,"💎 Thân thiết","👤 Thường"))) | H103: 098-1703 | I103: 北海道 | J103: 紋別郡雄武町 | K103: 沢木59番地の1 | L103: 9030991196
B104: =IF(A104="","",COUNTIFS('NHẬP ĐƠN'!A:A,A104,'NHẬP ĐƠN'!I:I,"<>Đã xoá")) | C104: =IF(A104="","",SUMPRODUCT(('NHẬP ĐƠN'!A$2:A$1000=A104)*('NHẬP ĐƠN'!I$2:I$1000<>"Đã xoá")*('NHẬP ĐƠN'!F$2:F$1000))) | D104: =IF(A104="","",SUMPRODUCT(('NHẬP ĐƠN'!A$2:A$1000=A104)*('NHẬP ĐƠN'!I$2:I$1000<>"Đã xoá")*('NHẬP ĐƠN'!G$2:G$1000)*('NHẬP ĐƠN'!F$2:F$1000))) | E104: =IF(B104>0,D104/B104,"") -> #DIV/0! | F104: =IFERROR(VLOOKUP(A104,'NHẬP ĐƠN'!A:J,10,FALSE),"") | G104: =IF(A104="","",IF(OR(D104>=10000,B104>=5),"⭐ VIP",IF(B104>=3,"💎 Thân thiết","👤 Thường")))
...

Sheet LỊCH SỬ EMS
A1: Mã EMS | B1: Ngày | C1: Số SKU | D1: Tổng SL | E1: Chi tiết | F1: JSON | G1: Status | H1: Last Check | I1: 17track Raw
A2: EB857015049CN | B2: 46130.528 | C2: 20 | D2: 78 | E2: 9091 S XANH THAN x9, 8558 S TRẮNG x8, M001 39 ĐEN x11, 8558 M XANH NÕN x7, 8558 M HỒNG x5, 8876 S ĐEN x4, 8558 M ĐEN x4, 5709 S XANH NHẠT x4, 5709 M XANH NHẠT x2, 8116 S TRẮNG x4, 8897 M TRẮNG x3, 9091 S TRẮNG x3, 9094 S XANH THAN x2, 8558 S HỒNG x2, 8116 M XANH THAN x2, 8876 M XÁM x1, 8825 S TRẮNG x1, 8116 L XANH THAN x1, 8740 M TRẮNG x4, 8558 M ĐEN x1 | F2: [{"sku":9091,"size":"S","color":"XANH THAN","qty":9},{"sku":8558,"size":"S","color":"TRẮNG","qty":8},{"sku":"M001","size":39,"color":"ĐEN","qty":11},{"sku":8558,"size":"M","color":"XANH NÕN","qty":7},{"sku":8558,"size":"M","color":"HỒNG","qty":5},{"sku":8876,"size":"S","color":"ĐEN","qty":4},{"sku":8558,"size":"M","color":"ĐEN","qty":4},{"sku":5709,"size":"S","color":"XANH NHẠT","qty":4},{"sku":5709,"size":"M","color":"XANH NHẠT","qty":2},{"sku":8116,"size":"S","color":"TRẮNG","qty":4},{"sku":8897,"size":"M","color":"TRẮNG","qty":3},{"sku":9091,"size":"S","color":"TRẮNG","qty":3},{"sku":9094,"size":"S","color":"XANH THAN","qty":2},{"sku":8558,"size":"S","color":"HỒNG","qty":2},{"sku":8116,"size":"M","color":"XANH THAN","qty":2},{"sku":8876,"size":"M","color":"XÁM","qty":1},{"sku":8825,"size":"S","color":"TRẮNG","qty":1},{"sku":8116,"size":"L","color":"XANH THAN","qty":1},{"sku":"8740","size":"M","color":"TRẮNG","qty":4},{"sku":"8558","size":"M","color":"ĐEN","qty":1}] | G2: Về kho | H2: 46130.088 | I2: 配達完了
A3: EB857164343CN | B3: 46132.394 | C3: 15 | D3: 97 | E3: M001 37 ĐEN x15, M006 FZ XÁM x13, M006 FZ ĐEN x15, M006 FZ TRẮNG x11, M006 FZ BE x9, MU01 FZ NÂU NHẠT x5, 8558 M TRẮNG x6, M001 40 ĐEN x4, 8558 M CAM x5, 8558 S ĐEN x4, 8558 S XANH NÕN x3, 8897 S TRẮNG x2, 8558 S CAM x2, 9094 S XÁM x2, M001 36 BE x1 | F3: [{"sku":"M001","size":37,"color":"ĐEN","qty":15},{"sku":"M006","size":"FZ","color":"XÁM","qty":13},{"sku":"M006","size":"FZ","color":"ĐEN","qty":15},{"sku":"M006","size":"FZ","color":"TRẮNG","qty":11},{"sku":"M006","size":"FZ","color":"BE","qty":9},{"sku":"MU01","size":"FZ","color":"NÂU NHẠT","qty":5},{"sku":8558,"size":"M","color":"TRẮNG","qty":6},{"sku":"M001","size":40,"color":"ĐEN","qty":4},{"sku":8558,"size":"M","color":"CAM","qty":5},{"sku":8558,"size":"S","color":"ĐEN","qty":4},{"sku":8558,"size":"S","color":"XANH NÕN","qty":3},{"sku":8897,"size":"S","color":"TRẮNG","qty":2},{"sku":8558,"size":"S","color":"CAM","qty":2},{"sku":9094,"size":"S","color":"XÁM","qty":2},{"sku":"M001","size":"36","color":"BE","qty":1}] | G3: Đã nhập kho
A4: EB857446239CN | B4: 46137.419 | C4: 24 | D4: 33 | E4: M001 38 ĐEN x2, M001 37 ĐEN x4, M001 35 BE x1, 7957 M XÁM x2, 7957 S TRẮNG x2, 7957 M ĐEN x1, 7957 M TRẮNG x1, 7957 S XÁM x1, 7957 S ĐEN x1, M007 FZ NGOCANH x1, M001 36 ĐEN x1, M001 36 BE x1, M001 37 BE x1, M001 38 BE x2, 8876 M ĐEN x2, P651W13129 38 BE x1, PE232WAS632 37 TÍM x1, P661W13310 37 BE x1, P661W13310 37 HỒNG x1, P661W13310 39 HỒNG x1, P661W12375 39 HỒNG x2, P661W12375 38 HỒNG x1, P661W13363 36 NÂU x1, P661W13363 37 NÂU x1 | F4: [{"sku":"M001","size":38,"color":"ĐEN","qty":2},{"sku":"M001","size":37,"color":"ĐEN","qty":4},{"sku":"M001","size":35,"color":"BE","qty":1},{"sku":7957,"size":"M","color":"XÁM","qty":2},{"sku":7957,"size":"S","color":"TRẮNG","qty":2},{"sku":7957,"size":"M","color":"ĐEN","qty":1},{"sku":7957,"size":"M","color":"TRẮNG","qty":1},{"sku":7957,"size":"S","color":"XÁM","qty":1},{"sku":7957,"size":"S","color":"ĐEN","qty":1},{"sku":"M007","size":"FZ","color":"NGOCANH","qty":1},{"sku":"M001","size":"36","color":"ĐEN","qty":1},{"sku":"M001","size":"36","color":"BE","qty":1},{"sku":"M001","size":"37","color":"BE","qty":1},{"sku":"M001","size":"38","color":"BE","qty":2},{"sku":"8876","size":"M","color":"ĐEN","qty":2},{"sku":"P651W13129","size":"38","color":"BE","qty":1},{"sku":"PE232WAS632","size":"37","color":"TÍM","qty":1},{"sku":"P661W13310","size":"37","color":"BE","qty":1},{"sku":"P661W13310","size":"37","color":"HỒNG","qty":1},{"sku":"P661W13310","size":"39","color":"HỒNG","qty":1},{"sku":"P661W12375","size":"39","color":"HỒNG","qty":2},{"sku":"P661W12375","size":"38","color":"HỒNG","qty":1},{"sku":"P661W13363","size":"36","color":"NÂU","qty":1},{"sku":"P661W13363","size":"37","color":"NÂU","qty":1}] | G4: Đã nhập kho
A5: EB857231330CN | B5: 46137.491 | C5: 19 | D5: 51 | E5: M005 38 ĐEN x1, M005 38 NÂU x1, P661W13404 37 NÂU x1, M004 FZ SỌC XANH x2, M004 FZ GẤU HỒNG x1, M004 FZ SỌC HỒNG x2, M004 FZ GẤU XANH x1, 9091 M TRẮNG x2, 9091 L TRẮNG x2, 9091 M XANH THAN x3, 8825 S ĐEN x4, 8876 S TRẮNG x3, TRA1 FZ VÀNG x6, M007 FZ HATHIQUYNH x1, M007 FZ LEYU x1, M001 38 ĐEN x8, M001 35 BE x2, M001 38 BE x3, M001 35 ĐEN x7 | F5: [{"sku":"M005","size":"38","color":"ĐEN","qty":1},{"sku":"M005","size":"38","color":"NÂU","qty":1},{"sku":"P661W13404","size":"37","color":"NÂU","qty":1},{"sku":"M004","size":"FZ","color":"SỌC XANH","qty":2},{"sku":"M004","size":"FZ","color":"GẤU HỒNG","qty":1},{"sku":"M004","size":"FZ","color":"SỌC HỒNG","qty":2},{"sku":"M004","size":"FZ","color":"GẤU XANH","qty":1},{"sku":"9091","size":"M","color":"TRẮNG","qty":2},{"sku":"9091","size":"L","color":"TRẮNG","qty":2},{"sku":"9091","size":"M","color":"XANH THAN","qty":3},{"sku":"8825","size":"S","color":"ĐEN","qty":4},{"sku":"8876","size":"S","color":"TRẮNG","qty":3},{"sku":"TRA1","size":"FZ","color":"VÀNG","qty":6},{"sku":"M007","size":"FZ","color":"HATHIQUYNH","qty":1},{"sku":"M007","size":"FZ","color":"LEYU","qty":1},{"sku":"M001","size":"38","color":"ĐEN","qty":8},{"sku":"M001","size":"35","color":"BE","qty":2},{"sku":"M001","size":"38","color":"BE","qty":3},{"sku":"M001","size":"35","color":"ĐEN","qty":7}] | G5: Đã nhập kho
A6: EB857446344CN | B6: 46137.769 | C6: 24 | D6: 76 | E6: M006 FZ XÁM x8, GIAY1 37 BE x6, M006 FZ TRẮNG x11, 1302 FZ 6 x6, M006 FZ BE x6, 81813 FZ TRẮNG x5, GIAY1 37 ĐEN x4, GIAY1 38 ĐEN x3, 1302 FZ 3 x3, 81813 FZ HỒNG x2, M006 FZ ĐEN x7, 1302 FZ 1 x2, 1302 FZ 9 x2, 81813 FZ ĐEN x1, 81813 FZ XANH NHẠT x1, 81813 FZ VÀNG x1, 1302 FZ 2 x1, 1302 FZ 8 x1, 1302 FZ 5 x1, M007 FZ GIALINH x1, P230MTX362-T800 37 BE x1, P230MTX362-T800 42 ĐEN x1, GIAY2 37 BE x1, GIAY2 39 BE x1 | F6: [{"sku":"M006","size":"FZ","color":"XÁM","qty":8},{"sku":"GIAY1","size":37,"color":"BE","qty":6},{"sku":"M006","size":"FZ","color":"TRẮNG","qty":11},{"sku":1302,"size":"FZ","color":6,"qty":6},{"sku":"M006","size":"FZ","color":"BE","qty":6},{"sku":81813,"size":"FZ","color":"TRẮNG","qty":5},{"sku":"GIAY1","size":37,"color":"ĐEN","qty":4},{"sku":"GIAY1","size":38,"color":"ĐEN","qty":3},{"sku":1302,"size":"FZ","color":3,"qty":3},{"sku":81813,"size":"FZ","color":"HỒNG","qty":2},{"sku":"M006","size":"FZ","color":"ĐEN","qty":7},{"sku":1302,"size":"FZ","color":1,"qty":2},{"sku":1302,"size":"FZ","color":9,"qty":2},{"sku":81813,"size":"FZ","color":"ĐEN","qty":1},{"sku":81813,"size":"FZ","color":"XANH NHẠT","qty":1},{"sku":81813,"size":"FZ","color":"VÀNG","qty":1},{"sku":1302,"size":"FZ","color":2,"qty":1},{"sku":1302,"size":"FZ","color":8,"qty":1},{"sku":1302,"size":"FZ","color":5,"qty":1},{"sku":"M007","size":"FZ","color":"GIALINH","qty":1},{"sku":"P230MTX362-T800","size":"37","color":"BE","qty":1},{"sku":"P230MTX362-T800","size":"42","color":"ĐEN","qty":1},{"sku":"GIAY2","size":"37","color":"BE","qty":1},{"sku":"GIAY2","size":"39","color":"BE","qty":1}] | G6: Đã nhập kho
A7: EB857651181CN | B7: 46140.438 | C7: 27 | D7: 42 | E7: TRA1 FZ VÀNG x4, GIAY1 39 BE x3, GIAY1 36 ĐEN x3, GIAY2 37 BE x3, GIAY1 36 BE x2, 5709 M XANH NHẠT x4, 3225 S BE x2, M007 FZ SOPH TRAN x2, GIAY1 40 ĐEN x1, 3225 L XANH THAN x1, 3225 S XANH THAN x1, GIAY1 39 ĐEN x1, GIAY1 35 ĐEN x1, GIAY2 38 BE x1, GIAY1 40 BE x1, GIAY1 38 BE x1, 3225 M XANH THAN x1, 5709 XL XANH NHẠT x1, M007 FZ THAOVY x1, M007 FZ DUONGNHUMAILINH x1, M007 FZ NGUYENTHAO x1, M007 FZ HANGUYEN x1, M007 FZ PHUONGQUYEN x1, M007 FZ MOONLEE x1, P651W13112C 37 BE x1, P651W13112C 37 XANH NHẠT x1, P651W13112C 39 BE x1 | F7: [{"sku":"TRA1","size":"FZ","color":"VÀNG","qty":4},{"sku":"GIAY1","size":39,"color":"BE","qty":3},{"sku":"GIAY1","size":36,"color":"ĐEN","qty":3},{"sku":"GIAY2","size":37,"color":"BE","qty":3},{"sku":"GIAY1","size":36,"color":"BE","qty":2},{"sku":5709,"size":"M","color":"XANH NHẠT","qty":4},{"sku":3225,"size":"S","color":"BE","qty":2},{"sku":"M007","size":"FZ","color":"SOPH TRAN","qty":2},{"sku":"GIAY1","size":40,"color":"ĐEN","qty":1},{"sku":3225,"size":"L","color":"XANH THAN","qty":1},{"sku":3225,"size":"S","color":"XANH THAN","qty":1},{"sku":"GIAY1","size":39,"color":"ĐEN","qty":1},{"sku":"GIAY1","size":35,"color":"ĐEN","qty":1},{"sku":"GIAY2","size":38,"color":"BE","qty":1},{"sku":"GIAY1","size":40,"color":"BE","qty":1},{"sku":"GIAY1","size":38,"color":"BE","qty":1},{"sku":3225,"size":"M","color":"XANH THAN","qty":1},{"sku":5709,"size":"XL","color":"XANH NHẠT","qty":1},{"sku":"M007","size":"FZ","color":"THAOVY","qty":1},{"sku":"M007","size":"FZ","color":"DUONGNHUMAILINH","qty":1},{"sku":"M007","size":"FZ","color":"NGUYENTHAO","qty":1},{"sku":"M007","size":"FZ","color":"HANGUYEN","qty":1},{"sku":"M007","size":"FZ","color":"PHUONGQUYEN","qty":1},{"sku":"M007","size":"FZ","color":"MOONLEE","qty":1},{"sku":"P651W13112C","size":"37","color":"BE","qty":1},{"sku":"P651W13112C","size":"37","color":"XANH NHẠT","qty":1},{"sku":"P651W13112C","size":"39","color":"BE","qty":1}] | G7: Đã nhập kho
A8: EB857551400CN/EB857551736CN | B8: 46141.467 | C8: 19 | D8: 69 | E8: 6612 FZ 5 x21, 6612 FZ 2 x19, 6612 FZ 9 x3, MU01 FZ NÂU NHẠT x6, MU01 FZ NÂU x3, MU01 FZ BE x2, M001 38 ĐEN x2, MU01 FZ HỒNG x1, M001 40 ĐEN x1, M007 FZ DONGOCUYEN x1, M007 FZ HUONGAKI x1, M007 FZ HALONG x1, M007 FZ THANHTHUY x1, M007 FZ HUYENTRANG x1, M007 FZ HUYNHVY x1, M007 FZ NGUYENTHIHANG x1, M001 37 ĐEN x2, M001 36 ĐEN x1, M001 36 BE x1 | F8: [{"sku":6612,"size":"FZ","color":5,"qty":21},{"sku":6612,"size":"FZ","color":2,"qty":19},{"sku":6612,"size":"FZ","color":9,"qty":3},{"sku":"MU01","size":"FZ","color":"NÂU NHẠT","qty":6},{"sku":"MU01","size":"FZ","color":"NÂU","qty":3},{"sku":"MU01","size":"FZ","color":"BE","qty":2},{"sku":"M001","size":38,"color":"ĐEN","qty":2},{"sku":"MU01","size":"FZ","color":"HỒNG","qty":1},{"sku":"M001","size":40,"color":"ĐEN","qty":1},{"sku":"M007","size":"FZ","color":"DONGOCUYEN","qty":1},{"sku":"M007","size":"FZ","color":"HUONGAKI","qty":1},{"sku":"M007","size":"FZ","color":"HALONG","qty":1},{"sku":"M007","size":"FZ","color":"THANHTHUY","qty":1},{"sku":"M007","size":"FZ","color":"HUYENTRANG","qty":1},{"sku":"M007","size":"FZ","color":"HUYNHVY","qty":1},{"sku":"M007","size":"FZ","color":"NGUYENTHIHANG","qty":1},{"sku":"M001","size":37,"color":"ĐEN","qty":2},{"sku":"M001","size":"36","color":"ĐEN","qty":1},{"sku":"M001","size":"36","color":"BE","qty":1}] | G8: Đã nhập kho
A9: EB858203321CN | B9: 46153.442 | C9: 29 | D9: 95 | E9: M010 FZ TRẮNG x17, 92212 FZ HỒNG x22, BRA1 M BE x1, BRA1 L BE x2, QUAN1 M A x10, TRA1 FZ VÀNG x6, 92212 FZ XÁM x1, BRA1 S BE x1, 8321 FZ XANH THAN x5, BRA1 L ĐEN x1, 8321 FZ NÂU x4, 92212 FZ ĐEN x1, QUAN1 L C x4, QUAN1 M C x3, 8321 FZ NÂU NHẠT x2, 92212 FZ TRẮNG x1, M006 FZ XÁM x1, GIAY1 38 BE x1, GIAY1 37 BE x1, M004 FZ SỌC HỒNG x1, M004 FZ GẤU VÀNG x1, GIAY1 37 ĐEN x1, GIAY2 38 ĐEN x1, QUAN1 XL A x1, QUAN1 XL B x1, BRA3 S BE x1, BRA3 M BE x1, M006 FZ ĐEN x2, M006 FZ TRẮNG x1 | F9: [{"sku":"M010","size":"FZ","color":"TRẮNG","qty":17},{"sku":92212,"size":"FZ","color":"HỒNG","qty":22},{"sku":"BRA1","size":"M","color":"BE","qty":1},{"sku":"BRA1","size":"L","color":"BE","qty":2},{"sku":"QUAN1","size":"M","color":"A","qty":10},{"sku":"TRA1","size":"FZ","color":"VÀNG","qty":6},{"sku":92212,"size":"FZ","color":"XÁM","qty":1},{"sku":"BRA1","size":"S","color":"BE","qty":1},{"sku":8321,"size":"FZ","color":"XANH THAN","qty":5},{"sku":"BRA1","size":"L","color":"ĐEN","qty":1},{"sku":8321,"size":"FZ","color":"NÂU","qty":4},{"sku":92212,"size":"FZ","color":"ĐEN","qty":1},{"sku":"QUAN1","size":"L","color":"C","qty":4},{"sku":"QUAN1","size":"M","color":"C","qty":3},{"sku":8321,"size":"FZ","color":"NÂU NHẠT","qty":2},{"sku":92212,"size":"FZ","color":"TRẮNG","qty":1},{"sku":"M006","size":"FZ","color":"XÁM","qty":1},{"sku":"GIAY1","size":38,"color":"BE","qty":1},{"sku":"GIAY1","size":37,"color":"BE","qty":1},{"sku":"M004","size":"FZ","color":"SỌC HỒNG","qty":1},{"sku":"M004","size":"FZ","color":"GẤU VÀNG","qty":1},{"sku":"GIAY1","size":37,"color":"ĐEN","qty":1},{"sku":"GIAY2","size":38,"color":"ĐEN","qty":1},{"sku":"QUAN1","size":"XL","color":"A","qty":1},{"sku":"QUAN1","size":"XL","color":"B","qty":1},{"sku":"BRA3","size":"S","color":"BE","qty":1},{"sku":"BRA3","size":"M","color":"BE","qty":1},{"sku":"M006","size":"FZ","color":"ĐEN","qty":2},{"sku":"M006","size":"FZ","color":"TRẮNG","qty":1}] | G9: Đã nhập kho
A10: EB858544970CN | B10: 46158.91 | C10: 21 | D10: 82 | E10: M010 FZ TRẮNG x14, 6612 FZ 5 x5, 6612 FZ 2 x6, 6612 FZ 9 x4, TRA1 FZ VÀNG x6, M012 FZ NÂU x8, M012 FZ ĐỎ x8, M012 FZ TÍM x8, 6612 FZ 4 x1, 5709 S XANH NHẠT x5, CK98118 M ĐEN x2, CK98118 S ĐEN x3, 3225 S XANH THAN x3, 6612 FZ 3 x1, M008 L TÍM x1, M008 L VÀNG x1, M008 M HỒNG x1, M008 L XÁM x1, 3225 M XANH THAN x2, CK98118 XL x1, M007 FZ LINHEM x1 | F10: [{"sku":"M010","size":"FZ","color":"TRẮNG","qty":14},{"sku":6612,"size":"FZ","color":5,"qty":5},{"sku":6612,"size":"FZ","color":2,"qty":6},{"sku":6612,"size":"FZ","color":9,"qty":4},{"sku":"TRA1","size":"FZ","color":"VÀNG","qty":6},{"sku":"M012","size":"FZ","color":"NÂU","qty":8},{"sku":"M012","size":"FZ","color":"ĐỎ","qty":8},{"sku":"M012","size":"FZ","color":"TÍM","qty":8},{"sku":6612,"size":"FZ","color":4,"qty":1},{"sku":5709,"size":"S","color":"XANH NHẠT","qty":5},{"sku":"CK98118","size":"M","color":"ĐEN","qty":2},{"sku":"CK98118","size":"S","color":"ĐEN","qty":3},{"sku":3225,"size":"S","color":"XANH THAN","qty":3},{"sku":6612,"size":"FZ","color":3,"qty":1},{"sku":"M008","size":"L","color":"TÍM","qty":1},{"sku":"M008","size":"L","color":"VÀNG","qty":1},{"sku":"M008","size":"M","color":"HỒNG","qty":1},{"sku":"M008","size":"L","color":"XÁM","qty":1},{"sku":3225,"size":"M","color":"XANH THAN","qty":2},{"sku":"CK98118","size":"XL","color":"","qty":1},{"sku":"M007","size":"FZ","color":"LINHEM","qty":1}] | G10: Đã nhập kho
A11: EB858203105CN | B11: 46158.917 | C11: 27 | D11: 149 | E11: BRA1 M BE x20, QUAN1 L B x13, QUAN1 L A x11, QUAN1 M B x8, BRA2 M BE x11, BRA1 L BE x11, 92212 FZ HỒNG x7, BRA2 L BE x8, 92212 FZ XÁM x6, BRA2 M TRẮNG x6, BRA1 M ĐEN x5, BRA1 L TRẮNG x5, BRA1 S BE x5, M014 FZ TÍM x5, BRA1 L ĐEN x4, BRA1 S TRẮNG x3, BRA2 L TRẮNG x3, BRA2 XL BE x2, 92212 FZ ĐEN x3, BRA1 M TRẮNG x2, BRA1 XL BE x2, BRA2 L ĐEN x2, BRA2 M ĐEN x2, BRA1 M HỒNG x1, BRA2 S TRẮNG x1, 92212 FZ TRẮNG x1, MU01 FZ BE x2 | F11: [{"sku":"BRA1","size":"M","color":"BE","qty":20},{"sku":"QUAN1","size":"L","color":"B","qty":13},{"sku":"QUAN1","size":"L","color":"A","qty":11},{"sku":"QUAN1","size":"M","color":"B","qty":8},{"sku":"BRA2","size":"M","color":"BE","qty":11},{"sku":"BRA1","size":"L","color":"BE","qty":11},{"sku":92212,"size":"FZ","color":"HỒNG","qty":7},{"sku":"BRA2","size":"L","color":"BE","qty":8},{"sku":92212,"size":"FZ","color":"XÁM","qty":6},{"sku":"BRA2","size":"M","color":"TRẮNG","qty":6},{"sku":"BRA1","size":"M","color":"ĐEN","qty":5},{"sku":"BRA1","size":"L","color":"TRẮNG","qty":5},{"sku":"BRA1","size":"S","color":"BE","qty":5},{"sku":"M014","size":"FZ","color":"TÍM","qty":5},{"sku":"BRA1","size":"L","color":"ĐEN","qty":4},{"sku":"BRA1","size":"S","color":"TRẮNG","qty":3},{"sku":"BRA2","size":"L","color":"TRẮNG","qty":3},{"sku":"BRA2","size":"XL","color":"BE","qty":2},{"sku":92212,"size":"FZ","color":"ĐEN","qty":3},{"sku":"BRA1","size":"M","color":"TRẮNG","qty":2},{"sku":"BRA1","size":"XL","color":"BE","qty":2},{"sku":"BRA2","size":"L","color":"ĐEN","qty":2},{"sku":"BRA2","size":"M","color":"ĐEN","qty":2},{"sku":"BRA1","size":"M","color":"HỒNG","qty":1},{"sku":"BRA2","size":"S","color":"TRẮNG","qty":1},{"sku":92212,"size":"FZ","color":"TRẮNG","qty":1},{"sku":"MU01","size":"FZ","color":"BE","qty":2}] | G11: Đã nhập kho
A12: EB858864333CN | B12: 46163.466 | C12: 31 | D12: 24538 | E12: 8610 M TRẮNG x1, 9031 M TRẮNG x6, 8888 S TRẮNG x1, 9083 S XANH NHẠT x1, 9031 S TRẮNG x4, 8558 M ĐEN x2, 8558 M TRẮNG x2, 9500 L XANH NHẠT x2, 9500 M XANH NHẠT x2, 8770 FZ XANH x1, 8558 S HỒNG x1, 8770 FZ XANH THAN x1, 8770 FZ TRẮNG x2, 9091 L XANH THAN x1, 8888 M TRẮNG x1, CK98118 L ĐEN x1, 9500 S XANH NHẠT x1, M007 FZ TRANG x1, CK98118 S ĐEN x1, CK98118 XL ĐEN x1, M007 37.5 Onitsuka x1, M007 37 Onitsuka x1, M007 39 Onitsuka x1, P661W13310 36 BE x7000, P661W13310 37 BE x7000, P230MTX362 36 NÂU x2900, P230MTX362 38 BE x2900, M005 39 NÂU x2350, M005 36 NÂU x2350, 8876 S ĐEN x1, 8558 M HỒNG x1 | F12: [{"sku":8610,"size":"M","color":"TRẮNG","qty":1},{"sku":9031,"size":"M","color":"TRẮNG","qty":6},{"sku":8888,"size":"S","color":"TRẮNG","qty":1},{"sku":9083,"size":"S","color":"XANH NHẠT","qty":1},{"sku":9031,"size":"S","color":"TRẮNG","qty":4},{"sku":8558,"size":"M","color":"ĐEN","qty":2},{"sku":8558,"size":"M","color":"TRẮNG","qty":2},{"sku":9500,"size":"L","color":"XANH NHẠT","qty":2},{"sku":9500,"size":"M","color":"XANH NHẠT","qty":2},{"sku":8770,"size":"FZ","color":"XANH","qty":1},{"sku":8558,"size":"S","color":"HỒNG","qty":1},{"sku":8770,"size":"FZ","color":"XANH THAN","qty":1},{"sku":8770,"size":"FZ","color":"TRẮNG","qty":2},{"sku":9091,"size":"L","color":"XANH THAN","qty":1},{"sku":8888,"size":"M","color":"TRẮNG","qty":1},{"sku":"CK98118","size":"L","color":"ĐEN","qty":1},{"sku":9500,"size":"S","color":"XANH NHẠT","qty":1},{"sku":"M007","size":"FZ","color":"TRANG","qty":1},{"sku":"CK98118","size":"S","color":"ĐEN","qty":1},{"sku":"CK98118","size":"XL","color":"ĐEN","qty":1},{"sku":"M007","size":"37.5","color":"Onitsuka","qty":1},{"sku":"M007","size":"37","color":"Onitsuka","qty":1},{"sku":"M007","size":"39","color":"Onitsuka","qty":1},{"sku":"P661W13310","size":"36","color":"BE","qty":7000},{"sku":"P661W13310","size":"37","color":"BE","qty":7000},{"sku":"P230MTX362","size":"36","color":"NÂU","qty":2900},{"sku":"P230MTX362","size":"38","color":"BE","qty":2900},{"sku":"M005","size":"39","color":"NÂU","qty":2350},{"sku":"M005","size":"36","color":"NÂU","qty":2350},{"sku":"8876","size":"S","color":"ĐEN","qty":1},{"sku":"8558","size":"M","color":"HỒNG","qty":1}] | G12: Đã nhập kho
A13: EB858864347CN | B13: 46163.517 | C13: 22 | D13: 91 | E13: M012 FZ VÀNG x24, M018 FZ BE x20, M012 FZ XANH NHẠT x10, 8319 S XANH THAN x7, 8610 M TRẮNG x6, 9083 S XANH NHẠT x4, 9277 FZ TRẮNG x4, M011 FZ NEW MOTION x2, 9277 FZ ĐEN x1, 9369 L XANH THAN x1, 9369 M XANH THAN x1, DEP1 35 TRẮNG x1, DEP1 37 ĐEN x1, DEP1 37 TRẮNG x1, DEP1 35 ĐEN x1, DEP1 36 TRẮNG x1, DEP1 36 XÁM x1, M007 FZ TRANGTHIEU x1, M007 FZ Lam Lam x1, 7249 M XANH NHẠT x1, 9094 S XANH THAN x1, 9094 S XÁM x1 | F13: [{"sku":"M012","size":"FZ","color":"VÀNG","qty":24},{"sku":"M018","size":"FZ","color":"BE","qty":20},{"sku":"M012","size":"FZ","color":"XANH NHẠT","qty":10},{"sku":8319,"size":"S","color":"XANH THAN","qty":7},{"sku":8610,"size":"M","color":"TRẮNG","qty":6},{"sku":9083,"size":"S","color":"XANH NHẠT","qty":4},{"sku":9277,"size":"FZ","color":"TRẮNG","qty":4},{"sku":"M011","size":"FZ","color":"NEW MOTION","qty":2},{"sku":9277,"size":"FZ","color":"ĐEN","qty":1},{"sku":9369,"size":"L","color":"XANH THAN","qty":1},{"sku":9369,"size":"M","color":"XANH THAN","qty":1},{"sku":"DEP1","size":35,"color":"TRẮNG","qty":1},{"sku":"DEP1","size":37,"color":"ĐEN","qty":1},{"sku":"DEP1","size":37,"color":"TRẮNG","qty":1},{"sku":"DEP1","size":35,"color":"ĐEN","qty":1},{"sku":"DEP1","size":36,"color":"TRẮNG","qty":1},{"sku":"DEP1","size":36,"color":"XÁM","qty":1},{"sku":"M007","size":"FZ","color":"TRANGTHIEU","qty":1},{"sku":"M007","size":"FZ","color":"Lam Lam","qty":1},{"sku":"7249","size":"M","color":"XANH NHẠT","qty":1},{"sku":"9094","size":"S","color":"XANH THAN","qty":1},{"sku":"9094","size":"S","color":"XÁM","qty":1}] | G13: Đã nhập kho
A14: EB858937438CN | B14: 46166.425 | C14: 43 | D14: 90 | E14: QUAN1 M A x5, QUAN1 M B x4, M015 M BE x5, M015 M XANH LÁ x5, M015 S BE x5, QUAN1 L A x3, M016 M ĐEN x4, M010 FZ TRẮNG x4, QUAN1 L B x2, M015 S XÁM x3, M015 M HỒNG x3, M015 M ĐEN x3, M016 L ĐEN x3, M016 L XANH THAN x3, QUAN1 XL C x1, P651W13112C 37 BE x2, QUAN1 M C x2, QUAN1 L C x2, M016 M XANH THAN x2, M017 L 1 x2, M017 L 3 x2, M007 FZ LiLy x1, M016 XL ĐEN x2, M016 XL TRẮNG x2, M016 M XÁM x2, P661W12375 35 HỒNG x1, P651W13112C 39 BE x1, M017 L 6 x1, M017 2XL 3 x1, M017 2XL 2 x1, M017 L 4 x1, M007 M NHUNG KULS x1, GIAY1 37 BE x1, M007 FZ BichChung x1, GIAY1 35 BE x1, P661W12375 38 BE x1, PX241WAS932 38 BE x1, P651W13112C 37 HỒNG x1, P651W13112C 36 BE x1, M001 38 ĐEN x1, M001 36 ĐEN x1, M001 38 BE x1, M001 37 ĐEN x1 | F14: [{"sku":"QUAN1","size":"M","color":"A","qty":5},{"sku":"QUAN1","size":"M","color":"B","qty":4},{"sku":"M015","size":"M","color":"BE","qty":5},{"sku":"M015","size":"M","color":"XANH LÁ","qty":5},{"sku":"M015","size":"S","color":"BE","qty":5},{"sku":"QUAN1","size":"L","color":"A","qty":3},{"sku":"M016","size":"M","color":"ĐEN","qty":4},{"sku":"M010","size":"FZ","color":"TRẮNG","qty":4},{"sku":"QUAN1","size":"L","color":"B","qty":2},{"sku":"M015","size":"S","color":"XÁM","qty":3},{"sku":"M015","size":"M","color":"HỒNG","qty":3},{"sku":"M015","size":"M","color":"ĐEN","qty":3},{"sku":"M016","size":"L","color":"ĐEN","qty":3},{"sku":"M016","size":"L","color":"XANH THAN","qty":3},{"sku":"QUAN1","size":"XL","color":"C","qty":1},{"sku":"P651W13112C","size":37,"color":"BE","qty":2},{"sku":"QUAN1","size":"M","color":"C","qty":2},{"sku":"QUAN1","size":"L","color":"C","qty":2},{"sku":"M016","size":"M","color":"XANH THAN","qty":2},{"sku":"M017","size":"L","color":1,"qty":2},{"sku":"M017","size":"L","color":3,"qty":2},{"sku":"M007","size":"FZ","color":"LiLy","qty":1},{"sku":"M016","size":"XL","color":"ĐEN","qty":2},{"sku":"M016","size":"XL","color":"TRẮNG","qty":2},{"sku":"M016","size":"M","color":"XÁM","qty":2},{"sku":"P661W12375","size":35,"color":"HỒNG","qty":1},{"sku":" P651W13112C","size":39,"color":"BE","qty":1},{"sku":"M017","size":"L","color":6,"qty":1},{"sku":"M017","size":"2XL","color":3,"qty":1},{"sku":"M017","size":"2XL","color":2,"qty":1},{"sku":"M017","size":"L","color":4,"qty":1},{"sku":"M007","size":"M","color":"NHUNG KULS","qty":1},{"sku":"GIAY1","size":37,"color":"BE","qty":1},{"sku":"M007","size":"FZ","color":"BichChung","qty":1},{"sku":"GIAY1","size":35,"color":"BE","qty":1},{"sku":"P661W12375","size":38,"color":"BE","qty":1},{"sku":"PX241WAS932","size":38,"color":"BE","qty":1},{"sku":"P651W13112C","size":37,"color":"HỒNG","qty":1},{"sku":"P651W13112C","size":36,"color":"BE","qty":1},{"sku":"M001","size":"38","color":"ĐEN","qty":1},{"sku":"M001","size":"36","color":"ĐEN","qty":1},{"sku":"M001","size":"38","color":"BE","qty":1},{"sku":"M001","size":"37","color":"ĐEN","qty":1}] | G14: Đã nhập kho
... A19: EB859664846CN | B19: 46184.419 | C19: 16 | D19: 29 | E19: M020 FZ XANH LÁ x14, M007 FZ LAMLAM x1, M007 FZ BUILUONG x1, M007 FZ PHAMLE x1, P661W13310 37 BE x1, P661W13310 38 BE x1, P661W13310 39 BE x1, P651W13112C 40 BE x1, P651W13112C 35 BE x1, P651W13112C 38 BE x1, P651W13112C 36 BE x1, P654W14261 37 NÂU x1, P651W13112C 39 BE x1, P651W13112C 37 XANH LÁ x1, P230MTX362-T800 39 NÂU x1, PX241WAS932 37 BE x1 | F19: [{"sku":"M020","size":"FZ","color":"XANH LÁ","qty":14},{"sku":"M007","size":"FZ","color":"LAMLAM","qty":1},{"sku":"M007","size":"FZ","color":"BUILUONG","qty":1},{"sku":"M007","size":"FZ","color":"PHAMLE","qty":1},{"sku":"P661W13310","size":37,"color":"BE","qty":1},{"sku":"P661W13310","size":38,"color":"BE","qty":1},{"sku":"P661W13310","size":39,"color":"BE","qty":1},{"sku":"P651W13112C","size":40,"color":"BE","qty":1},{"sku":"P651W13112C","size":35,"color":"BE","qty":1},{"sku":"P651W13112C","size":38,"color":"BE","qty":1},{"sku":"P651W13112C","size":36,"color":"BE","qty":1},{"sku":"P654W14261","size":37,"color":"NÂU","qty":1},{"sku":"P651W13112C","size":39,"color":"BE","qty":1},{"sku":"P651W13112C","size":37,"color":"XANH LÁ","qty":1},{"sku":"P230MTX362-T800","size":39,"color":"NÂU","qty":1},{"sku":"PX241WAS932","size":37,"color":"BE","qty":1}] | G19: Đã nhập kho

Sheet số lượng cần đặt
A1: =IFERROR(__xludf.DUMMYFUNCTION("QUERY({ARRAYFORMULA(TO_TEXT('NHẬP ĐƠN'!C2:C1580)),'NHẬP ĐƠN'!D2:D1580,'NHẬP ĐƠN'!E2:E1580,'NHẬP ĐƠN'!F2:F1580},""SELECT Col1,Col2,Col3,SUM(Col4) WHERE Col1<>'' GROUP BY Col1,Col2,Col3 LABEL SUM(Col4) 'Tổng số lượng cần đặt'"",0)"),"") | B1: =IFERROR(__xludf.DUMMYFUNCTION("""COMPUTED_VALUE"""),"") | C1: =IFERROR(__xludf.DUMMYFUNCTION("""COMPUTED_VALUE"""),"") | D1: =IFERROR(__xludf.DUMMYFUNCTION("""COMPUTED_VALUE"""),"Tổng số lượng cần đặt") -> Tổng số lượng cần đặt | G1: Đã Đặt | H1: Chưa đặt
A2: =IFERROR(__xludf.DUMMYFUNCTION("""COMPUTED_VALUE""")," P651W13112C") -> P651W13112C | B2: =IFERROR(__xludf.DUMMYFUNCTION("""COMPUTED_VALUE"""),"39") -> 39 | C2: =IFERROR(__xludf.DUMMYFUNCTION("""COMPUTED_VALUE"""),"BE") -> BE | D2: =IFERROR(__xludf.DUMMYFUNCTION("""COMPUTED_VALUE"""),1.0) -> 1 | G2: {=MAP(A2:A1580,B2:B1580,C2:C1580,LAMBDA(m,s,c,IF(m="","",IFERROR(SUMIFS('DATA_ĐÃ_ĐẶT'!D:D,'DATA_ĐÃ_ĐẶT'!A:A,m,'DATA_ĐÃ_ĐẶT'!B:B,s,'DATA_ĐÃ_ĐẶT'!C:C,c),0))))} -> 0 | H2: =(D2-G2) -> 1
A3: =IFERROR(__xludf.DUMMYFUNCTION("""COMPUTED_VALUE"""),"1302") -> 1302 | B3: =IFERROR(__xludf.DUMMYFUNCTION("""COMPUTED_VALUE"""),"FZ") -> FZ | C3: =IFERROR(__xludf.DUMMYFUNCTION("""COMPUTED_VALUE"""),"1") -> 1 | D3: =IFERROR(__xludf.DUMMYFUNCTION("""COMPUTED_VALUE"""),2.0) -> 2 | G3: 0 | H3: =(D3-G3) -> 2
A4: =IFERROR(__xludf.DUMMYFUNCTION("""COMPUTED_VALUE"""),"1302") -> 1302 | B4: =IFERROR(__xludf.DUMMYFUNCTION("""COMPUTED_VALUE"""),"FZ") -> FZ | C4: =IFERROR(__xludf.DUMMYFUNCTION("""COMPUTED_VALUE"""),"2") -> 2 | D4: =IFERROR(__xludf.DUMMYFUNCTION("""COMPUTED_VALUE"""),1.0) -> 1 | G4: 0 | H4: =(D4-G4) -> 1
A5: =IFERROR(__xludf.DUMMYFUNCTION("""COMPUTED_VALUE"""),"1302") -> 1302 | B5: =IFERROR(__xludf.DUMMYFUNCTION("""COMPUTED_VALUE"""),"FZ") -> FZ | C5: =IFERROR(__xludf.DUMMYFUNCTION("""COMPUTED_VALUE"""),"3") -> 3 | D5: =IFERROR(__xludf.DUMMYFUNCTION("""COMPUTED_VALUE"""),3.0) -> 3 | G5: 0 | H5: =(D5-G5) -> 3
A6: =IFERROR(__xludf.DUMMYFUNCTION("""COMPUTED_VALUE"""),"1302") -> 1302 | B6: =IFERROR(__xludf.DUMMYFUNCTION("""COMPUTED_VALUE"""),"FZ") -> FZ | C6: =IFERROR(__xludf.DUMMYFUNCTION("""COMPUTED_VALUE"""),"5") -> 5 | D6: =IFERROR(__xludf.DUMMYFUNCTION("""COMPUTED_VALUE"""),1.0) -> 1 | G6: 0 | H6: =(D6-G6) -> 1
A7: =IFERROR(__xludf.DUMMYFUNCTION("""COMPUTED_VALUE"""),"1302") -> 1302 | B7: =IFERROR(__xludf.DUMMYFUNCTION("""COMPUTED_VALUE"""),"FZ") -> FZ | C7: =IFERROR(__xludf.DUMMYFUNCTION("""COMPUTED_VALUE"""),"6") -> 6 | D7: =IFERROR(__xludf.DUMMYFUNCTION("""COMPUTED_VALUE"""),6.0) -> 6 | G7: 0 | H7: =(D7-G7) -> 6
A8: =IFERROR(__xludf.DUMMYFUNCTION("""COMPUTED_VALUE"""),"1302") -> 1302 | B8: =IFERROR(__xludf.DUMMYFUNCTION("""COMPUTED_VALUE"""),"FZ") -> FZ | C8: =IFERROR(__xludf.DUMMYFUNCTION("""COMPUTED_VALUE"""),"8") -> 8 | D8: =IFERROR(__xludf.DUMMYFUNCTION("""COMPUTED_VALUE"""),1.0) -> 1 | G8: 0 | H8: =(D8-G8) -> 1
A9: =IFERROR(__xludf.DUMMYFUNCTION("""COMPUTED_VALUE"""),"1302") -> 1302 | B9: =IFERROR(__xludf.DUMMYFUNCTION("""COMPUTED_VALUE"""),"FZ") -> FZ | C9: =IFERROR(__xludf.DUMMYFUNCTION("""COMPUTED_VALUE"""),"9") -> 9 | D9: =IFERROR(__xludf.DUMMYFUNCTION("""COMPUTED_VALUE"""),2.0) -> 2 | G9: 0 | H9: =(D9-G9) -> 2
A10: =IFERROR(__xludf.DUMMYFUNCTION("""COMPUTED_VALUE"""),"1302") -> 1302 | B10: =IFERROR(__xludf.DUMMYFUNCTION("""COMPUTED_VALUE"""),"FZ") -> FZ | C10: =IFERROR(__xludf.DUMMYFUNCTION("""COMPUTED_VALUE"""),"SỌC XANH") -> SỌC XANH | D10: =IFERROR(__xludf.DUMMYFUNCTION("""COMPUTED_VALUE"""),1.0) -> 1 | G10: 0 | H10: =(D10-G10) -> 1
A11: =IFERROR(__xludf.DUMMYFUNCTION("""COMPUTED_VALUE"""),"1639") -> 1639 | B11: =IFERROR(__xludf.DUMMYFUNCTION("""COMPUTED_VALUE"""),"M") -> M | C11: =IFERROR(__xludf.DUMMYFUNCTION("""COMPUTED_VALUE"""),"CAM") -> CAM | D11: =IFERROR(__xludf.DUMMYFUNCTION("""COMPUTED_VALUE"""),1.0) -> 1 | G11: 0 | H11: =(D11-G11) -> 1
A12: =IFERROR(__xludf.DUMMYFUNCTION("""COMPUTED_VALUE"""),"1639") -> 1639 | B12: =IFERROR(__xludf.DUMMYFUNCTION("""COMPUTED_VALUE"""),"S") -> S | C12: =IFERROR(__xludf.DUMMYFUNCTION("""COMPUTED_VALUE"""),"CAM") -> CAM | D12: =IFERROR(__xludf.DUMMYFUNCTION("""COMPUTED_VALUE"""),2.0) -> 2 | G12: 0 | H12: =(D12-G12) -> 2
A13: =IFERROR(__xludf.DUMMYFUNCTION("""COMPUTED_VALUE"""),"1653") -> 1653 | B13: =IFERROR(__xludf.DUMMYFUNCTION("""COMPUTED_VALUE"""),"M") -> M | C13: =IFERROR(__xludf.DUMMYFUNCTION("""COMPUTED_VALUE"""),"TRẮNG") -> TRẮNG | D13: =IFERROR(__xludf.DUMMYFUNCTION("""COMPUTED_VALUE"""),10.0) -> 10 | G13: 0 | H13: =(D13-G13) -> 10
A14: =IFERROR(__xludf.DUMMYFUNCTION("""COMPUTED_VALUE"""),"1653") -> 1653 | B14: =IFERROR(__xludf.DUMMYFUNCTION("""COMPUTED_VALUE"""),"S") -> S | C14: =IFERROR(__xludf.DUMMYFUNCTION("""COMPUTED_VALUE"""),"TRẮNG") -> TRẮNG | D14: =IFERROR(__xludf.DUMMYFUNCTION("""COMPUTED_VALUE"""),10.0) -> 10 | G14: 0 | H14: =(D14-G14) -> 10
A15: =IFERROR(__xludf.DUMMYFUNCTION("""COMPUTED_VALUE"""),"3225") -> 3225 | B15: =IFERROR(__xludf.DUMMYFUNCTION("""COMPUTED_VALUE"""),"L") -> L | C15: =IFERROR(__xludf.DUMMYFUNCTION("""COMPUTED_VALUE"""),"XANH THAN") -> XANH THAN | D15: =IFERROR(__xludf.DUMMYFUNCTION("""COMPUTED_VALUE"""),2.0) -> 2 | G15: 0 | H15: =(D15-G15) -> 2
A16: =IFERROR(__xludf.DUMMYFUNCTION("""COMPUTED_VALUE"""),"3225") -> 3225 | B16: =IFERROR(__xludf.DUMMYFUNCTION("""COMPUTED_VALUE"""),"M") -> M | C16: =IFERROR(__xludf.DUMMYFUNCTION("""COMPUTED_VALUE"""),"XANH THAN") -> XANH THAN | D16: =IFERROR(__xludf.DUMMYFUNCTION("""COMPUTED_VALUE"""),2.0) -> 2 | G16: 0 | H16: =(D16-G16) -> 2
A17: =IFERROR(__xludf.DUMMYFUNCTION("""COMPUTED_VALUE"""),"3225") -> 3225 | B17: =IFERROR(__xludf.DUMMYFUNCTION("""COMPUTED_VALUE"""),"S") -> S | C17: =IFERROR(__xludf.DUMMYFUNCTION("""COMPUTED_VALUE"""),"BE") -> BE | D17: =IFERROR(__xludf.DUMMYFUNCTION("""COMPUTED_VALUE"""),2.0) -> 2 | G17: 0 | H17: =(D17-G17) -> 2
A18: =IFERROR(__xludf.DUMMYFUNCTION("""COMPUTED_VALUE"""),"3225") -> 3225 | B18: =IFERROR(__xludf.DUMMYFUNCTION("""COMPUTED_VALUE"""),"S") -> S | C18: =IFERROR(__xludf.DUMMYFUNCTION("""COMPUTED_VALUE"""),"XANH THAN") -> XANH THAN | D18: =IFERROR(__xludf.DUMMYFUNCTION("""COMPUTED_VALUE"""),4.0) -> 4 | G18: 0 | H18: =(D18-G18) -> 4
A19: =IFERROR(__xludf.DUMMYFUNCTION("""COMPUTED_VALUE"""),"5007") -> 5007 | B19: =IFERROR(__xludf.DUMMYFUNCTION("""COMPUTED_VALUE"""),"M") -> M | C19: =IFERROR(__xludf.DUMMYFUNCTION("""COMPUTED_VALUE"""),"TRẮNG") -> TRẮNG | D19: =IFERROR(__xludf.DUMMYFUNCTION("""COMPUTED_VALUE"""),3.0) -> 3 | G19: 0 | H19: =(D19-G19) -> 3
A20: =IFERROR(__xludf.DUMMYFUNCTION("""COMPUTED_VALUE"""),"5007") -> 5007 | B20: =IFERROR(__xludf.DUMMYFUNCTION("""COMPUTED_VALUE"""),"M") -> M | C20: =IFERROR(__xludf.DUMMYFUNCTION("""COMPUTED_VALUE"""),"ĐEN") -> ĐEN | D20: =IFERROR(__xludf.DUMMYFUNCTION("""COMPUTED_VALUE"""),3.0) -> 3 | G20: 0 | H20: =(D20-G20) -> 3
A21: =IFERROR(__xludf.DUMMYFUNCTION("""COMPUTED_VALUE"""),"5007") -> 5007 | B21: =IFERROR(__xludf.DUMMYFUNCTION("""COMPUTED_VALUE"""),"S") -> S | C21: =IFERROR(__xludf.DUMMYFUNCTION("""COMPUTED_VALUE"""),"TRẮNG") -> TRẮNG | D21: =IFERROR(__xludf.DUMMYFUNCTION("""COMPUTED_VALUE"""),1.0) -> 1 | G21: 0 | H21: =(D21-G21) -> 1
A22: =IFERROR(__xludf.DUMMYFUNCTION("""COMPUTED_VALUE"""),"5344") -> 5344 | B22: =IFERROR(__xludf.DUMMYFUNCTION("""COMPUTED_VALUE"""),"L") -> L | C22: =IFERROR(__xludf.DUMMYFUNCTION("""COMPUTED_VALUE"""),"XANH THAN") -> XANH THAN | D22: =IFERROR(__xludf.DUMMYFUNCTION("""COMPUTED_VALUE"""),1.0) -> 1 | G22: 1 | H22: =(D22-G22) -> 0
A23: =IFERROR(__xludf.DUMMYFUNCTION("""COMPUTED_VALUE"""),"5344") -> 5344 | B23: =IFERROR(__xludf.DUMMYFUNCTION("""COMPUTED_VALUE"""),"M") -> M | C23: =IFERROR(__xludf.DUMMYFUNCTION("""COMPUTED_VALUE"""),"XANH THAN") -> XANH THAN | D23: =IFERROR(__xludf.DUMMYFUNCTION("""COMPUTED_VALUE"""),2.0) -> 2 | G23: 2 | H23: =(D23-G23) -> 0
A24: =IFERROR(__xludf.DUMMYFUNCTION("""COMPUTED_VALUE"""),"5344") -> 5344 | B24: =IFERROR(__xludf.DUMMYFUNCTION("""COMPUTED_VALUE"""),"S") -> S | C24: =IFERROR(__xludf.DUMMYFUNCTION("""COMPUTED_VALUE"""),"XANH THAN") -> XANH THAN | D24: =IFERROR(__xludf.DUMMYFUNCTION("""COMPUTED_VALUE"""),6.0) -> 6 | G24: 6 | H24: =(D24-G24) -> 0
A25: =IFERROR(__xludf.DUMMYFUNCTION("""COMPUTED_VALUE"""),"5670") -> 5670 | B25: =IFERROR(__xludf.DUMMYFUNCTION("""COMPUTED_VALUE"""),"M") -> M | C25: =IFERROR(__xludf.DUMMYFUNCTION("""COMPUTED_VALUE"""),"TRẮNG") -> TRẮNG | D25: =IFERROR(__xludf.DUMMYFUNCTION("""COMPUTED_VALUE"""),7.0) -> 7 | G25: 0 | H25: =(D25-G25) -> 7
A26: =IFERROR(__xludf.DUMMYFUNCTION("""COMPUTED_VALUE"""),"5670") -> 5670 | B26: =IFERROR(__xludf.DUMMYFUNCTION("""COMPUTED_VALUE"""),"S") -> S | C26: =IFERROR(__xludf.DUMMYFUNCTION("""COMPUTED_VALUE"""),"TRẮNG") -> TRẮNG | D26: =IFERROR(__xludf.DUMMYFUNCTION("""COMPUTED_VALUE"""),7.0) -> 7 | G26: 0 | H26: =(D26-G26) -> 7
A27: =IFERROR(__xludf.DUMMYFUNCTION("""COMPUTED_VALUE"""),"5709") -> 5709 | B27: =IFERROR(__xludf.DUMMYFUNCTION("""COMPUTED_VALUE"""),"L") -> L | C27: =IFERROR(__xludf.DUMMYFUNCTION("""COMPUTED_VALUE"""),"XANH NHẠT") -> XANH NHẠT | D27: =IFERROR(__xludf.DUMMYFUNCTION("""COMPUTED_VALUE"""),2.0) -> 2 | G27: 2 | H27: =(D27-G27) -> 0
A28: =IFERROR(__xludf.DUMMYFUNCTION("""COMPUTED_VALUE"""),"5709") -> 5709 | B28: =IFERROR(__xludf.DUMMYFUNCTION("""COMPUTED_VALUE"""),"M") -> M | C28: =IFERROR(__xludf.DUMMYFUNCTION("""COMPUTED_VALUE"""),"XANH NHẠT") -> XANH NHẠT | D28: =IFERROR(__xludf.DUMMYFUNCTION("""COMPUTED_VALUE"""),11.0) -> 11 | G28: 5 | H28: =(D28-G28) -> 6
A29: =IFERROR(__xludf.DUMMYFUNCTION("""COMPUTED_VALUE"""),"5709") -> 5709 | B29: =IFERROR(__xludf.DUMMYFUNCTION("""COMPUTED_VALUE"""),"S") -> S | C29: =IFERROR(__xludf.DUMMYFUNCTION("""COMPUTED_VALUE"""),"XANH NHẠT") -> XANH NHẠT | D29: =IFERROR(__xludf.DUMMYFUNCTION("""COMPUTED_VALUE"""),13.0) -> 13 | G29: 5 | H29: =(D29-G29) -> 8
A30: =IFERROR(__xludf.DUMMYFUNCTION("""COMPUTED_VALUE"""),"5709") -> 5709 | B30: =IFERROR(__xludf.DUMMYFUNCTION("""COMPUTED_VALUE"""),"XL") -> XL | C30: =IFERROR(__xludf.DUMMYFUNCTION("""COMPUTED_VALUE"""),"XANH NHẠT") -> XANH NHẠT | D30: =IFERROR(__xludf.DUMMYFUNCTION("""COMPUTED_VALUE"""),1.0) -> 1 | G30: 0 | H30: =(D30-G30) -> 1
A31: =IFERROR(__xludf.DUMMYFUNCTION("""COMPUTED_VALUE"""),"627") -> 627 | B31: =IFERROR(__xludf.DUMMYFUNCTION("""COMPUTED_VALUE"""),"FZ") -> FZ | C31: =IFERROR(__xludf.DUMMYFUNCTION("""COMPUTED_VALUE"""),"BE") -> BE | D31: =IFERROR(__xludf.DUMMYFUNCTION("""COMPUTED_VALUE"""),2.0) -> 2 | G31: 0 | H31: =(D31-G31) -> 2
A32: =IFERROR(__xludf.DUMMYFUNCTION("""COMPUTED_VALUE"""),"627") -> 627 | B32: =IFERROR(__xludf.DUMMYFUNCTION("""COMPUTED_VALUE"""),"FZ") -> FZ | C32: =IFERROR(__xludf.DUMMYFUNCTION("""COMPUTED_VALUE"""),"NÂU") -> NÂU | D32: =IFERROR(__xludf.DUMMYFUNCTION("""COMPUTED_VALUE"""),3.0) -> 3 | G32: 0 | H32: =(D32-G32) -> 3
A33: =IFERROR(__xludf.DUMMYFUNCTION("""COMPUTED_VALUE"""),"627") -> 627 | B33: =IFERROR(__xludf.DUMMYFUNCTION("""COMPUTED_VALUE"""),"FZ") -> FZ | C33: =IFERROR(__xludf.DUMMYFUNCTION("""COMPUTED_VALUE"""),"TRẮNG") -> TRẮNG | D33: =IFERROR(__xludf.DUMMYFUNCTION("""COMPUTED_VALUE"""),5.0) -> 5 | G33: 0 | H33: =(D33-G33) -> 5
A34: =IFERROR(__xludf.DUMMYFUNCTION("""COMPUTED_VALUE"""),"627") -> 627 | B34: =IFERROR(__xludf.DUMMYFUNCTION("""COMPUTED_VALUE"""),"FZ") -> FZ | C34: =IFERROR(__xludf.DUMMYFUNCTION("""COMPUTED_VALUE"""),"XÁM") -> XÁM | D34: =IFERROR(__xludf.DUMMYFUNCTION("""COMPUTED_VALUE"""),2.0) -> 2 | G34: 0 | H34: =(D34-G34) -> 2
A35: =IFERROR(__xludf.DUMMYFUNCTION("""COMPUTED_VALUE"""),"627") -> 627 | B35: =IFERROR(__xludf.DUMMYFUNCTION("""COMPUTED_VALUE"""),"FZ") -> FZ | C35: =IFERROR(__xludf.DUMMYFUNCTION("""COMPUTED_VALUE"""),"ĐEN") -> ĐEN | D35: =IFERROR(__xludf.DUMMYFUNCTION("""COMPUTED_VALUE"""),8.0) -> 8 | G35: 0 | H35: =(D35-G35) -> 8
A36: =IFERROR(__xludf.DUMMYFUNCTION("""COMPUTED_VALUE"""),"6612") -> 6612 | B36: =IFERROR(__xludf.DUMMYFUNCTION("""COMPUTED_VALUE"""),"FZ") -> FZ | C36: =IFERROR(__xludf.DUMMYFUNCTION("""COMPUTED_VALUE"""),"1") -> 1 | D36: =IFERROR(__xludf.DUMMYFUNCTION("""COMPUTED_VALUE"""),2.0) -> 2 | G36: 0 | H36: =(D36-G36) -> 2
A37: =IFERROR(__xludf.DUMMYFUNCTION("""COMPUTED_VALUE"""),"6612") -> 6612 | B37: =IFERROR(__xludf.DUMMYFUNCTION("""COMPUTED_VALUE"""),"FZ") -> FZ | C37: =IFERROR(__xludf.DUMMYFUNCTION("""COMPUTED_VALUE"""),"2") -> 2 | D37: =IFERROR(__xludf.DUMMYFUNCTION("""COMPUTED_VALUE"""),36.0) -> 36 | G37: 0 | H37: =(D37-G37) -> 36
A38: =IFERROR(__xludf.DUMMYFUNCTION("""COMPUTED_VALUE"""),"6612") -> 6612 | B38: =IFERROR(__xludf.DUMMYFUNCTION("""COMPUTED_VALUE"""),"FZ") -> FZ | C38: =IFERROR(__xludf.DUMMYFUNCTION("""COMPUTED_VALUE"""),"3") -> 3 | D38: =IFERROR(__xludf.DUMMYFUNCTION("""COMPUTED_VALUE"""),14.0) -> 14 | G38: 0 | H38: =(D38-G38) -> 14
A39: =IFERROR(__xludf.DUMMYFUNCTION("""COMPUTED_VALUE"""),"6612") -> 6612 | B39: =IFERROR(__xludf.DUMMYFUNCTION("""COMPUTED_VALUE"""),"FZ") -> FZ | C39: =IFERROR(__xludf.DUMMYFUNCTION("""COMPUTED_VALUE"""),"4") -> 4 | D39: =IFERROR(__xludf.DUMMYFUNCTION("""COMPUTED_VALUE"""),11.0) -> 11 | G39: 0 | H39: =(D39-G39) -> 11
A40: =IFERROR(__xludf.DUMMYFUNCTION("""COMPUTED_VALUE"""),"6612") -> 6612 | B40: =IFERROR(__xludf.DUMMYFUNCTION("""COMPUTED_VALUE"""),"FZ") -> FZ | C40: =IFERROR(__xludf.DUMMYFUNCTION("""COMPUTED_VALUE"""),"5") -> 5 | D40: =IFERROR(__xludf.DUMMYFUNCTION("""COMPUTED_VALUE"""),44.0) -> 44 | G40: 0 | H40: =(D40-G40) -> 44
A41: =IFERROR(__xludf.DUMMYFUNCTION("""COMPUTED_VALUE"""),"6612") -> 6612 | B41: =IFERROR(__xludf.DUMMYFUNCTION("""COMPUTED_VALUE"""),"FZ") -> FZ | C41: =IFERROR(__xludf.DUMMYFUNCTION("""COMPUTED_VALUE"""),"6") -> 6 | D41: =IFERROR(__xludf.DUMMYFUNCTION("""COMPUTED_VALUE"""),2.0) -> 2 | G41: 0 | H41: =(D41-G41) -> 2
A42: =IFERROR(__xludf.DUMMYFUNCTION("""COMPUTED_VALUE"""),"6612") -> 6612 | B42: =IFERROR(__xludf.DUMMYFUNCTION("""COMPUTED_VALUE"""),"FZ") -> FZ | C42: =IFERROR(__xludf.DUMMYFUNCTION("""COMPUTED_VALUE"""),"8") -> 8 | D42: =IFERROR(__xludf.DUMMYFUNCTION("""COMPUTED_VALUE"""),1.0) -> 1 | G42: 0 | H42: =(D42-G42) -> 1
A43: =IFERROR(__xludf.DUMMYFUNCTION("""COMPUTED_VALUE"""),"6612") -> 6612 | B43: =IFERROR(__xludf.DUMMYFUNCTION("""COMPUTED_VALUE"""),"FZ") -> FZ | C43: =IFERROR(__xludf.DUMMYFUNCTION("""COMPUTED_VALUE"""),"9") -> 9 | D43: =IFERROR(__xludf.DUMMYFUNCTION("""COMPUTED_VALUE"""),18.0) -> 18 | G43: 0 | H43: =(D43-G43) -> 18
A44: =IFERROR(__xludf.DUMMYFUNCTION("""COMPUTED_VALUE"""),"6612") -> 6612 | B44: =IFERROR(__xludf.DUMMYFUNCTION("""COMPUTED_VALUE"""),"FZ") -> FZ | C44: =IFERROR(__xludf.DUMMYFUNCTION("""COMPUTED_VALUE"""),"ĐEN") -> ĐEN | D44: =IFERROR(__xludf.DUMMYFUNCTION("""COMPUTED_VALUE"""),1.0) -> 1 | G44: 0 | H44: =(D44-G44) -> 1
A45: =IFERROR(__xludf.DUMMYFUNCTION("""COMPUTED_VALUE"""),"6866") -> 6866 | B45: =IFERROR(__xludf.DUMMYFUNCTION("""COMPUTED_VALUE"""),"FZ") -> FZ | C45: =IFERROR(__xludf.DUMMYFUNCTION("""COMPUTED_VALUE"""),"XANH") -> XANH | D45: =IFERROR(__xludf.DUMMYFUNCTION("""COMPUTED_VALUE"""),18.0) -> 18 | G45: 0 | H45: =(D45-G45) -> 18
A46: =IFERROR(__xludf.DUMMYFUNCTION("""COMPUTED_VALUE"""),"7137") -> 7137 | B46: =IFERROR(__xludf.DUMMYFUNCTION("""COMPUTED_VALUE"""),"S") -> S | C46: =IFERROR(__xludf.DUMMYFUNCTION("""COMPUTED_VALUE"""),"XANH THAN") -> XANH THAN | D46: =IFERROR(__xludf.DUMMYFUNCTION("""COMPUTED_VALUE"""),2.0) -> 2 | G46: 2 | H46: =(D46-G46) -> 0
A47: =IFERROR(__xludf.DUMMYFUNCTION("""COMPUTED_VALUE"""),"7249") -> 7249 | B47: =IFERROR(__xludf.DUMMYFUNCTION("""COMPUTED_VALUE"""),"M") -> M | C47: =IFERROR(__xludf.DUMMYFUNCTION("""COMPUTED_VALUE"""),"XANH NHẠT") -> XANH NHẠT | D47: =IFERROR(__xludf.DUMMYFUNCTION("""COMPUTED_VALUE"""),2.0) -> 2 | G47: 0 | H47: =(D47-G47) -> 2
A48: =IFERROR(__xludf.DUMMYFUNCTION("""COMPUTED_VALUE"""),"7249") -> 7249 | B48: =IFERROR(__xludf.DUMMYFUNCTION("""COMPUTED_VALUE"""),"M") -> M | C48: =IFERROR(__xludf.DUMMYFUNCTION("""COMPUTED_VALUE"""),"XANH THAN") -> XANH THAN | D48: =IFERROR(__xludf.DUMMYFUNCTION("""COMPUTED_VALUE"""),4.0) -> 4 | G48: 5 | H48: =(D48-G48) -> -1
A49: =IFERROR(__xludf.DUMMYFUNCTION("""COMPUTED_VALUE"""),"7249") -> 7249 | B49: =IFERROR(__xludf.DUMMYFUNCTION("""COMPUTED_VALUE"""),"S") -> S | C49: =IFERROR(__xludf.DUMMYFUNCTION("""COMPUTED_VALUE"""),"XANH THAN") -> XANH THAN | D49: =IFERROR(__xludf.DUMMYFUNCTION("""COMPUTED_VALUE"""),5.0) -> 5 | G49: 4 | H49: =(D49-G49) -> 1
A50: =IFERROR(__xludf.DUMMYFUNCTION("""COMPUTED_VALUE"""),"7307") -> 7307 | B50: =IFERROR(__xludf.DUMMYFUNCTION("""COMPUTED_VALUE"""),"M") -> M | C50: =IFERROR(__xludf.DUMMYFUNCTION("""COMPUTED_VALUE"""),"NÂU") -> NÂU | D50: =IFERROR(__xludf.DUMMYFUNCTION("""COMPUTED_VALUE"""),1.0) -> 1 | G50: 1 | H50: =(D50-G50) -> 0
A51: =IFERROR(__xludf.DUMMYFUNCTION("""COMPUTED_VALUE"""),"7307") -> 7307 | B51: =IFERROR(__xludf.DUMMYFUNCTION("""COMPUTED_VALUE"""),"S") -> S | C51: =IFERROR(__xludf.DUMMYFUNCTION("""COMPUTED_VALUE"""),"BE") -> BE | D51: =IFERROR(__xludf.DUMMYFUNCTION("""COMPUTED_VALUE"""),1.0) -> 1 | G51: 1 | H51: =(D51-G51) -> 0
A52: =IFERROR(__xludf.DUMMYFUNCTION("""COMPUTED_VALUE"""),"7322") -> 7322 | B52: =IFERROR(__xludf.DUMMYFUNCTION("""COMPUTED_VALUE"""),"L") -> L | C52: =IFERROR(__xludf.DUMMYFUNCTION("""COMPUTED_VALUE"""),"XANH THAN") -> XANH THAN | D52: =IFERROR(__xludf.DUMMYFUNCTION("""COMPUTED_VALUE"""),2.0) -> 2 | G52: 2 | H52: =(D52-G52) -> 0
A53: =IFERROR(__xludf.DUMMYFUNCTION("""COMPUTED_VALUE"""),"7322") -> 7322 | B53: =IFERROR(__xludf.DUMMYFUNCTION("""COMPUTED_VALUE"""),"M") -> M | C53: =IFERROR(__xludf.DUMMYFUNCTION("""COMPUTED_VALUE"""),"XANH THAN") -> XANH THAN | D53: =IFERROR(__xludf.DUMMYFUNCTION("""COMPUTED_VALUE"""),3.0) -> 3 | G53: 3 | H53: =(D53-G53) -> 0
A54: =IFERROR(__xludf.DUMMYFUNCTION("""COMPUTED_VALUE"""),"7322") -> 7322 | B54: =IFERROR(__xludf.DUMMYFUNCTION("""COMPUTED_VALUE"""),"S") -> S | C54: =IFERROR(__xludf.DUMMYFUNCTION("""COMPUTED_VALUE"""),"XANH THAN") -> XANH THAN | D54: =IFERROR(__xludf.DUMMYFUNCTION("""COMPUTED_VALUE"""),5.0) -> 5 | G54: 5 | H54: =(D54-G54) -> 0
A55: =IFERROR(__xludf.DUMMYFUNCTION("""COMPUTED_VALUE"""),"7367") -> 7367 | B55: =IFERROR(__xludf.DUMMYFUNCTION("""COMPUTED_VALUE"""),"S") -> S | C55: =IFERROR(__xludf.DUMMYFUNCTION("""COMPUTED_VALUE"""),"NÂU") -> NÂU | D55: =IFERROR(__xludf.DUMMYFUNCTION("""COMPUTED_VALUE"""),1.0) -> 1 | G55: 0 | H55: =(D55-G55) -> 1
A56: =IFERROR(__xludf.DUMMYFUNCTION("""COMPUTED_VALUE"""),"7367") -> 7367 | B56: =IFERROR(__xludf.DUMMYFUNCTION("""COMPUTED_VALUE"""),"S") -> S | C56: =IFERROR(__xludf.DUMMYFUNCTION("""COMPUTED_VALUE"""),"TRẮNG") -> TRẮNG | D56: =IFERROR(__xludf.DUMMYFUNCTION("""COMPUTED_VALUE"""),2.0) -> 2 | G56: 0 | H56: =(D56-G56) -> 2
A57: =IFERROR(__xludf.DUMMYFUNCTION("""COMPUTED_VALUE"""),"7398") -> 7398 | B57: =IFERROR(__xludf.DUMMYFUNCTION("""COMPUTED_VALUE"""),"S") -> S | C57: =IFERROR(__xludf.DUMMYFUNCTION("""COMPUTED_VALUE"""),"HỒNG") -> HỒNG | D57: =IFERROR(__xludf.DUMMYFUNCTION("""COMPUTED_VALUE"""),2.0) -> 2 | G57: 2 | H57: =(D57-G57) -> 0
A58: =IFERROR(__xludf.DUMMYFUNCTION("""COMPUTED_VALUE"""),"7398") -> 7398 | B58: =IFERROR(__xludf.DUMMYFUNCTION("""COMPUTED_VALUE"""),"S") -> S | C58: =IFERROR(__xludf.DUMMYFUNCTION("""COMPUTED_VALUE"""),"TRẮNG") -> TRẮNG | D58: =IFERROR(__xludf.DUMMYFUNCTION("""COMPUTED_VALUE"""),1.0) -> 1 | G58: 1 | H58: =(D58-G58) -> 0
A59: =IFERROR(__xludf.DUMMYFUNCTION("""COMPUTED_VALUE"""),"7398") -> 7398 | B59: =IFERROR(__xludf.DUMMYFUNCTION("""COMPUTED_VALUE"""),"S") -> S | C59: =IFERROR(__xludf.DUMMYFUNCTION("""COMPUTED_VALUE"""),"XÁM") -> XÁM | D59: =IFERROR(__xludf.DUMMYFUNCTION("""COMPUTED_VALUE"""),1.0) -> 1 | G59: 1 | H59: =(D59-G59) -> 0
A60: =IFERROR(__xludf.DUMMYFUNCTION("""COMPUTED_VALUE"""),"7398") -> 7398 | B60: =IFERROR(__xludf.DUMMYFUNCTION("""COMPUTED_VALUE"""),"S") -> S | C60: =IFERROR(__xludf.DUMMYFUNCTION("""COMPUTED_VALUE"""),"ĐEN") -> ĐEN | D60: =IFERROR(__xludf.DUMMYFUNCTION("""COMPUTED_VALUE"""),2.0) -> 2 | G60: 2 | H60: =(D60-G60) -> 0
A61: =IFERROR(__xludf.DUMMYFUNCTION("""COMPUTED_VALUE"""),"7436") -> 7436 | B61: =IFERROR(__xludf.DUMMYFUNCTION("""COMPUTED_VALUE"""),"M") -> M | C61: =IFERROR(__xludf.DUMMYFUNCTION("""COMPUTED_VALUE"""),"XANH THAN") -> XANH THAN | D61: =IFERROR(__xludf.DUMMYFUNCTION("""COMPUTED_VALUE"""),3.0) -> 3 | G61: 3 | H61: =(D61-G61) -> 0
A62: =IFERROR(__xludf.DUMMYFUNCTION("""COMPUTED_VALUE"""),"7436") -> 7436 | B62: =IFERROR(__xludf.DUMMYFUNCTION("""COMPUTED_VALUE"""),"S") -> S | C62: =IFERROR(__xludf.DUMMYFUNCTION("""COMPUTED_VALUE"""),"XANH THAN") -> XANH THAN | D62: =IFERROR(__xludf.DUMMYFUNCTION("""COMPUTED_VALUE"""),3.0) -> 3 | G62: 3 | H62: =(D62-G62) -> 0
A63: =IFERROR(__xludf.DUMMYFUNCTION("""COMPUTED_VALUE"""),"7458") -> 7458 | B63: =IFERROR(__xludf.DUMMYFUNCTION("""COMPUTED_VALUE"""),"M") -> M | C63: =IFERROR(__xludf.DUMMYFUNCTION("""COMPUTED_VALUE"""),"ĐEN") -> ĐEN | D63: =IFERROR(__xludf.DUMMYFUNCTION("""COMPUTED_VALUE"""),3.0) -> 3 | G63: 3 | H63: =(D63-G63) -> 0
A64: =IFERROR(__xludf.DUMMYFUNCTION("""COMPUTED_VALUE"""),"7458") -> 7458 | B64: =IFERROR(__xludf.DUMMYFUNCTION("""COMPUTED_VALUE"""),"S") -> S | C64: =IFERROR(__xludf.DUMMYFUNCTION("""COMPUTED_VALUE"""),"ĐEN") -> ĐEN | D64: =IFERROR(__xludf.DUMMYFUNCTION("""COMPUTED_VALUE"""),1.0) -> 1 | G64: 1 | H64: =(D64-G64) -> 0
A65: =IFERROR(__xludf.DUMMYFUNCTION("""COMPUTED_VALUE"""),"7739") -> 7739 | B65: =IFERROR(__xludf.DUMMYFUNCTION("""COMPUTED_VALUE"""),"M") -> M | C65: =IFERROR(__xludf.DUMMYFUNCTION("""COMPUTED_VALUE"""),"NÂU") -> NÂU | D65: =IFERROR(__xludf.DUMMYFUNCTION("""COMPUTED_VALUE"""),3.0) -> 3 | G65: 3 | H65: =(D65-G65) -> 0
A66: =IFERROR(__xludf.DUMMYFUNCTION("""COMPUTED_VALUE"""),"7739") -> 7739 | B66: =IFERROR(__xludf.DUMMYFUNCTION("""COMPUTED_VALUE"""),"S") -> S | C66: =IFERROR(__xludf.DUMMYFUNCTION("""COMPUTED_VALUE"""),"NÂU") -> NÂU | D66: =IFERROR(__xludf.DUMMYFUNCTION("""COMPUTED_VALUE"""),3.0) -> 3 | G66: 3 | H66: =(D66-G66) -> 0
A67: =IFERROR(__xludf.DUMMYFUNCTION("""COMPUTED_VALUE"""),"7739") -> 7739 | B67: =IFERROR(__xludf.DUMMYFUNCTION("""COMPUTED_VALUE"""),"S") -> S | C67: =IFERROR(__xludf.DUMMYFUNCTION("""COMPUTED_VALUE"""),"ĐEN") -> ĐEN | D67: =IFERROR(__xludf.DUMMYFUNCTION("""COMPUTED_VALUE"""),1.0) -> 1 | G67: 1 | H67: =(D67-G67) -> 0
A68: =IFERROR(__xludf.DUMMYFUNCTION("""COMPUTED_VALUE"""),"7859") -> 7859 | B68: =IFERROR(__xludf.DUMMYFUNCTION("""COMPUTED_VALUE"""),"FZ") -> FZ | C68: =IFERROR(__xludf.DUMMYFUNCTION("""COMPUTED_VALUE"""),"BE") -> BE | D68: =IFERROR(__xludf.DUMMYFUNCTION("""COMPUTED_VALUE"""),5.0) -> 5 | G68: 5 | H68: =(D68-G68) -> 0
A69: =IFERROR(__xludf.DUMMYFUNCTION("""COMPUTED_VALUE"""),"7859") -> 7859 | B69: =IFERROR(__xludf.DUMMYFUNCTION("""COMPUTED_VALUE"""),"FZ") -> FZ | C69: =IFERROR(__xludf.DUMMYFUNCTION("""COMPUTED_VALUE"""),"HỒNG") -> HỒNG | D69: =IFERROR(__xludf.DUMMYFUNCTION("""COMPUTED_VALUE"""),7.0) -> 7 | G69: 7 | H69: =(D69-G69) -> 0
A70: =IFERROR(__xludf.DUMMYFUNCTION("""COMPUTED_VALUE"""),"7910") -> 7910 | B70: =IFERROR(__xludf.DUMMYFUNCTION("""COMPUTED_VALUE"""),"M") -> M | C70: =IFERROR(__xludf.DUMMYFUNCTION("""COMPUTED_VALUE"""),"TRẮNG") -> TRẮNG | D70: =IFERROR(__xludf.DUMMYFUNCTION("""COMPUTED_VALUE"""),1.0) -> 1 | G70: 1 | H70: =(D70-G70) -> 0
A71: =IFERROR(__xludf.DUMMYFUNCTION("""COMPUTED_VALUE"""),"7910") -> 7910 | B71: =IFERROR(__xludf.DUMMYFUNCTION("""COMPUTED_VALUE"""),"S") -> S | C71: =IFERROR(__xludf.DUMMYFUNCTION("""COMPUTED_VALUE"""),"NÂU") -> NÂU | D71: =IFERROR(__xludf.DUMMYFUNCTION("""COMPUTED_VALUE"""),1.0) -> 1 | G71: 1 | H71: =(D71-G71) -> 0
A72: =IFERROR(__xludf.DUMMYFUNCTION("""COMPUTED_VALUE"""),"7910") -> 7910 | B72: =IFERROR(__xludf.DUMMYFUNCTION("""COMPUTED_VALUE"""),"S") -> S | C72: =IFERROR(__xludf.DUMMYFUNCTION("""COMPUTED_VALUE"""),"ĐEN") -> ĐEN | D72: =IFERROR(__xludf.DUMMYFUNCTION("""COMPUTED_VALUE"""),1.0) -> 1 | G72: 1 | H72: =(D72-G72) -> 0
A73: =IFERROR(__xludf.DUMMYFUNCTION("""COMPUTED_VALUE"""),"7957") -> 7957 | B73: =IFERROR(__xludf.DUMMYFUNCTION("""COMPUTED_VALUE"""),"M") -> M | C73: =IFERROR(__xludf.DUMMYFUNCTION("""COMPUTED_VALUE"""),"TRẮNG") -> TRẮNG | D73: =IFERROR(__xludf.DUMMYFUNCTION("""COMPUTED_VALUE"""),1.0) -> 1 | G73: 0 | H73: =(D73-G73) -> 1
A74: =IFERROR(__xludf.DUMMYFUNCTION("""COMPUTED_VALUE"""),"7957") -> 7957 | B74: =IFERROR(__xludf.DUMMYFUNCTION("""COMPUTED_VALUE"""),"M") -> M | C74: =IFERROR(__xludf.DUMMYFUNCTION("""COMPUTED_VALUE"""),"XÁM") -> XÁM | D74: =IFERROR(__xludf.DUMMYFUNCTION("""COMPUTED_VALUE"""),4.0) -> 4 | G74: 2 | H74: =(D74-G74) -> 2
A75: =IFERROR(__xludf.DUMMYFUNCTION("""COMPUTED_VALUE"""),"7957") -> 7957 | B75: =IFERROR(__xludf.DUMMYFUNCTION("""COMPUTED_VALUE"""),"M") -> M | C75: =IFERROR(__xludf.DUMMYFUNCTION("""COMPUTED_VALUE"""),"ĐEN") -> ĐEN | D75: =IFERROR(__xludf.DUMMYFUNCTION("""COMPUTED_VALUE"""),6.0) -> 6 | G75: 4 | H75: =(D75-G75) -> 2
A76: =IFERROR(__xludf.DUMMYFUNCTION("""COMPUTED_VALUE"""),"7957") -> 7957 | B76: =IFERROR(__xludf.DUMMYFUNCTION("""COMPUTED_VALUE"""),"S") -> S | C76: =IFERROR(__xludf.DUMMYFUNCTION("""COMPUTED_VALUE"""),"BE") -> BE | D76: =IFERROR(__xludf.DUMMYFUNCTION("""COMPUTED_VALUE"""),2.0) -> 2 | G76: 0 | H76: =(D76-G76) -> 2
A77: =IFERROR(__xludf.DUMMYFUNCTION("""COMPUTED_VALUE"""),"7957") -> 7957 | B77: =IFERROR(__xludf.DUMMYFUNCTION("""COMPUTED_VALUE"""),"S") -> S | C77: =IFERROR(__xludf.DUMMYFUNCTION("""COMPUTED_VALUE"""),"TRẮNG") -> TRẮNG | D77: =IFERROR(__xludf.DUMMYFUNCTION("""COMPUTED_VALUE"""),2.0) -> 2 | G77: 2 | H77: =(D77-G77) -> 0
A78: =IFERROR(__xludf.DUMMYFUNCTION("""COMPUTED_VALUE"""),"7957") -> 7957 | B78: =IFERROR(__xludf.DUMMYFUNCTION("""COMPUTED_VALUE"""),"S") -> S | C78: =IFERROR(__xludf.DUMMYFUNCTION("""COMPUTED_VALUE"""),"XÁM") -> XÁM | D78: =IFERROR(__xludf.DUMMYFUNCTION("""COMPUTED_VALUE"""),2.0) -> 2 | G78: 1 | H78: =(D78-G78) -> 1
A79: =IFERROR(__xludf.DUMMYFUNCTION("""COMPUTED_VALUE"""),"7957") -> 7957 | B79: =IFERROR(__xludf.DUMMYFUNCTION("""COMPUTED_VALUE"""),"S") -> S | C79: =IFERROR(__xludf.DUMMYFUNCTION("""COMPUTED_VALUE"""),"ĐEN") -> ĐEN | D79: =IFERROR(__xludf.DUMMYFUNCTION("""COMPUTED_VALUE"""),5.0) -> 5 | G79: 4 | H79: =(D79-G79) -> 1
A80: =IFERROR(__xludf.DUMMYFUNCTION("""COMPUTED_VALUE"""),"8012") -> 8012 | B80: =IFERROR(__xludf.DUMMYFUNCTION("""COMPUTED_VALUE"""),"FZ") -> FZ | C80: =IFERROR(__xludf.DUMMYFUNCTION("""COMPUTED_VALUE"""),"NÂU") -> NÂU | D80: =IFERROR(__xludf.DUMMYFUNCTION("""COMPUTED_VALUE"""),4.0) -> 4 | G80: 0 | H80: =(D80-G80) -> 4
A81: =IFERROR(__xludf.DUMMYFUNCTION("""COMPUTED_VALUE"""),"8012") -> 8012 | B81: =IFERROR(__xludf.DUMMYFUNCTION("""COMPUTED_VALUE"""),"FZ") -> FZ | C81: =IFERROR(__xludf.DUMMYFUNCTION("""COMPUTED_VALUE"""),"XANH") -> XANH | D81: =IFERROR(__xludf.DUMMYFUNCTION("""COMPUTED_VALUE"""),5.0) -> 5 | G81: 0 | H81: =(D81-G81) -> 5
A82: =IFERROR(__xludf.DUMMYFUNCTION("""COMPUTED_VALUE"""),"8012") -> 8012 | B82: =IFERROR(__xludf.DUMMYFUNCTION("""COMPUTED_VALUE"""),"FZ") -> FZ | C82: =IFERROR(__xludf.DUMMYFUNCTION("""COMPUTED_VALUE"""),"XANH THAN") -> XANH THAN | D82: =IFERROR(__xludf.DUMMYFUNCTION("""COMPUTED_VALUE"""),1.0) -> 1 | G82: 0 | H82: =(D82-G82) -> 1
A83: =IFERROR(__xludf.DUMMYFUNCTION("""COMPUTED_VALUE"""),"8116") -> 8116 | B83: =IFERROR(__xludf.DUMMYFUNCTION("""COMPUTED_VALUE"""),"L") -> L | C83: =IFERROR(__xludf.DUMMYFUNCTION("""COMPUTED_VALUE"""),"XANH THAN") -> XANH THAN | D83: =IFERROR(__xludf.DUMMYFUNCTION("""COMPUTED_VALUE"""),1.0) -> 1 | G83: 0 | H83: =(D83-G83) -> 1
A84: =IFERROR(__xludf.DUMMYFUNCTION("""COMPUTED_VALUE"""),"8116") -> 8116 | B84: =IFERROR(__xludf.DUMMYFUNCTION("""COMPUTED_VALUE"""),"M") -> M | C84: =IFERROR(__xludf.DUMMYFUNCTION("""COMPUTED_VALUE"""),"XANH THAN") -> XANH THAN | D84: =IFERROR(__xludf.DUMMYFUNCTION("""COMPUTED_VALUE"""),2.0) -> 2 | G84: 0 | H84: =(D84-G84) -> 2
A85: =IFERROR(__xludf.DUMMYFUNCTION("""COMPUTED_VALUE"""),"8116") -> 8116 | B85: =IFERROR(__xludf.DUMMYFUNCTION("""COMPUTED_VALUE"""),"S") -> S | C85: =IFERROR(__xludf.DUMMYFUNCTION("""COMPUTED_VALUE"""),"TRẮNG") -> TRẮNG | D85: =IFERROR(__xludf.DUMMYFUNCTION("""COMPUTED_VALUE"""),4.0) -> 4 | G85: 0 | H85: =(D85-G85) -> 4
A86: =IFERROR(__xludf.DUMMYFUNCTION("""COMPUTED_VALUE"""),"8116") -> 8116 | B86: =IFERROR(__xludf.DUMMYFUNCTION("""COMPUTED_VALUE"""),"S") -> S | C86: =IFERROR(__xludf.DUMMYFUNCTION("""COMPUTED_VALUE"""),"XANH THAN") -> XANH THAN | D86: =IFERROR(__xludf.DUMMYFUNCTION("""COMPUTED_VALUE"""),2.0) -> 2 | G86: 0 | H86: =(D86-G86) -> 2
A87: =IFERROR(__xludf.DUMMYFUNCTION("""COMPUTED_VALUE"""),"81813") -> 81813 | B87: =IFERROR(__xludf.DUMMYFUNCTION("""COMPUTED_VALUE"""),"FZ") -> FZ | C87: =IFERROR(__xludf.DUMMYFUNCTION("""COMPUTED_VALUE"""),"HỒNG") -> HỒNG | D87: =IFERROR(__xludf.DUMMYFUNCTION("""COMPUTED_VALUE"""),16.0) -> 16 | G87: 14 | H87: =(D87-G87) -> 2
A88: =IFERROR(__xludf.DUMMYFUNCTION("""COMPUTED_VALUE"""),"81813") -> 81813 | B88: =IFERROR(__xludf.DUMMYFUNCTION("""COMPUTED_VALUE"""),"FZ") -> FZ | C88: =IFERROR(__xludf.DUMMYFUNCTION("""COMPUTED_VALUE"""),"TRẮNG") -> TRẮNG | D88: =IFERROR(__xludf.DUMMYFUNCTION("""COMPUTED_VALUE"""),10.0) -> 10 | G88: 6 | H88: =(D88-G88) -> 4
A89: =IFERROR(__xludf.DUMMYFUNCTION("""COMPUTED_VALUE"""),"81813") -> 81813 | B89: =IFERROR(__xludf.DUMMYFUNCTION("""COMPUTED_VALUE"""),"FZ") -> FZ | C89: =IFERROR(__xludf.DUMMYFUNCTION("""COMPUTED_VALUE"""),"VÀNG") -> VÀNG | D89: =IFERROR(__xludf.DUMMYFUNCTION("""COMPUTED_VALUE"""),6.0) -> 6 | G89: 4 | H89: =(D89-G89) -> 2
A90: =IFERROR(__xludf.DUMMYFUNCTION("""COMPUTED_VALUE"""),"81813") -> 81813 | B90: =IFERROR(__xludf.DUMMYFUNCTION("""COMPUTED_VALUE"""),"FZ") -> FZ | C90: =IFERROR(__xludf.DUMMYFUNCTION("""COMPUTED_VALUE"""),"XANH NHẠT") -> XANH NHẠT | D90: =IFERROR(__xludf.DUMMYFUNCTION("""COMPUTED_VALUE"""),3.0) -> 3 | G90: 1 | H90: =(D90-G90) -> 2
A91: =IFERROR(__xludf.DUMMYFUNCTION("""COMPUTED_VALUE"""),"81813") -> 81813 | B91: =IFERROR(__xludf.DUMMYFUNCTION("""COMPUTED_VALUE"""),"FZ") -> FZ | C91: =IFERROR(__xludf.DUMMYFUNCTION("""COMPUTED_VALUE"""),"XÁM") -> XÁM | D91: =IFERROR(__xludf.DUMMYFUNCTION("""COMPUTED_VALUE"""),3.0) -> 3 | G91: 3 | H91: =(D91-G91) -> 0
A92: =IFERROR(__xludf.DUMMYFUNCTION("""COMPUTED_VALUE"""),"81813") -> 81813 | B92: =IFERROR(__xludf.DUMMYFUNCTION("""COMPUTED_VALUE"""),"FZ") -> FZ | C92: =IFERROR(__xludf.DUMMYFUNCTION("""COMPUTED_VALUE"""),"ĐEN") -> ĐEN | D92: =IFERROR(__xludf.DUMMYFUNCTION("""COMPUTED_VALUE"""),6.0) -> 6 | G92: 4 | H92: =(D92-G92) -> 2
A93: =IFERROR(__xludf.DUMMYFUNCTION("""COMPUTED_VALUE"""),"81813") -> 81813 | B93: =IFERROR(__xludf.DUMMYFUNCTION("""COMPUTED_VALUE"""),"FZ") -> FZ | C93: =IFERROR(__xludf.DUMMYFUNCTION("""COMPUTED_VALUE"""),"ĐỎ") -> ĐỎ | D93: =IFERROR(__xludf.DUMMYFUNCTION("""COMPUTED_VALUE"""),1.0) -> 1 | G93: 1 | H93: =(D93-G93) -> 0
A94: =IFERROR(__xludf.DUMMYFUNCTION("""COMPUTED_VALUE"""),"8319") -> 8319 | B94: =IFERROR(__xludf.DUMMYFUNCTION("""COMPUTED_VALUE"""),"L") -> L | C94: =IFERROR(__xludf.DUMMYFUNCTION("""COMPUTED_VALUE"""),"XANH THAN") -> XANH THAN | D94: =IFERROR(__xludf.DUMMYFUNCTION("""COMPUTED_VALUE"""),1.0) -> 1 | G94: 0 | H94: =(D94-G94) -> 1
A95: =IFERROR(__xludf.DUMMYFUNCTION("""COMPUTED_VALUE"""),"8319") -> 8319 | B95: =IFERROR(__xludf.DUMMYFUNCTION("""COMPUTED_VALUE"""),"M") -> M | C95: =IFERROR(__xludf.DUMMYFUNCTION("""COMPUTED_VALUE"""),"XANH THAN") -> XANH THAN | D95: =IFERROR(__xludf.DUMMYFUNCTION("""COMPUTED_VALUE"""),12.0) -> 12 | G95: 5 | H95: =(D95-G95) -> 7
A96: =IFERROR(__xludf.DUMMYFUNCTION("""COMPUTED_VALUE"""),"8319") -> 8319 | B96: =IFERROR(__xludf.DUMMYFUNCTION("""COMPUTED_VALUE"""),"S") -> S | C96: =IFERROR(__xludf.DUMMYFUNCTION("""COMPUTED_VALUE"""),"XANH THAN") -> XANH THAN | D96: =IFERROR(__xludf.DUMMYFUNCTION("""COMPUTED_VALUE"""),19.0) -> 19 | G96: 10 | H96: =(D96-G96) -> 9
A97: =IFERROR(__xludf.DUMMYFUNCTION("""COMPUTED_VALUE"""),"8321") -> 8321 | B97: =IFERROR(__xludf.DUMMYFUNCTION("""COMPUTED_VALUE"""),"FZ") -> FZ | C97: =IFERROR(__xludf.DUMMYFUNCTION("""COMPUTED_VALUE"""),"NÂU") -> NÂU | D97: =IFERROR(__xludf.DUMMYFUNCTION("""COMPUTED_VALUE"""),18.0) -> 18 | G97: 0 | H97: =(D97-G97) -> 18
A98: =IFERROR(__xludf.DUMMYFUNCTION("""COMPUTED_VALUE"""),"8321") -> 8321 | B98: =IFERROR(__xludf.DUMMYFUNCTION("""COMPUTED_VALUE"""),"FZ") -> FZ | C98: =IFERROR(__xludf.DUMMYFUNCTION("""COMPUTED_VALUE"""),"NÂU NHẠT") -> NÂU NHẠT | D98: =IFERROR(__xludf.DUMMYFUNCTION("""COMPUTED_VALUE"""),7.0) -> 7 | G98: 0 | H98: =(D98-G98) -> 7
A99: =IFERROR(__xludf.DUMMYFUNCTION("""COMPUTED_VALUE"""),"8321") -> 8321 | B99: =IFERROR(__xludf.DUMMYFUNCTION("""COMPUTED_VALUE"""),"FZ") -> FZ | C99: =IFERROR(__xludf.DUMMYFUNCTION("""COMPUTED_VALUE"""),"XANH THAN") -> XANH THAN | D99: =IFERROR(__xludf.DUMMYFUNCTION("""COMPUTED_VALUE"""),11.0) -> 11 | G99: 0 | H99: =(D99-G99) -> 11
A100: =IFERROR(__xludf.DUMMYFUNCTION("""COMPUTED_VALUE"""),"8436") -> 8436 | B100: =IFERROR(__xludf.DUMMYFUNCTION("""COMPUTED_VALUE"""),"M") -> M | C100: =IFERROR(__xludf.DUMMYFUNCTION("""COMPUTED_VALUE"""),"TRẮNG") -> TRẮNG | D100: =IFERROR(__xludf.DUMMYFUNCTION("""COMPUTED_VALUE"""),7.0) -> 7 | G100: 0 | H100: =(D100-G100) -> 7
...

Sheet DATA_ĐÃ_ĐẶT
A1: Mã SP | B1: SIZE | C1: COLOR | D1: Đã đặt
A2: 5344 | B2: L | C2: XANH THAN | D2: 1
A3: 5344 | B3: M | C3: XANH THAN | D3: 2
A4: 5344 | B4: S | C4: XANH THAN | D4: 6
A5: 7137 | B5: S | C5: XANH THAN | D5: 2
A6: 7249 | B6: M | C6: XANH THAN | D6: 5
A7: 7249 | B7: S | C7: XANH THAN | D7: 4
A8: 7307 | B8: M | C8: NÂU | D8: 1
A9: 7307 | B9: S | C9: BE | D9: 1
A10: 7322 | B10: L | C10: XANH THAN | D10: 2
A11: 7322 | B11: M | C11: XANH THAN | D11: 3
A12: 7322 | B12: S | C12: XANH THAN | D12: 5
A13: 7398 | B13: S | C13: HỒNG | D13: 2
... A93: M001 | B93: 40 | C93: BE | D93: 2
A94: M006 | B94: FZ | C94: BE | D94: 20 | G94: 0 | H94: =(D94-G94) -> 20
A95: M006 | B95: FZ | C95: TRẮNG | D95: 50 | G95: 0 | H95: =(D95-G95) -> 50
A96: M006 | B96: FZ | C96: XÁM | D96: 25 | G96: 0 | H96: =(D96-G96) -> 25
A97: M006 | B97: FZ | C97: ĐEN | D97: 45 | G97: 0 | H97: =(D97-G97) -> 45
A98: M004 | B98: FZ | C98: HỒNG | D98: 5
A99: M004 | B99: FZ | C99: VÀNG | D99: 1
A100: M004 | B100: FZ | C100: XANH NHẠT | D100: 6
A101: M005 | B101: 35 | C101: NÂU | D101: 2
A102: M005 | B102: 36 | C102: NÂU | D102: 1
A103: M005 | B103: 37 | C103: BE | D103: 1
A104: M005 | B104: 37 | C104: NÂU | D104: 1
A105: M005 | B105: 38 | C105: NÂU | D105: 1
A106: 5709 | B106: L | C106: XANH NHẠT | D106: 2
A107: 5709 | B107: M | C107: XANH NHẠT | D107: 5
A108: 5709 | B108: S | C108: XANH NHẠT | D108: 5
A109: 81813 | B109: FZ | C109: HỒNG | D109: 14
... A126: 9140 | B126: S | C126: ĐỎ | D126: 2
